package com.tencent.tencentmap.mapsdk.a;

import android.text.TextUtils;
import java.net.MalformedURLException;
import java.net.URL;
import org.apache.http.impl.client.DefaultHttpClient;

public final class ez
  implements eu
{
  private DefaultHttpClient a = null;
  
  private static ew a(boolean paramBoolean, String paramString, byte[] paramArrayOfByte)
  {
    try
    {
      URL localURL = new URL(fz.c(paramString));
      int i = localURL.getPort();
      fb localfb = new fb(localURL.getHost(), new int[] { i });
      localfb.a(paramBoolean);
      if ((!TextUtils.isEmpty(paramString)) && (paramString.toLowerCase().startsWith("https://"))) {
        localfb.b(true);
      }
      localfb.a(localURL.getFile());
      localfb.a(paramArrayOfByte);
      localfb.b(paramString);
      return localfb;
    }
    catch (MalformedURLException paramArrayOfByte)
    {
      throw new ff("url format error:" + paramString);
    }
  }
  
  /* Error */
  private DefaultHttpClient a(fb paramfb)
  {
    // Byte code:
    //   0: aload_0
    //   1: getfield 14	com/tencent/tencentmap/mapsdk/a/ez:a	Lorg/apache/http/impl/client/DefaultHttpClient;
    //   4: ifnonnull +150 -> 154
    //   7: new 97	org/apache/http/params/BasicHttpParams
    //   10: dup
    //   11: invokespecial 98	org/apache/http/params/BasicHttpParams:<init>	()V
    //   14: astore 4
    //   16: aload 4
    //   18: iconst_0
    //   19: invokestatic 104	org/apache/http/client/params/HttpClientParams:setRedirecting	(Lorg/apache/http/params/HttpParams;Z)V
    //   22: aload_0
    //   23: new 106	org/apache/http/impl/client/DefaultHttpClient
    //   26: dup
    //   27: aload 4
    //   29: invokespecial 109	org/apache/http/impl/client/DefaultHttpClient:<init>	(Lorg/apache/http/params/HttpParams;)V
    //   32: putfield 14	com/tencent/tencentmap/mapsdk/a/ez:a	Lorg/apache/http/impl/client/DefaultHttpClient;
    //   35: aload_1
    //   36: invokevirtual 113	com/tencent/tencentmap/mapsdk/a/fb:p	()Z
    //   39: ifeq +230 -> 269
    //   42: invokestatic 118	java/security/KeyStore:getDefaultType	()Ljava/lang/String;
    //   45: invokestatic 122	java/security/KeyStore:getInstance	(Ljava/lang/String;)Ljava/security/KeyStore;
    //   48: astore 5
    //   50: aload 5
    //   52: aconst_null
    //   53: aconst_null
    //   54: invokevirtual 126	java/security/KeyStore:load	(Ljava/io/InputStream;[C)V
    //   57: new 128	com/tencent/tencentmap/mapsdk/a/fy
    //   60: dup
    //   61: aload 5
    //   63: aload_1
    //   64: invokevirtual 131	com/tencent/tencentmap/mapsdk/a/fb:n	()Ljava/lang/String;
    //   67: invokespecial 134	com/tencent/tencentmap/mapsdk/a/fy:<init>	(Ljava/security/KeyStore;Ljava/lang/String;)V
    //   70: astore_1
    //   71: aload_1
    //   72: new 136	org/apache/http/conn/ssl/AllowAllHostnameVerifier
    //   75: dup
    //   76: invokespecial 137	org/apache/http/conn/ssl/AllowAllHostnameVerifier:<init>	()V
    //   79: invokevirtual 143	org/apache/http/conn/ssl/SSLSocketFactory:setHostnameVerifier	(Lorg/apache/http/conn/ssl/X509HostnameVerifier;)V
    //   82: new 145	org/apache/http/conn/scheme/SchemeRegistry
    //   85: dup
    //   86: invokespecial 146	org/apache/http/conn/scheme/SchemeRegistry:<init>	()V
    //   89: astore 5
    //   91: aload 5
    //   93: new 148	org/apache/http/conn/scheme/Scheme
    //   96: dup
    //   97: ldc -106
    //   99: aload_1
    //   100: sipush 443
    //   103: invokespecial 153	org/apache/http/conn/scheme/Scheme:<init>	(Ljava/lang/String;Lorg/apache/http/conn/scheme/SocketFactory;I)V
    //   106: invokevirtual 157	org/apache/http/conn/scheme/SchemeRegistry:register	(Lorg/apache/http/conn/scheme/Scheme;)Lorg/apache/http/conn/scheme/Scheme;
    //   109: pop
    //   110: aload 5
    //   112: new 148	org/apache/http/conn/scheme/Scheme
    //   115: dup
    //   116: ldc -97
    //   118: invokestatic 165	org/apache/http/conn/scheme/PlainSocketFactory:getSocketFactory	()Lorg/apache/http/conn/scheme/PlainSocketFactory;
    //   121: bipush 80
    //   123: invokespecial 153	org/apache/http/conn/scheme/Scheme:<init>	(Ljava/lang/String;Lorg/apache/http/conn/scheme/SocketFactory;I)V
    //   126: invokevirtual 157	org/apache/http/conn/scheme/SchemeRegistry:register	(Lorg/apache/http/conn/scheme/Scheme;)Lorg/apache/http/conn/scheme/Scheme;
    //   129: pop
    //   130: aload_0
    //   131: new 106	org/apache/http/impl/client/DefaultHttpClient
    //   134: dup
    //   135: new 167	org/apache/http/impl/conn/tsccm/ThreadSafeClientConnManager
    //   138: dup
    //   139: aload 4
    //   141: aload 5
    //   143: invokespecial 170	org/apache/http/impl/conn/tsccm/ThreadSafeClientConnManager:<init>	(Lorg/apache/http/params/HttpParams;Lorg/apache/http/conn/scheme/SchemeRegistry;)V
    //   146: aload 4
    //   148: invokespecial 173	org/apache/http/impl/client/DefaultHttpClient:<init>	(Lorg/apache/http/conn/ClientConnectionManager;Lorg/apache/http/params/HttpParams;)V
    //   151: putfield 14	com/tencent/tencentmap/mapsdk/a/ez:a	Lorg/apache/http/impl/client/DefaultHttpClient;
    //   154: aload_0
    //   155: getfield 14	com/tencent/tencentmap/mapsdk/a/ez:a	Lorg/apache/http/impl/client/DefaultHttpClient;
    //   158: invokestatic 178	com/tencent/tencentmap/mapsdk/a/fw:a	(Lorg/apache/http/client/HttpClient;)V
    //   161: aload_0
    //   162: getfield 14	com/tencent/tencentmap/mapsdk/a/ez:a	Lorg/apache/http/impl/client/DefaultHttpClient;
    //   165: astore_1
    //   166: bipush 20
    //   168: istore_2
    //   169: invokestatic 181	com/tencent/tencentmap/mapsdk/a/fw:f	()Z
    //   172: ifeq +169 -> 341
    //   175: bipush 15
    //   177: istore_2
    //   178: bipush 15
    //   180: istore_3
    //   181: aload_1
    //   182: invokeinterface 187 1 0
    //   187: ldc -67
    //   189: iload_3
    //   190: sipush 1000
    //   193: imul
    //   194: invokestatic 195	java/lang/Integer:valueOf	(I)Ljava/lang/Integer;
    //   197: invokeinterface 201 3 0
    //   202: pop
    //   203: aload_1
    //   204: invokeinterface 187 1 0
    //   209: ldc -53
    //   211: iload_2
    //   212: sipush 1000
    //   215: imul
    //   216: invokestatic 195	java/lang/Integer:valueOf	(I)Ljava/lang/Integer;
    //   219: invokeinterface 201 3 0
    //   224: pop
    //   225: aload_0
    //   226: getfield 14	com/tencent/tencentmap/mapsdk/a/ez:a	Lorg/apache/http/impl/client/DefaultHttpClient;
    //   229: new 205	org/apache/http/impl/client/DefaultHttpRequestRetryHandler
    //   232: dup
    //   233: iconst_0
    //   234: iconst_0
    //   235: invokespecial 208	org/apache/http/impl/client/DefaultHttpRequestRetryHandler:<init>	(IZ)V
    //   238: invokevirtual 212	org/apache/http/impl/client/DefaultHttpClient:setHttpRequestRetryHandler	(Lorg/apache/http/client/HttpRequestRetryHandler;)V
    //   241: aload_0
    //   242: getfield 14	com/tencent/tencentmap/mapsdk/a/ez:a	Lorg/apache/http/impl/client/DefaultHttpClient;
    //   245: new 214	com/tencent/tencentmap/mapsdk/a/fa
    //   248: dup
    //   249: invokespecial 215	com/tencent/tencentmap/mapsdk/a/fa:<init>	()V
    //   252: invokevirtual 219	org/apache/http/impl/client/DefaultHttpClient:setKeepAliveStrategy	(Lorg/apache/http/conn/ConnectionKeepAliveStrategy;)V
    //   255: aload_0
    //   256: getfield 14	com/tencent/tencentmap/mapsdk/a/ez:a	Lorg/apache/http/impl/client/DefaultHttpClient;
    //   259: areturn
    //   260: astore_1
    //   261: aload_0
    //   262: aconst_null
    //   263: putfield 14	com/tencent/tencentmap/mapsdk/a/ez:a	Lorg/apache/http/impl/client/DefaultHttpClient;
    //   266: goto -112 -> 154
    //   269: new 145	org/apache/http/conn/scheme/SchemeRegistry
    //   272: dup
    //   273: invokespecial 146	org/apache/http/conn/scheme/SchemeRegistry:<init>	()V
    //   276: astore_1
    //   277: aload_1
    //   278: new 148	org/apache/http/conn/scheme/Scheme
    //   281: dup
    //   282: ldc -97
    //   284: invokestatic 165	org/apache/http/conn/scheme/PlainSocketFactory:getSocketFactory	()Lorg/apache/http/conn/scheme/PlainSocketFactory;
    //   287: bipush 80
    //   289: invokespecial 153	org/apache/http/conn/scheme/Scheme:<init>	(Ljava/lang/String;Lorg/apache/http/conn/scheme/SocketFactory;I)V
    //   292: invokevirtual 157	org/apache/http/conn/scheme/SchemeRegistry:register	(Lorg/apache/http/conn/scheme/Scheme;)Lorg/apache/http/conn/scheme/Scheme;
    //   295: pop
    //   296: aload_1
    //   297: new 148	org/apache/http/conn/scheme/Scheme
    //   300: dup
    //   301: ldc -106
    //   303: invokestatic 165	org/apache/http/conn/scheme/PlainSocketFactory:getSocketFactory	()Lorg/apache/http/conn/scheme/PlainSocketFactory;
    //   306: bipush 80
    //   308: invokespecial 153	org/apache/http/conn/scheme/Scheme:<init>	(Ljava/lang/String;Lorg/apache/http/conn/scheme/SocketFactory;I)V
    //   311: invokevirtual 157	org/apache/http/conn/scheme/SchemeRegistry:register	(Lorg/apache/http/conn/scheme/Scheme;)Lorg/apache/http/conn/scheme/Scheme;
    //   314: pop
    //   315: aload_0
    //   316: new 106	org/apache/http/impl/client/DefaultHttpClient
    //   319: dup
    //   320: new 167	org/apache/http/impl/conn/tsccm/ThreadSafeClientConnManager
    //   323: dup
    //   324: aload 4
    //   326: aload_1
    //   327: invokespecial 170	org/apache/http/impl/conn/tsccm/ThreadSafeClientConnManager:<init>	(Lorg/apache/http/params/HttpParams;Lorg/apache/http/conn/scheme/SchemeRegistry;)V
    //   330: aload 4
    //   332: invokespecial 173	org/apache/http/impl/client/DefaultHttpClient:<init>	(Lorg/apache/http/conn/ClientConnectionManager;Lorg/apache/http/params/HttpParams;)V
    //   335: putfield 14	com/tencent/tencentmap/mapsdk/a/ez:a	Lorg/apache/http/impl/client/DefaultHttpClient;
    //   338: goto -184 -> 154
    //   341: invokestatic 222	com/tencent/tencentmap/mapsdk/a/fw:h	()Z
    //   344: ifeq +12 -> 356
    //   347: bipush 15
    //   349: istore_2
    //   350: bipush 15
    //   352: istore_3
    //   353: goto -172 -> 181
    //   356: invokestatic 225	com/tencent/tencentmap/mapsdk/a/fw:g	()Z
    //   359: ifeq +16 -> 375
    //   362: bipush 10
    //   364: istore_2
    //   365: bipush 15
    //   367: istore_3
    //   368: goto -187 -> 181
    //   371: astore_1
    //   372: goto -117 -> 255
    //   375: bipush 10
    //   377: istore_3
    //   378: goto -197 -> 181
    // Local variable table:
    //   start	length	slot	name	signature
    //   0	381	0	this	ez
    //   0	381	1	paramfb	fb
    //   168	197	2	i	int
    //   180	198	3	j	int
    //   14	317	4	localBasicHttpParams	org.apache.http.params.BasicHttpParams
    //   48	94	5	localObject	Object
    // Exception table:
    //   from	to	target	type
    //   42	154	260	java/lang/Exception
    //   241	255	371	java/lang/Throwable
  }
  
  private static boolean a(long paramLong)
  {
    if (fw.f()) {
      if (System.currentTimeMillis() - paramLong <= 6000L) {}
    }
    do
    {
      do
      {
        return true;
        return false;
        if (!fw.h()) {
          break;
        }
      } while (System.currentTimeMillis() - paramLong > 10000L);
      return false;
    } while (System.currentTimeMillis() - paramLong > 10000L);
    return false;
  }
  
  /* Error */
  private fc b(fb paramfb)
  {
    // Byte code:
    //   0: new 241	com/tencent/tencentmap/mapsdk/a/fc
    //   3: dup
    //   4: invokespecial 242	com/tencent/tencentmap/mapsdk/a/fc:<init>	()V
    //   7: astore 23
    //   9: new 244	com/tencent/tencentmap/mapsdk/a/ey
    //   12: dup
    //   13: aload_1
    //   14: invokespecial 247	com/tencent/tencentmap/mapsdk/a/ey:<init>	(Lcom/tencent/tencentmap/mapsdk/a/fb;)V
    //   17: astore 40
    //   19: aload 40
    //   21: getfield 250	com/tencent/tencentmap/mapsdk/a/ey:c	Ljava/util/List;
    //   24: astore 41
    //   26: aload 40
    //   28: getfield 253	com/tencent/tencentmap/mapsdk/a/ey:b	Ljava/lang/String;
    //   31: astore 42
    //   33: aload 41
    //   35: invokeinterface 258 1 0
    //   40: istore 8
    //   42: aload 41
    //   44: invokeinterface 258 1 0
    //   49: istore 9
    //   51: iconst_0
    //   52: istore 4
    //   54: ldc_w 260
    //   57: astore 20
    //   59: iconst_0
    //   60: istore 14
    //   62: invokestatic 232	java/lang/System:currentTimeMillis	()J
    //   65: aload_1
    //   66: invokevirtual 263	com/tencent/tencentmap/mapsdk/a/fb:q	()J
    //   69: lsub
    //   70: l2i
    //   71: istore 10
    //   73: iconst_0
    //   74: istore_3
    //   75: ldc_w 260
    //   78: astore 22
    //   80: iconst_0
    //   81: istore 5
    //   83: iload 4
    //   85: aload_1
    //   86: invokevirtual 266	com/tencent/tencentmap/mapsdk/a/fb:j	()I
    //   89: if_icmpgt +7746 -> 7835
    //   92: iload_3
    //   93: ifne +7742 -> 7835
    //   96: invokestatic 232	java/lang/System:currentTimeMillis	()J
    //   99: lstore 16
    //   101: aload_1
    //   102: invokevirtual 269	com/tencent/tencentmap/mapsdk/a/fb:l	()Z
    //   105: ifeq +31 -> 136
    //   108: ldc_w 271
    //   111: ldc_w 273
    //   114: invokestatic 278	com/tencent/tencentmap/mapsdk/a/fx:c	(Ljava/lang/String;Ljava/lang/String;)V
    //   117: new 241	com/tencent/tencentmap/mapsdk/a/fc
    //   120: dup
    //   121: invokespecial 242	com/tencent/tencentmap/mapsdk/a/fc:<init>	()V
    //   124: astore 23
    //   126: aload 23
    //   128: bipush -20
    //   130: putfield 281	com/tencent/tencentmap/mapsdk/a/fc:a	I
    //   133: aload 23
    //   135: areturn
    //   136: new 241	com/tencent/tencentmap/mapsdk/a/fc
    //   139: dup
    //   140: invokespecial 242	com/tencent/tencentmap/mapsdk/a/fc:<init>	()V
    //   143: astore 33
    //   145: aload 33
    //   147: iload 4
    //   149: putfield 284	com/tencent/tencentmap/mapsdk/a/fc:i	I
    //   152: new 286	com/tencent/tencentmap/mapsdk/a/fd
    //   155: dup
    //   156: invokespecial 287	com/tencent/tencentmap/mapsdk/a/fd:<init>	()V
    //   159: astore 39
    //   161: aload 39
    //   163: aload 42
    //   165: putfield 290	com/tencent/tencentmap/mapsdk/a/fd:y	Ljava/lang/String;
    //   168: aload 39
    //   170: iload 10
    //   172: putfield 291	com/tencent/tencentmap/mapsdk/a/fd:i	I
    //   175: aload 39
    //   177: aload 40
    //   179: getfield 294	com/tencent/tencentmap/mapsdk/a/ey:a	Lcom/tencent/tencentmap/mapsdk/a/ep;
    //   182: putfield 296	com/tencent/tencentmap/mapsdk/a/fd:b	Lcom/tencent/tencentmap/mapsdk/a/ep;
    //   185: aconst_null
    //   186: astore 27
    //   188: aconst_null
    //   189: astore 37
    //   191: aconst_null
    //   192: astore 28
    //   194: aconst_null
    //   195: astore 38
    //   197: aconst_null
    //   198: astore 29
    //   200: aconst_null
    //   201: astore 35
    //   203: aconst_null
    //   204: astore 36
    //   206: iconst_0
    //   207: istore 13
    //   209: iload 4
    //   211: aload_1
    //   212: invokevirtual 266	com/tencent/tencentmap/mapsdk/a/fb:j	()I
    //   215: if_icmpne +6 -> 221
    //   218: iconst_1
    //   219: istore 13
    //   221: iload 4
    //   223: iload 9
    //   225: irem
    //   226: istore_2
    //   227: iload_2
    //   228: iload 8
    //   230: iconst_1
    //   231: isub
    //   232: if_icmpge +85 -> 317
    //   235: aload 20
    //   237: astore 26
    //   239: aload 22
    //   241: astore 25
    //   243: aload 29
    //   245: astore 24
    //   247: iload_3
    //   248: istore 6
    //   250: iload_3
    //   251: istore 7
    //   253: aload 39
    //   255: iconst_1
    //   256: putfield 300	com/tencent/tencentmap/mapsdk/a/fd:x	Z
    //   259: aload 20
    //   261: astore 26
    //   263: aload 22
    //   265: astore 25
    //   267: aload 29
    //   269: astore 24
    //   271: iload_3
    //   272: istore 6
    //   274: iload_3
    //   275: istore 7
    //   277: aload_1
    //   278: ldc_w 302
    //   281: aload_1
    //   282: invokevirtual 131	com/tencent/tencentmap/mapsdk/a/fb:n	()Ljava/lang/String;
    //   285: invokevirtual 304	com/tencent/tencentmap/mapsdk/a/fb:a	(Ljava/lang/String;Ljava/lang/String;)V
    //   288: aload 20
    //   290: astore 26
    //   292: aload 22
    //   294: astore 25
    //   296: aload 29
    //   298: astore 24
    //   300: iload_3
    //   301: istore 6
    //   303: iload_3
    //   304: istore 7
    //   306: aload_1
    //   307: ldc_w 306
    //   310: aload_1
    //   311: invokevirtual 131	com/tencent/tencentmap/mapsdk/a/fb:n	()Ljava/lang/String;
    //   314: invokevirtual 304	com/tencent/tencentmap/mapsdk/a/fb:a	(Ljava/lang/String;Ljava/lang/String;)V
    //   317: aload 20
    //   319: astore 26
    //   321: aload 22
    //   323: astore 25
    //   325: aload 29
    //   327: astore 24
    //   329: iload_3
    //   330: istore 6
    //   332: iload_3
    //   333: istore 7
    //   335: aload 41
    //   337: iload_2
    //   338: invokeinterface 310 2 0
    //   343: checkcast 312	com/tencent/tencentmap/mapsdk/a/ep
    //   346: astore 34
    //   348: aload 20
    //   350: astore 26
    //   352: aload 22
    //   354: astore 25
    //   356: aload 29
    //   358: astore 24
    //   360: iload_3
    //   361: istore 6
    //   363: iload_3
    //   364: istore 7
    //   366: aload 39
    //   368: aload 34
    //   370: putfield 313	com/tencent/tencentmap/mapsdk/a/fd:a	Lcom/tencent/tencentmap/mapsdk/a/ep;
    //   373: aload 20
    //   375: astore 26
    //   377: aload 22
    //   379: astore 25
    //   381: aload 29
    //   383: astore 24
    //   385: iload_3
    //   386: istore 6
    //   388: iload_3
    //   389: istore 7
    //   391: aload 39
    //   393: aload_1
    //   394: invokevirtual 315	com/tencent/tencentmap/mapsdk/a/fb:c	()Ljava/lang/String;
    //   397: putfield 317	com/tencent/tencentmap/mapsdk/a/fd:c	Ljava/lang/String;
    //   400: aload 20
    //   402: astore 26
    //   404: aload 22
    //   406: astore 25
    //   408: aload 29
    //   410: astore 24
    //   412: iload_3
    //   413: istore 6
    //   415: iload_3
    //   416: istore 7
    //   418: aload 39
    //   420: aload_1
    //   421: invokevirtual 113	com/tencent/tencentmap/mapsdk/a/fb:p	()Z
    //   424: putfield 320	com/tencent/tencentmap/mapsdk/a/fd:D	Z
    //   427: aload 20
    //   429: astore 26
    //   431: aload 22
    //   433: astore 25
    //   435: aload 29
    //   437: astore 24
    //   439: iload_3
    //   440: istore 6
    //   442: iload_3
    //   443: istore 7
    //   445: aload 39
    //   447: aload_1
    //   448: invokevirtual 266	com/tencent/tencentmap/mapsdk/a/fb:j	()I
    //   451: putfield 323	com/tencent/tencentmap/mapsdk/a/fd:u	I
    //   454: aload 20
    //   456: astore 26
    //   458: aload 22
    //   460: astore 25
    //   462: aload 29
    //   464: astore 24
    //   466: iload_3
    //   467: istore 6
    //   469: iload_3
    //   470: istore 7
    //   472: invokestatic 232	java/lang/System:currentTimeMillis	()J
    //   475: aload_1
    //   476: invokevirtual 263	com/tencent/tencentmap/mapsdk/a/fb:q	()J
    //   479: lsub
    //   480: aload_1
    //   481: invokevirtual 326	com/tencent/tencentmap/mapsdk/a/fb:o	()I
    //   484: i2l
    //   485: lcmp
    //   486: ifgt +11 -> 497
    //   489: iload_3
    //   490: istore_2
    //   491: iload 4
    //   493: iconst_1
    //   494: if_icmple +68 -> 562
    //   497: aload 20
    //   499: astore 26
    //   501: aload 22
    //   503: astore 25
    //   505: aload 29
    //   507: astore 24
    //   509: iload_3
    //   510: istore 6
    //   512: iload_3
    //   513: istore 7
    //   515: aload 41
    //   517: aload 41
    //   519: invokeinterface 258 1 0
    //   524: iconst_1
    //   525: isub
    //   526: invokeinterface 310 2 0
    //   531: checkcast 312	com/tencent/tencentmap/mapsdk/a/ep
    //   534: astore 34
    //   536: iconst_1
    //   537: istore 6
    //   539: iconst_1
    //   540: istore 7
    //   542: iconst_1
    //   543: istore_2
    //   544: aload 20
    //   546: astore 26
    //   548: aload 22
    //   550: astore 25
    //   552: aload 29
    //   554: astore 24
    //   556: aload 39
    //   558: iconst_1
    //   559: putfield 329	com/tencent/tencentmap/mapsdk/a/fd:A	Z
    //   562: aload 20
    //   564: astore 26
    //   566: aload 22
    //   568: astore 25
    //   570: aload 29
    //   572: astore 24
    //   574: iload_2
    //   575: istore 6
    //   577: iload_2
    //   578: istore 7
    //   580: aload 20
    //   582: invokestatic 51	android/text/TextUtils:isEmpty	(Ljava/lang/CharSequence;)Z
    //   585: ifeq +1506 -> 2091
    //   588: aload 20
    //   590: astore 26
    //   592: aload 22
    //   594: astore 25
    //   596: aload 29
    //   598: astore 24
    //   600: iload_2
    //   601: istore 6
    //   603: iload_2
    //   604: istore 7
    //   606: aload_1
    //   607: invokevirtual 113	com/tencent/tencentmap/mapsdk/a/fb:p	()Z
    //   610: ifne +1313 -> 1923
    //   613: aload 20
    //   615: astore 26
    //   617: aload 22
    //   619: astore 25
    //   621: aload 29
    //   623: astore 24
    //   625: iload_2
    //   626: istore 6
    //   628: iload_2
    //   629: istore 7
    //   631: aload 34
    //   633: invokevirtual 331	com/tencent/tencentmap/mapsdk/a/ep:b	()I
    //   636: iconst_m1
    //   637: if_icmpeq +1242 -> 1879
    //   640: aload 20
    //   642: astore 26
    //   644: aload 22
    //   646: astore 25
    //   648: aload 29
    //   650: astore 24
    //   652: iload_2
    //   653: istore 6
    //   655: iload_2
    //   656: istore 7
    //   658: new 79	java/lang/StringBuilder
    //   661: dup
    //   662: ldc_w 333
    //   665: invokespecial 82	java/lang/StringBuilder:<init>	(Ljava/lang/String;)V
    //   668: aload 34
    //   670: invokevirtual 335	com/tencent/tencentmap/mapsdk/a/ep:a	()Ljava/lang/String;
    //   673: invokevirtual 86	java/lang/StringBuilder:append	(Ljava/lang/String;)Ljava/lang/StringBuilder;
    //   676: ldc_w 337
    //   679: invokevirtual 86	java/lang/StringBuilder:append	(Ljava/lang/String;)Ljava/lang/StringBuilder;
    //   682: aload 34
    //   684: invokevirtual 331	com/tencent/tencentmap/mapsdk/a/ep:b	()I
    //   687: invokevirtual 340	java/lang/StringBuilder:append	(I)Ljava/lang/StringBuilder;
    //   690: invokevirtual 89	java/lang/StringBuilder:toString	()Ljava/lang/String;
    //   693: astore 21
    //   695: aload 20
    //   697: astore 26
    //   699: aload 22
    //   701: astore 25
    //   703: aload 29
    //   705: astore 24
    //   707: iload_2
    //   708: istore 6
    //   710: iload_2
    //   711: istore 7
    //   713: aload_1
    //   714: invokevirtual 343	com/tencent/tencentmap/mapsdk/a/fb:e	()Ljava/lang/String;
    //   717: astore 30
    //   719: aload 21
    //   721: astore 23
    //   723: aload 20
    //   725: astore 26
    //   727: aload 22
    //   729: astore 25
    //   731: aload 29
    //   733: astore 24
    //   735: iload_2
    //   736: istore 6
    //   738: iload_2
    //   739: istore 7
    //   741: aload 30
    //   743: invokestatic 51	android/text/TextUtils:isEmpty	(Ljava/lang/CharSequence;)Z
    //   746: ifne +72 -> 818
    //   749: aload 20
    //   751: astore 26
    //   753: aload 22
    //   755: astore 25
    //   757: aload 29
    //   759: astore 24
    //   761: iload_2
    //   762: istore 6
    //   764: iload_2
    //   765: istore 7
    //   767: aload 30
    //   769: ldc_w 345
    //   772: invokevirtual 62	java/lang/String:startsWith	(Ljava/lang/String;)Z
    //   775: ifeq +1267 -> 2042
    //   778: aload 20
    //   780: astore 26
    //   782: aload 22
    //   784: astore 25
    //   786: aload 29
    //   788: astore 24
    //   790: iload_2
    //   791: istore 6
    //   793: iload_2
    //   794: istore 7
    //   796: new 79	java/lang/StringBuilder
    //   799: dup
    //   800: invokespecial 346	java/lang/StringBuilder:<init>	()V
    //   803: aload 21
    //   805: invokevirtual 86	java/lang/StringBuilder:append	(Ljava/lang/String;)Ljava/lang/StringBuilder;
    //   808: aload 30
    //   810: invokevirtual 86	java/lang/StringBuilder:append	(Ljava/lang/String;)Ljava/lang/StringBuilder;
    //   813: invokevirtual 89	java/lang/StringBuilder:toString	()Ljava/lang/String;
    //   816: astore 23
    //   818: aload 20
    //   820: astore 26
    //   822: aload 22
    //   824: astore 25
    //   826: aload 29
    //   828: astore 24
    //   830: iload_2
    //   831: istore 6
    //   833: iload_2
    //   834: istore 7
    //   836: aload 39
    //   838: aload 23
    //   840: putfield 349	com/tencent/tencentmap/mapsdk/a/fd:d	Ljava/lang/String;
    //   843: aload 23
    //   845: astore 21
    //   847: iconst_3
    //   848: istore 6
    //   850: aload 20
    //   852: astore 32
    //   854: aload 22
    //   856: astore 29
    //   858: aload 36
    //   860: astore 31
    //   862: iload 6
    //   864: istore_3
    //   865: aload 20
    //   867: astore 30
    //   869: aload 22
    //   871: astore 25
    //   873: aload 37
    //   875: astore 27
    //   877: aload 20
    //   879: astore 24
    //   881: aload 22
    //   883: astore 26
    //   885: aload 38
    //   887: astore 28
    //   889: ldc_w 271
    //   892: new 79	java/lang/StringBuilder
    //   895: dup
    //   896: ldc_w 351
    //   899: invokespecial 82	java/lang/StringBuilder:<init>	(Ljava/lang/String;)V
    //   902: iload 4
    //   904: invokevirtual 340	java/lang/StringBuilder:append	(I)Ljava/lang/StringBuilder;
    //   907: ldc_w 353
    //   910: invokevirtual 86	java/lang/StringBuilder:append	(Ljava/lang/String;)Ljava/lang/StringBuilder;
    //   913: aload 21
    //   915: invokevirtual 86	java/lang/StringBuilder:append	(Ljava/lang/String;)Ljava/lang/StringBuilder;
    //   918: ldc_w 355
    //   921: invokevirtual 86	java/lang/StringBuilder:append	(Ljava/lang/String;)Ljava/lang/StringBuilder;
    //   924: iload 14
    //   926: invokevirtual 358	java/lang/StringBuilder:append	(Z)Ljava/lang/StringBuilder;
    //   929: ldc_w 360
    //   932: invokevirtual 86	java/lang/StringBuilder:append	(Ljava/lang/String;)Ljava/lang/StringBuilder;
    //   935: aload 34
    //   937: invokevirtual 363	java/lang/StringBuilder:append	(Ljava/lang/Object;)Ljava/lang/StringBuilder;
    //   940: invokevirtual 89	java/lang/StringBuilder:toString	()Ljava/lang/String;
    //   943: invokestatic 364	com/tencent/tencentmap/mapsdk/a/fx:a	(Ljava/lang/String;Ljava/lang/String;)V
    //   946: aload 20
    //   948: astore 32
    //   950: aload 22
    //   952: astore 29
    //   954: aload 36
    //   956: astore 31
    //   958: iload 6
    //   960: istore_3
    //   961: aload 20
    //   963: astore 30
    //   965: aload 22
    //   967: astore 25
    //   969: aload 37
    //   971: astore 27
    //   973: aload 20
    //   975: astore 24
    //   977: aload 22
    //   979: astore 26
    //   981: aload 38
    //   983: astore 28
    //   985: aload_1
    //   986: invokevirtual 366	com/tencent/tencentmap/mapsdk/a/fb:b	()Z
    //   989: ifeq +1141 -> 2130
    //   992: aload 20
    //   994: astore 32
    //   996: aload 22
    //   998: astore 29
    //   1000: aload 36
    //   1002: astore 31
    //   1004: iload 6
    //   1006: istore_3
    //   1007: aload 20
    //   1009: astore 30
    //   1011: aload 22
    //   1013: astore 25
    //   1015: aload 37
    //   1017: astore 27
    //   1019: aload 20
    //   1021: astore 24
    //   1023: aload 22
    //   1025: astore 26
    //   1027: aload 38
    //   1029: astore 28
    //   1031: new 368	org/apache/http/client/methods/HttpGet
    //   1034: dup
    //   1035: aload 21
    //   1037: invokespecial 369	org/apache/http/client/methods/HttpGet:<init>	(Ljava/lang/String;)V
    //   1040: astore 34
    //   1042: aload 20
    //   1044: astore 32
    //   1046: aload 22
    //   1048: astore 29
    //   1050: aload 36
    //   1052: astore 31
    //   1054: iload 6
    //   1056: istore_3
    //   1057: aload 20
    //   1059: astore 30
    //   1061: aload 22
    //   1063: astore 25
    //   1065: aload 37
    //   1067: astore 27
    //   1069: aload 20
    //   1071: astore 24
    //   1073: aload 22
    //   1075: astore 26
    //   1077: aload 38
    //   1079: astore 28
    //   1081: aload 34
    //   1083: ldc_w 371
    //   1086: ldc_w 373
    //   1089: invokeinterface 378 3 0
    //   1094: aload 20
    //   1096: astore 32
    //   1098: aload 22
    //   1100: astore 29
    //   1102: aload 36
    //   1104: astore 31
    //   1106: iload 6
    //   1108: istore_3
    //   1109: aload 20
    //   1111: astore 30
    //   1113: aload 22
    //   1115: astore 25
    //   1117: aload 37
    //   1119: astore 27
    //   1121: aload 20
    //   1123: astore 24
    //   1125: aload 22
    //   1127: astore 26
    //   1129: aload 38
    //   1131: astore 28
    //   1133: aload_1
    //   1134: invokevirtual 381	com/tencent/tencentmap/mapsdk/a/fb:g	()Ljava/util/Map;
    //   1137: astore 23
    //   1139: aload 23
    //   1141: ifnull +1501 -> 2642
    //   1144: aload 20
    //   1146: astore 32
    //   1148: aload 22
    //   1150: astore 29
    //   1152: aload 36
    //   1154: astore 31
    //   1156: iload 6
    //   1158: istore_3
    //   1159: aload 20
    //   1161: astore 30
    //   1163: aload 22
    //   1165: astore 25
    //   1167: aload 37
    //   1169: astore 27
    //   1171: aload 20
    //   1173: astore 24
    //   1175: aload 22
    //   1177: astore 26
    //   1179: aload 38
    //   1181: astore 28
    //   1183: aload 23
    //   1185: invokeinterface 384 1 0
    //   1190: ifle +1452 -> 2642
    //   1193: iload 14
    //   1195: ifne +1447 -> 2642
    //   1198: aload 20
    //   1200: astore 32
    //   1202: aload 22
    //   1204: astore 29
    //   1206: aload 36
    //   1208: astore 31
    //   1210: iload 6
    //   1212: istore_3
    //   1213: aload 20
    //   1215: astore 30
    //   1217: aload 22
    //   1219: astore 25
    //   1221: aload 37
    //   1223: astore 27
    //   1225: aload 20
    //   1227: astore 24
    //   1229: aload 22
    //   1231: astore 26
    //   1233: aload 38
    //   1235: astore 28
    //   1237: aload 23
    //   1239: invokeinterface 388 1 0
    //   1244: invokeinterface 394 1 0
    //   1249: astore 43
    //   1251: aload 20
    //   1253: astore 32
    //   1255: aload 22
    //   1257: astore 29
    //   1259: aload 36
    //   1261: astore 31
    //   1263: iload 6
    //   1265: istore_3
    //   1266: aload 20
    //   1268: astore 30
    //   1270: aload 22
    //   1272: astore 25
    //   1274: aload 37
    //   1276: astore 27
    //   1278: aload 20
    //   1280: astore 24
    //   1282: aload 22
    //   1284: astore 26
    //   1286: aload 38
    //   1288: astore 28
    //   1290: aload 43
    //   1292: invokeinterface 399 1 0
    //   1297: ifeq +1241 -> 2538
    //   1300: aload 20
    //   1302: astore 32
    //   1304: aload 22
    //   1306: astore 29
    //   1308: aload 36
    //   1310: astore 31
    //   1312: iload 6
    //   1314: istore_3
    //   1315: aload 20
    //   1317: astore 30
    //   1319: aload 22
    //   1321: astore 25
    //   1323: aload 37
    //   1325: astore 27
    //   1327: aload 20
    //   1329: astore 24
    //   1331: aload 22
    //   1333: astore 26
    //   1335: aload 38
    //   1337: astore 28
    //   1339: aload 43
    //   1341: invokeinterface 403 1 0
    //   1346: checkcast 53	java/lang/String
    //   1349: astore 44
    //   1351: aload 20
    //   1353: astore 32
    //   1355: aload 22
    //   1357: astore 29
    //   1359: aload 36
    //   1361: astore 31
    //   1363: iload 6
    //   1365: istore_3
    //   1366: aload 20
    //   1368: astore 30
    //   1370: aload 22
    //   1372: astore 25
    //   1374: aload 37
    //   1376: astore 27
    //   1378: aload 20
    //   1380: astore 24
    //   1382: aload 22
    //   1384: astore 26
    //   1386: aload 38
    //   1388: astore 28
    //   1390: aload 34
    //   1392: aload 44
    //   1394: aload 23
    //   1396: aload 44
    //   1398: invokeinterface 406 2 0
    //   1403: checkcast 53	java/lang/String
    //   1406: invokeinterface 378 3 0
    //   1411: goto -160 -> 1251
    //   1414: astore 22
    //   1416: aload 32
    //   1418: astore 20
    //   1420: aload 31
    //   1422: astore 23
    //   1424: aload 29
    //   1426: astore 21
    //   1428: iload_2
    //   1429: istore 7
    //   1431: ldc_w 271
    //   1434: ldc_w 408
    //   1437: aload 22
    //   1439: invokestatic 411	com/tencent/tencentmap/mapsdk/a/fx:a	(Ljava/lang/String;Ljava/lang/String;Ljava/lang/Throwable;)V
    //   1442: aload 39
    //   1444: aload 22
    //   1446: invokevirtual 415	java/lang/Object:getClass	()Ljava/lang/Class;
    //   1449: invokevirtual 420	java/lang/Class:getSimpleName	()Ljava/lang/String;
    //   1452: putfield 422	com/tencent/tencentmap/mapsdk/a/fd:q	Ljava/lang/String;
    //   1455: aload 39
    //   1457: new 79	java/lang/StringBuilder
    //   1460: dup
    //   1461: invokespecial 346	java/lang/StringBuilder:<init>	()V
    //   1464: iload_3
    //   1465: invokevirtual 340	java/lang/StringBuilder:append	(I)Ljava/lang/StringBuilder;
    //   1468: ldc_w 424
    //   1471: invokevirtual 86	java/lang/StringBuilder:append	(Ljava/lang/String;)Ljava/lang/StringBuilder;
    //   1474: aload 22
    //   1476: invokestatic 427	com/tencent/tencentmap/mapsdk/a/fz:a	(Ljava/lang/Exception;)Ljava/lang/String;
    //   1479: invokevirtual 86	java/lang/StringBuilder:append	(Ljava/lang/String;)Ljava/lang/StringBuilder;
    //   1482: invokevirtual 89	java/lang/StringBuilder:toString	()Ljava/lang/String;
    //   1485: putfield 430	com/tencent/tencentmap/mapsdk/a/fd:r	Ljava/lang/String;
    //   1488: aload 33
    //   1490: aload 22
    //   1492: putfield 433	com/tencent/tencentmap/mapsdk/a/fc:b	Ljava/lang/Exception;
    //   1495: invokestatic 435	com/tencent/tencentmap/mapsdk/a/fw:e	()Z
    //   1498: ifeq +6230 -> 7728
    //   1501: aload 22
    //   1503: instanceof 437
    //   1506: ifeq +6100 -> 7606
    //   1509: bipush -10
    //   1511: istore_2
    //   1512: aload 33
    //   1514: iload_2
    //   1515: putfield 281	com/tencent/tencentmap/mapsdk/a/fc:a	I
    //   1518: aload 39
    //   1520: getfield 430	com/tencent/tencentmap/mapsdk/a/fd:r	Ljava/lang/String;
    //   1523: ldc_w 439
    //   1526: invokevirtual 442	java/lang/String:contains	(Ljava/lang/CharSequence;)Z
    //   1529: ifeq +10 -> 1539
    //   1532: aload 33
    //   1534: bipush -18
    //   1536: putfield 281	com/tencent/tencentmap/mapsdk/a/fc:a	I
    //   1539: aload 39
    //   1541: new 79	java/lang/StringBuilder
    //   1544: dup
    //   1545: invokespecial 346	java/lang/StringBuilder:<init>	()V
    //   1548: aload_1
    //   1549: invokevirtual 443	com/tencent/tencentmap/mapsdk/a/fb:a	()Ljava/lang/String;
    //   1552: invokevirtual 86	java/lang/StringBuilder:append	(Ljava/lang/String;)Ljava/lang/StringBuilder;
    //   1555: ldc_w 445
    //   1558: invokevirtual 86	java/lang/StringBuilder:append	(Ljava/lang/String;)Ljava/lang/StringBuilder;
    //   1561: iload 4
    //   1563: invokevirtual 340	java/lang/StringBuilder:append	(I)Ljava/lang/StringBuilder;
    //   1566: invokevirtual 89	java/lang/StringBuilder:toString	()Ljava/lang/String;
    //   1569: putfield 447	com/tencent/tencentmap/mapsdk/a/fd:p	Ljava/lang/String;
    //   1572: aload 39
    //   1574: iload 4
    //   1576: putfield 450	com/tencent/tencentmap/mapsdk/a/fd:s	I
    //   1579: aload 20
    //   1581: invokestatic 51	android/text/TextUtils:isEmpty	(Ljava/lang/CharSequence;)Z
    //   1584: ifeq +6150 -> 7734
    //   1587: iload 4
    //   1589: iconst_1
    //   1590: iadd
    //   1591: istore_3
    //   1592: iconst_0
    //   1593: istore_2
    //   1594: invokestatic 454	com/tencent/tencentmap/mapsdk/a/em:b	()Ljava/lang/String;
    //   1597: invokestatic 51	android/text/TextUtils:isEmpty	(Ljava/lang/CharSequence;)Z
    //   1600: ifne +198 -> 1798
    //   1603: aload 33
    //   1605: getfield 281	com/tencent/tencentmap/mapsdk/a/fc:a	I
    //   1608: bipush -21
    //   1610: if_icmpeq +188 -> 1798
    //   1613: aload 33
    //   1615: invokestatic 232	java/lang/System:currentTimeMillis	()J
    //   1618: aload_1
    //   1619: invokevirtual 263	com/tencent/tencentmap/mapsdk/a/fb:q	()J
    //   1622: lsub
    //   1623: l2i
    //   1624: putfield 457	com/tencent/tencentmap/mapsdk/a/fc:k	I
    //   1627: aload 39
    //   1629: aload 33
    //   1631: getfield 281	com/tencent/tencentmap/mapsdk/a/fc:a	I
    //   1634: putfield 458	com/tencent/tencentmap/mapsdk/a/fd:k	I
    //   1637: aload 39
    //   1639: aload 21
    //   1641: putfield 461	com/tencent/tencentmap/mapsdk/a/fd:C	Ljava/lang/String;
    //   1644: aload 39
    //   1646: aload 33
    //   1648: getfield 457	com/tencent/tencentmap/mapsdk/a/fc:k	I
    //   1651: putfield 463	com/tencent/tencentmap/mapsdk/a/fd:l	I
    //   1654: aload 39
    //   1656: invokestatic 232	java/lang/System:currentTimeMillis	()J
    //   1659: lload 16
    //   1661: lsub
    //   1662: l2i
    //   1663: putfield 466	com/tencent/tencentmap/mapsdk/a/fd:m	I
    //   1666: aload 39
    //   1668: aload 20
    //   1670: putfield 468	com/tencent/tencentmap/mapsdk/a/fd:f	Ljava/lang/String;
    //   1673: aload_1
    //   1674: invokevirtual 366	com/tencent/tencentmap/mapsdk/a/fb:b	()Z
    //   1677: ifne +6093 -> 7770
    //   1680: aload_1
    //   1681: invokevirtual 471	com/tencent/tencentmap/mapsdk/a/fb:h	()[B
    //   1684: ifnull +6086 -> 7770
    //   1687: aload 39
    //   1689: aload_1
    //   1690: invokevirtual 471	com/tencent/tencentmap/mapsdk/a/fb:h	()[B
    //   1693: arraylength
    //   1694: i2l
    //   1695: putfield 474	com/tencent/tencentmap/mapsdk/a/fd:n	J
    //   1698: aload 39
    //   1700: iload 13
    //   1702: putfield 477	com/tencent/tencentmap/mapsdk/a/fd:z	Z
    //   1705: iload 13
    //   1707: ifeq +17 -> 1724
    //   1710: aload 39
    //   1712: getfield 458	com/tencent/tencentmap/mapsdk/a/fd:k	I
    //   1715: ifeq +9 -> 1724
    //   1718: aload 39
    //   1720: iconst_1
    //   1721: putfield 480	com/tencent/tencentmap/mapsdk/a/fd:w	I
    //   1724: aload 39
    //   1726: aload_1
    //   1727: invokevirtual 482	com/tencent/tencentmap/mapsdk/a/fb:m	()Z
    //   1730: putfield 485	com/tencent/tencentmap/mapsdk/a/fd:B	Z
    //   1733: invokestatic 490	com/tencent/tencentmap/mapsdk/a/el:a	()Lcom/tencent/tencentmap/mapsdk/a/el;
    //   1736: new 492	com/tencent/tencentmap/mapsdk/a/fe
    //   1739: dup
    //   1740: aload 39
    //   1742: invokespecial 495	com/tencent/tencentmap/mapsdk/a/fe:<init>	(Lcom/tencent/tencentmap/mapsdk/a/fd;)V
    //   1745: invokevirtual 498	com/tencent/tencentmap/mapsdk/a/el:a	(Ljava/lang/Runnable;)V
    //   1748: aload_1
    //   1749: aload 39
    //   1751: invokevirtual 500	com/tencent/tencentmap/mapsdk/a/fb:a	(Lcom/tencent/tencentmap/mapsdk/a/fd;)V
    //   1754: aload 33
    //   1756: aload 39
    //   1758: getfield 313	com/tencent/tencentmap/mapsdk/a/fd:a	Lcom/tencent/tencentmap/mapsdk/a/ep;
    //   1761: invokevirtual 335	com/tencent/tencentmap/mapsdk/a/ep:a	()Ljava/lang/String;
    //   1764: putfield 502	com/tencent/tencentmap/mapsdk/a/fc:l	Ljava/lang/String;
    //   1767: aload 33
    //   1769: aload 39
    //   1771: invokevirtual 503	com/tencent/tencentmap/mapsdk/a/fd:toString	()Ljava/lang/String;
    //   1774: putfield 504	com/tencent/tencentmap/mapsdk/a/fc:d	Ljava/lang/String;
    //   1777: aload 33
    //   1779: aload 39
    //   1781: getfield 447	com/tencent/tencentmap/mapsdk/a/fd:p	Ljava/lang/String;
    //   1784: putfield 506	com/tencent/tencentmap/mapsdk/a/fc:m	Ljava/lang/String;
    //   1787: ldc_w 508
    //   1790: aload 39
    //   1792: invokevirtual 503	com/tencent/tencentmap/mapsdk/a/fd:toString	()Ljava/lang/String;
    //   1795: invokestatic 510	com/tencent/tencentmap/mapsdk/a/fx:b	(Ljava/lang/String;Ljava/lang/String;)V
    //   1798: aload 23
    //   1800: ifnull +15 -> 1815
    //   1803: aload_1
    //   1804: invokevirtual 269	com/tencent/tencentmap/mapsdk/a/fb:l	()Z
    //   1807: ifne +8 -> 1815
    //   1810: aload_1
    //   1811: invokevirtual 511	com/tencent/tencentmap/mapsdk/a/fb:f	()Z
    //   1814: pop
    //   1815: lload 16
    //   1817: invokestatic 513	com/tencent/tencentmap/mapsdk/a/ez:a	(J)Z
    //   1820: istore 13
    //   1822: aload 33
    //   1824: astore 23
    //   1826: aload 33
    //   1828: getfield 281	com/tencent/tencentmap/mapsdk/a/fc:a	I
    //   1831: bipush -4
    //   1833: if_icmpeq -1700 -> 133
    //   1836: aload 33
    //   1838: astore 23
    //   1840: aload 33
    //   1842: getfield 281	com/tencent/tencentmap/mapsdk/a/fc:a	I
    //   1845: bipush -17
    //   1847: if_icmpeq -1714 -> 133
    //   1850: aload 33
    //   1852: astore 23
    //   1854: iload 13
    //   1856: ifne -1723 -> 133
    //   1859: iload_3
    //   1860: istore 4
    //   1862: iload 7
    //   1864: istore_3
    //   1865: aload 21
    //   1867: astore 22
    //   1869: iload_2
    //   1870: istore 5
    //   1872: aload 33
    //   1874: astore 23
    //   1876: goto -1793 -> 83
    //   1879: aload 20
    //   1881: astore 26
    //   1883: aload 22
    //   1885: astore 25
    //   1887: aload 29
    //   1889: astore 24
    //   1891: iload_2
    //   1892: istore 6
    //   1894: iload_2
    //   1895: istore 7
    //   1897: new 79	java/lang/StringBuilder
    //   1900: dup
    //   1901: ldc_w 333
    //   1904: invokespecial 82	java/lang/StringBuilder:<init>	(Ljava/lang/String;)V
    //   1907: aload 34
    //   1909: invokevirtual 335	com/tencent/tencentmap/mapsdk/a/ep:a	()Ljava/lang/String;
    //   1912: invokevirtual 86	java/lang/StringBuilder:append	(Ljava/lang/String;)Ljava/lang/StringBuilder;
    //   1915: invokevirtual 89	java/lang/StringBuilder:toString	()Ljava/lang/String;
    //   1918: astore 21
    //   1920: goto -1225 -> 695
    //   1923: aload 20
    //   1925: astore 26
    //   1927: aload 22
    //   1929: astore 25
    //   1931: aload 29
    //   1933: astore 24
    //   1935: iload_2
    //   1936: istore 6
    //   1938: iload_2
    //   1939: istore 7
    //   1941: aload 34
    //   1943: invokevirtual 331	com/tencent/tencentmap/mapsdk/a/ep:b	()I
    //   1946: iconst_m1
    //   1947: if_icmpeq +52 -> 1999
    //   1950: aload 20
    //   1952: astore 26
    //   1954: aload 22
    //   1956: astore 25
    //   1958: aload 29
    //   1960: astore 24
    //   1962: iload_2
    //   1963: istore 6
    //   1965: iload_2
    //   1966: istore 7
    //   1968: new 79	java/lang/StringBuilder
    //   1971: dup
    //   1972: ldc 58
    //   1974: invokespecial 82	java/lang/StringBuilder:<init>	(Ljava/lang/String;)V
    //   1977: aload 34
    //   1979: invokevirtual 335	com/tencent/tencentmap/mapsdk/a/ep:a	()Ljava/lang/String;
    //   1982: invokevirtual 86	java/lang/StringBuilder:append	(Ljava/lang/String;)Ljava/lang/StringBuilder;
    //   1985: ldc_w 515
    //   1988: invokevirtual 86	java/lang/StringBuilder:append	(Ljava/lang/String;)Ljava/lang/StringBuilder;
    //   1991: invokevirtual 89	java/lang/StringBuilder:toString	()Ljava/lang/String;
    //   1994: astore 21
    //   1996: goto -1301 -> 695
    //   1999: aload 20
    //   2001: astore 26
    //   2003: aload 22
    //   2005: astore 25
    //   2007: aload 29
    //   2009: astore 24
    //   2011: iload_2
    //   2012: istore 6
    //   2014: iload_2
    //   2015: istore 7
    //   2017: new 79	java/lang/StringBuilder
    //   2020: dup
    //   2021: ldc 58
    //   2023: invokespecial 82	java/lang/StringBuilder:<init>	(Ljava/lang/String;)V
    //   2026: aload 34
    //   2028: invokevirtual 335	com/tencent/tencentmap/mapsdk/a/ep:a	()Ljava/lang/String;
    //   2031: invokevirtual 86	java/lang/StringBuilder:append	(Ljava/lang/String;)Ljava/lang/StringBuilder;
    //   2034: invokevirtual 89	java/lang/StringBuilder:toString	()Ljava/lang/String;
    //   2037: astore 21
    //   2039: goto -1344 -> 695
    //   2042: aload 20
    //   2044: astore 26
    //   2046: aload 22
    //   2048: astore 25
    //   2050: aload 29
    //   2052: astore 24
    //   2054: iload_2
    //   2055: istore 6
    //   2057: iload_2
    //   2058: istore 7
    //   2060: new 79	java/lang/StringBuilder
    //   2063: dup
    //   2064: invokespecial 346	java/lang/StringBuilder:<init>	()V
    //   2067: aload 21
    //   2069: invokevirtual 86	java/lang/StringBuilder:append	(Ljava/lang/String;)Ljava/lang/StringBuilder;
    //   2072: ldc_w 345
    //   2075: invokevirtual 86	java/lang/StringBuilder:append	(Ljava/lang/String;)Ljava/lang/StringBuilder;
    //   2078: aload 30
    //   2080: invokevirtual 86	java/lang/StringBuilder:append	(Ljava/lang/String;)Ljava/lang/StringBuilder;
    //   2083: invokevirtual 89	java/lang/StringBuilder:toString	()Ljava/lang/String;
    //   2086: astore 23
    //   2088: goto -1270 -> 818
    //   2091: aload 20
    //   2093: astore 26
    //   2095: aload 22
    //   2097: astore 25
    //   2099: aload 29
    //   2101: astore 24
    //   2103: iload_2
    //   2104: istore 6
    //   2106: iload_2
    //   2107: istore 7
    //   2109: aload 39
    //   2111: aload 20
    //   2113: putfield 468	com/tencent/tencentmap/mapsdk/a/fd:f	Ljava/lang/String;
    //   2116: aconst_null
    //   2117: astore 23
    //   2119: aload 20
    //   2121: astore 21
    //   2123: aload 23
    //   2125: astore 20
    //   2127: goto -1280 -> 847
    //   2130: aload 20
    //   2132: astore 32
    //   2134: aload 22
    //   2136: astore 29
    //   2138: aload 36
    //   2140: astore 31
    //   2142: iload 6
    //   2144: istore_3
    //   2145: aload 20
    //   2147: astore 30
    //   2149: aload 22
    //   2151: astore 25
    //   2153: aload 37
    //   2155: astore 27
    //   2157: aload 20
    //   2159: astore 24
    //   2161: aload 22
    //   2163: astore 26
    //   2165: aload 38
    //   2167: astore 28
    //   2169: new 517	org/apache/http/client/methods/HttpPost
    //   2172: dup
    //   2173: aload 21
    //   2175: invokespecial 518	org/apache/http/client/methods/HttpPost:<init>	(Ljava/lang/String;)V
    //   2178: astore 34
    //   2180: goto -1138 -> 1042
    //   2183: astore 20
    //   2185: aload 30
    //   2187: astore 20
    //   2189: aload 27
    //   2191: astore 23
    //   2193: aload 25
    //   2195: astore 21
    //   2197: iload_2
    //   2198: istore_3
    //   2199: aload 39
    //   2201: new 79	java/lang/StringBuilder
    //   2204: dup
    //   2205: invokespecial 346	java/lang/StringBuilder:<init>	()V
    //   2208: aload_1
    //   2209: invokevirtual 443	com/tencent/tencentmap/mapsdk/a/fb:a	()Ljava/lang/String;
    //   2212: invokevirtual 86	java/lang/StringBuilder:append	(Ljava/lang/String;)Ljava/lang/StringBuilder;
    //   2215: ldc_w 445
    //   2218: invokevirtual 86	java/lang/StringBuilder:append	(Ljava/lang/String;)Ljava/lang/StringBuilder;
    //   2221: iload 4
    //   2223: invokevirtual 340	java/lang/StringBuilder:append	(I)Ljava/lang/StringBuilder;
    //   2226: invokevirtual 89	java/lang/StringBuilder:toString	()Ljava/lang/String;
    //   2229: putfield 447	com/tencent/tencentmap/mapsdk/a/fd:p	Ljava/lang/String;
    //   2232: aload 39
    //   2234: iload 4
    //   2236: putfield 450	com/tencent/tencentmap/mapsdk/a/fd:s	I
    //   2239: aload 20
    //   2241: invokestatic 51	android/text/TextUtils:isEmpty	(Ljava/lang/CharSequence;)Z
    //   2244: ifeq +5535 -> 7779
    //   2247: iload 4
    //   2249: iconst_1
    //   2250: iadd
    //   2251: istore 5
    //   2253: iconst_0
    //   2254: istore_2
    //   2255: invokestatic 454	com/tencent/tencentmap/mapsdk/a/em:b	()Ljava/lang/String;
    //   2258: invokestatic 51	android/text/TextUtils:isEmpty	(Ljava/lang/CharSequence;)Z
    //   2261: ifne +198 -> 2459
    //   2264: aload 33
    //   2266: getfield 281	com/tencent/tencentmap/mapsdk/a/fc:a	I
    //   2269: bipush -21
    //   2271: if_icmpeq +188 -> 2459
    //   2274: aload 33
    //   2276: invokestatic 232	java/lang/System:currentTimeMillis	()J
    //   2279: aload_1
    //   2280: invokevirtual 263	com/tencent/tencentmap/mapsdk/a/fb:q	()J
    //   2283: lsub
    //   2284: l2i
    //   2285: putfield 457	com/tencent/tencentmap/mapsdk/a/fc:k	I
    //   2288: aload 39
    //   2290: aload 33
    //   2292: getfield 281	com/tencent/tencentmap/mapsdk/a/fc:a	I
    //   2295: putfield 458	com/tencent/tencentmap/mapsdk/a/fd:k	I
    //   2298: aload 39
    //   2300: aload 21
    //   2302: putfield 461	com/tencent/tencentmap/mapsdk/a/fd:C	Ljava/lang/String;
    //   2305: aload 39
    //   2307: aload 33
    //   2309: getfield 457	com/tencent/tencentmap/mapsdk/a/fc:k	I
    //   2312: putfield 463	com/tencent/tencentmap/mapsdk/a/fd:l	I
    //   2315: aload 39
    //   2317: invokestatic 232	java/lang/System:currentTimeMillis	()J
    //   2320: lload 16
    //   2322: lsub
    //   2323: l2i
    //   2324: putfield 466	com/tencent/tencentmap/mapsdk/a/fd:m	I
    //   2327: aload 39
    //   2329: aload 20
    //   2331: putfield 468	com/tencent/tencentmap/mapsdk/a/fd:f	Ljava/lang/String;
    //   2334: aload_1
    //   2335: invokevirtual 366	com/tencent/tencentmap/mapsdk/a/fb:b	()Z
    //   2338: ifne +5479 -> 7817
    //   2341: aload_1
    //   2342: invokevirtual 471	com/tencent/tencentmap/mapsdk/a/fb:h	()[B
    //   2345: ifnull +5472 -> 7817
    //   2348: aload 39
    //   2350: aload_1
    //   2351: invokevirtual 471	com/tencent/tencentmap/mapsdk/a/fb:h	()[B
    //   2354: arraylength
    //   2355: i2l
    //   2356: putfield 474	com/tencent/tencentmap/mapsdk/a/fd:n	J
    //   2359: aload 39
    //   2361: iload 13
    //   2363: putfield 477	com/tencent/tencentmap/mapsdk/a/fd:z	Z
    //   2366: iload 13
    //   2368: ifeq +17 -> 2385
    //   2371: aload 39
    //   2373: getfield 458	com/tencent/tencentmap/mapsdk/a/fd:k	I
    //   2376: ifeq +9 -> 2385
    //   2379: aload 39
    //   2381: iconst_1
    //   2382: putfield 480	com/tencent/tencentmap/mapsdk/a/fd:w	I
    //   2385: aload 39
    //   2387: aload_1
    //   2388: invokevirtual 482	com/tencent/tencentmap/mapsdk/a/fb:m	()Z
    //   2391: putfield 485	com/tencent/tencentmap/mapsdk/a/fd:B	Z
    //   2394: invokestatic 490	com/tencent/tencentmap/mapsdk/a/el:a	()Lcom/tencent/tencentmap/mapsdk/a/el;
    //   2397: new 492	com/tencent/tencentmap/mapsdk/a/fe
    //   2400: dup
    //   2401: aload 39
    //   2403: invokespecial 495	com/tencent/tencentmap/mapsdk/a/fe:<init>	(Lcom/tencent/tencentmap/mapsdk/a/fd;)V
    //   2406: invokevirtual 498	com/tencent/tencentmap/mapsdk/a/el:a	(Ljava/lang/Runnable;)V
    //   2409: aload_1
    //   2410: aload 39
    //   2412: invokevirtual 500	com/tencent/tencentmap/mapsdk/a/fb:a	(Lcom/tencent/tencentmap/mapsdk/a/fd;)V
    //   2415: aload 33
    //   2417: aload 39
    //   2419: getfield 313	com/tencent/tencentmap/mapsdk/a/fd:a	Lcom/tencent/tencentmap/mapsdk/a/ep;
    //   2422: invokevirtual 335	com/tencent/tencentmap/mapsdk/a/ep:a	()Ljava/lang/String;
    //   2425: putfield 502	com/tencent/tencentmap/mapsdk/a/fc:l	Ljava/lang/String;
    //   2428: aload 33
    //   2430: aload 39
    //   2432: invokevirtual 503	com/tencent/tencentmap/mapsdk/a/fd:toString	()Ljava/lang/String;
    //   2435: putfield 504	com/tencent/tencentmap/mapsdk/a/fc:d	Ljava/lang/String;
    //   2438: aload 33
    //   2440: aload 39
    //   2442: getfield 447	com/tencent/tencentmap/mapsdk/a/fd:p	Ljava/lang/String;
    //   2445: putfield 506	com/tencent/tencentmap/mapsdk/a/fc:m	Ljava/lang/String;
    //   2448: ldc_w 508
    //   2451: aload 39
    //   2453: invokevirtual 503	com/tencent/tencentmap/mapsdk/a/fd:toString	()Ljava/lang/String;
    //   2456: invokestatic 510	com/tencent/tencentmap/mapsdk/a/fx:b	(Ljava/lang/String;Ljava/lang/String;)V
    //   2459: aload 23
    //   2461: ifnull +15 -> 2476
    //   2464: aload_1
    //   2465: invokevirtual 269	com/tencent/tencentmap/mapsdk/a/fb:l	()Z
    //   2468: ifne +8 -> 2476
    //   2471: aload_1
    //   2472: invokevirtual 511	com/tencent/tencentmap/mapsdk/a/fb:f	()Z
    //   2475: pop
    //   2476: lload 16
    //   2478: invokestatic 513	com/tencent/tencentmap/mapsdk/a/ez:a	(J)Z
    //   2481: istore 13
    //   2483: aload 33
    //   2485: astore 23
    //   2487: aload 33
    //   2489: getfield 281	com/tencent/tencentmap/mapsdk/a/fc:a	I
    //   2492: bipush -4
    //   2494: if_icmpeq -2361 -> 133
    //   2497: aload 33
    //   2499: astore 23
    //   2501: aload 33
    //   2503: getfield 281	com/tencent/tencentmap/mapsdk/a/fc:a	I
    //   2506: bipush -17
    //   2508: if_icmpeq -2375 -> 133
    //   2511: aload 33
    //   2513: astore 23
    //   2515: iload 13
    //   2517: ifne -2384 -> 133
    //   2520: iload 5
    //   2522: istore 4
    //   2524: aload 21
    //   2526: astore 22
    //   2528: iload_2
    //   2529: istore 5
    //   2531: aload 33
    //   2533: astore 23
    //   2535: goto -2452 -> 83
    //   2538: aload 20
    //   2540: astore 32
    //   2542: aload 22
    //   2544: astore 29
    //   2546: aload 36
    //   2548: astore 31
    //   2550: iload 6
    //   2552: istore_3
    //   2553: aload 20
    //   2555: astore 30
    //   2557: aload 22
    //   2559: astore 25
    //   2561: aload 37
    //   2563: astore 27
    //   2565: aload 20
    //   2567: astore 24
    //   2569: aload 22
    //   2571: astore 26
    //   2573: aload 38
    //   2575: astore 28
    //   2577: getstatic 520	com/tencent/tencentmap/mapsdk/a/fw:c	Z
    //   2580: ifeq +62 -> 2642
    //   2583: iload 4
    //   2585: iconst_2
    //   2586: if_icmpne +56 -> 2642
    //   2589: aload 20
    //   2591: astore 32
    //   2593: aload 22
    //   2595: astore 29
    //   2597: aload 36
    //   2599: astore 31
    //   2601: iload 6
    //   2603: istore_3
    //   2604: aload 20
    //   2606: astore 30
    //   2608: aload 22
    //   2610: astore 25
    //   2612: aload 37
    //   2614: astore 27
    //   2616: aload 20
    //   2618: astore 24
    //   2620: aload 22
    //   2622: astore 26
    //   2624: aload 38
    //   2626: astore 28
    //   2628: aload 34
    //   2630: ldc_w 522
    //   2633: aload_1
    //   2634: invokevirtual 131	com/tencent/tencentmap/mapsdk/a/fb:n	()Ljava/lang/String;
    //   2637: invokeinterface 378 3 0
    //   2642: aload 20
    //   2644: astore 32
    //   2646: aload 22
    //   2648: astore 29
    //   2650: aload 36
    //   2652: astore 31
    //   2654: iload 6
    //   2656: istore_3
    //   2657: aload 20
    //   2659: astore 30
    //   2661: aload 22
    //   2663: astore 25
    //   2665: aload 37
    //   2667: astore 27
    //   2669: aload 20
    //   2671: astore 24
    //   2673: aload 22
    //   2675: astore 26
    //   2677: aload 38
    //   2679: astore 28
    //   2681: aload 34
    //   2683: ldc_w 524
    //   2686: new 79	java/lang/StringBuilder
    //   2689: dup
    //   2690: ldc_w 526
    //   2693: invokespecial 82	java/lang/StringBuilder:<init>	(Ljava/lang/String;)V
    //   2696: invokestatic 528	com/tencent/tencentmap/mapsdk/a/em:f	()Ljava/lang/String;
    //   2699: invokevirtual 86	java/lang/StringBuilder:append	(Ljava/lang/String;)Ljava/lang/StringBuilder;
    //   2702: ldc_w 530
    //   2705: invokevirtual 86	java/lang/StringBuilder:append	(Ljava/lang/String;)Ljava/lang/StringBuilder;
    //   2708: aload_1
    //   2709: invokevirtual 443	com/tencent/tencentmap/mapsdk/a/fb:a	()Ljava/lang/String;
    //   2712: invokevirtual 86	java/lang/StringBuilder:append	(Ljava/lang/String;)Ljava/lang/StringBuilder;
    //   2715: ldc_w 445
    //   2718: invokevirtual 86	java/lang/StringBuilder:append	(Ljava/lang/String;)Ljava/lang/StringBuilder;
    //   2721: iload 4
    //   2723: invokevirtual 340	java/lang/StringBuilder:append	(I)Ljava/lang/StringBuilder;
    //   2726: invokevirtual 89	java/lang/StringBuilder:toString	()Ljava/lang/String;
    //   2729: invokeinterface 378 3 0
    //   2734: iload 14
    //   2736: ifeq +670 -> 3406
    //   2739: aload 20
    //   2741: astore 32
    //   2743: aload 22
    //   2745: astore 29
    //   2747: aload 36
    //   2749: astore 31
    //   2751: iload 6
    //   2753: istore_3
    //   2754: aload 20
    //   2756: astore 30
    //   2758: aload 22
    //   2760: astore 25
    //   2762: aload 37
    //   2764: astore 27
    //   2766: aload 20
    //   2768: astore 24
    //   2770: aload 22
    //   2772: astore 26
    //   2774: aload 38
    //   2776: astore 28
    //   2778: aload 23
    //   2780: invokeinterface 388 1 0
    //   2785: invokeinterface 394 1 0
    //   2790: astore 43
    //   2792: aload 20
    //   2794: astore 32
    //   2796: aload 22
    //   2798: astore 29
    //   2800: aload 36
    //   2802: astore 31
    //   2804: iload 6
    //   2806: istore_3
    //   2807: aload 20
    //   2809: astore 30
    //   2811: aload 22
    //   2813: astore 25
    //   2815: aload 37
    //   2817: astore 27
    //   2819: aload 20
    //   2821: astore 24
    //   2823: aload 22
    //   2825: astore 26
    //   2827: aload 38
    //   2829: astore 28
    //   2831: aload 43
    //   2833: invokeinterface 399 1 0
    //   2838: ifeq +463 -> 3301
    //   2841: aload 20
    //   2843: astore 32
    //   2845: aload 22
    //   2847: astore 29
    //   2849: aload 36
    //   2851: astore 31
    //   2853: iload 6
    //   2855: istore_3
    //   2856: aload 20
    //   2858: astore 30
    //   2860: aload 22
    //   2862: astore 25
    //   2864: aload 37
    //   2866: astore 27
    //   2868: aload 20
    //   2870: astore 24
    //   2872: aload 22
    //   2874: astore 26
    //   2876: aload 38
    //   2878: astore 28
    //   2880: aload 43
    //   2882: invokeinterface 403 1 0
    //   2887: checkcast 53	java/lang/String
    //   2890: astore 44
    //   2892: aload 20
    //   2894: astore 32
    //   2896: aload 22
    //   2898: astore 29
    //   2900: aload 36
    //   2902: astore 31
    //   2904: iload 6
    //   2906: istore_3
    //   2907: aload 20
    //   2909: astore 30
    //   2911: aload 22
    //   2913: astore 25
    //   2915: aload 37
    //   2917: astore 27
    //   2919: aload 20
    //   2921: astore 24
    //   2923: aload 22
    //   2925: astore 26
    //   2927: aload 38
    //   2929: astore 28
    //   2931: aload 34
    //   2933: aload 44
    //   2935: aload 23
    //   2937: aload 44
    //   2939: invokeinterface 406 2 0
    //   2944: checkcast 53	java/lang/String
    //   2947: invokeinterface 378 3 0
    //   2952: goto -160 -> 2792
    //   2955: astore 22
    //   2957: aload 28
    //   2959: astore 23
    //   2961: aload 26
    //   2963: astore 21
    //   2965: aload 24
    //   2967: astore 20
    //   2969: aload 39
    //   2971: new 79	java/lang/StringBuilder
    //   2974: dup
    //   2975: invokespecial 346	java/lang/StringBuilder:<init>	()V
    //   2978: aload_1
    //   2979: invokevirtual 443	com/tencent/tencentmap/mapsdk/a/fb:a	()Ljava/lang/String;
    //   2982: invokevirtual 86	java/lang/StringBuilder:append	(Ljava/lang/String;)Ljava/lang/StringBuilder;
    //   2985: ldc_w 445
    //   2988: invokevirtual 86	java/lang/StringBuilder:append	(Ljava/lang/String;)Ljava/lang/StringBuilder;
    //   2991: iload 4
    //   2993: invokevirtual 340	java/lang/StringBuilder:append	(I)Ljava/lang/StringBuilder;
    //   2996: invokevirtual 89	java/lang/StringBuilder:toString	()Ljava/lang/String;
    //   2999: putfield 447	com/tencent/tencentmap/mapsdk/a/fd:p	Ljava/lang/String;
    //   3002: aload 39
    //   3004: iload 4
    //   3006: putfield 450	com/tencent/tencentmap/mapsdk/a/fd:s	I
    //   3009: aload 20
    //   3011: invokestatic 51	android/text/TextUtils:isEmpty	(Ljava/lang/CharSequence;)Z
    //   3014: ifne +19 -> 3033
    //   3017: iload 5
    //   3019: iconst_1
    //   3020: iadd
    //   3021: bipush 6
    //   3023: if_icmple +10 -> 3033
    //   3026: aload 33
    //   3028: bipush -5
    //   3030: putfield 281	com/tencent/tencentmap/mapsdk/a/fc:a	I
    //   3033: invokestatic 454	com/tencent/tencentmap/mapsdk/a/em:b	()Ljava/lang/String;
    //   3036: invokestatic 51	android/text/TextUtils:isEmpty	(Ljava/lang/CharSequence;)Z
    //   3039: ifne +198 -> 3237
    //   3042: aload 33
    //   3044: getfield 281	com/tencent/tencentmap/mapsdk/a/fc:a	I
    //   3047: bipush -21
    //   3049: if_icmpeq +188 -> 3237
    //   3052: aload 33
    //   3054: invokestatic 232	java/lang/System:currentTimeMillis	()J
    //   3057: aload_1
    //   3058: invokevirtual 263	com/tencent/tencentmap/mapsdk/a/fb:q	()J
    //   3061: lsub
    //   3062: l2i
    //   3063: putfield 457	com/tencent/tencentmap/mapsdk/a/fc:k	I
    //   3066: aload 39
    //   3068: aload 33
    //   3070: getfield 281	com/tencent/tencentmap/mapsdk/a/fc:a	I
    //   3073: putfield 458	com/tencent/tencentmap/mapsdk/a/fd:k	I
    //   3076: aload 39
    //   3078: aload 21
    //   3080: putfield 461	com/tencent/tencentmap/mapsdk/a/fd:C	Ljava/lang/String;
    //   3083: aload 39
    //   3085: aload 33
    //   3087: getfield 457	com/tencent/tencentmap/mapsdk/a/fc:k	I
    //   3090: putfield 463	com/tencent/tencentmap/mapsdk/a/fd:l	I
    //   3093: aload 39
    //   3095: invokestatic 232	java/lang/System:currentTimeMillis	()J
    //   3098: lload 16
    //   3100: lsub
    //   3101: l2i
    //   3102: putfield 466	com/tencent/tencentmap/mapsdk/a/fd:m	I
    //   3105: aload 39
    //   3107: aload 20
    //   3109: putfield 468	com/tencent/tencentmap/mapsdk/a/fd:f	Ljava/lang/String;
    //   3112: aload_1
    //   3113: invokevirtual 366	com/tencent/tencentmap/mapsdk/a/fb:b	()Z
    //   3116: ifne +4710 -> 7826
    //   3119: aload_1
    //   3120: invokevirtual 471	com/tencent/tencentmap/mapsdk/a/fb:h	()[B
    //   3123: ifnull +4703 -> 7826
    //   3126: aload 39
    //   3128: aload_1
    //   3129: invokevirtual 471	com/tencent/tencentmap/mapsdk/a/fb:h	()[B
    //   3132: arraylength
    //   3133: i2l
    //   3134: putfield 474	com/tencent/tencentmap/mapsdk/a/fd:n	J
    //   3137: aload 39
    //   3139: iload 13
    //   3141: putfield 477	com/tencent/tencentmap/mapsdk/a/fd:z	Z
    //   3144: iload 13
    //   3146: ifeq +17 -> 3163
    //   3149: aload 39
    //   3151: getfield 458	com/tencent/tencentmap/mapsdk/a/fd:k	I
    //   3154: ifeq +9 -> 3163
    //   3157: aload 39
    //   3159: iconst_1
    //   3160: putfield 480	com/tencent/tencentmap/mapsdk/a/fd:w	I
    //   3163: aload 39
    //   3165: aload_1
    //   3166: invokevirtual 482	com/tencent/tencentmap/mapsdk/a/fb:m	()Z
    //   3169: putfield 485	com/tencent/tencentmap/mapsdk/a/fd:B	Z
    //   3172: invokestatic 490	com/tencent/tencentmap/mapsdk/a/el:a	()Lcom/tencent/tencentmap/mapsdk/a/el;
    //   3175: new 492	com/tencent/tencentmap/mapsdk/a/fe
    //   3178: dup
    //   3179: aload 39
    //   3181: invokespecial 495	com/tencent/tencentmap/mapsdk/a/fe:<init>	(Lcom/tencent/tencentmap/mapsdk/a/fd;)V
    //   3184: invokevirtual 498	com/tencent/tencentmap/mapsdk/a/el:a	(Ljava/lang/Runnable;)V
    //   3187: aload_1
    //   3188: aload 39
    //   3190: invokevirtual 500	com/tencent/tencentmap/mapsdk/a/fb:a	(Lcom/tencent/tencentmap/mapsdk/a/fd;)V
    //   3193: aload 33
    //   3195: aload 39
    //   3197: getfield 313	com/tencent/tencentmap/mapsdk/a/fd:a	Lcom/tencent/tencentmap/mapsdk/a/ep;
    //   3200: invokevirtual 335	com/tencent/tencentmap/mapsdk/a/ep:a	()Ljava/lang/String;
    //   3203: putfield 502	com/tencent/tencentmap/mapsdk/a/fc:l	Ljava/lang/String;
    //   3206: aload 33
    //   3208: aload 39
    //   3210: invokevirtual 503	com/tencent/tencentmap/mapsdk/a/fd:toString	()Ljava/lang/String;
    //   3213: putfield 504	com/tencent/tencentmap/mapsdk/a/fc:d	Ljava/lang/String;
    //   3216: aload 33
    //   3218: aload 39
    //   3220: getfield 447	com/tencent/tencentmap/mapsdk/a/fd:p	Ljava/lang/String;
    //   3223: putfield 506	com/tencent/tencentmap/mapsdk/a/fc:m	Ljava/lang/String;
    //   3226: ldc_w 508
    //   3229: aload 39
    //   3231: invokevirtual 503	com/tencent/tencentmap/mapsdk/a/fd:toString	()Ljava/lang/String;
    //   3234: invokestatic 510	com/tencent/tencentmap/mapsdk/a/fx:b	(Ljava/lang/String;Ljava/lang/String;)V
    //   3237: aload 23
    //   3239: ifnull +15 -> 3254
    //   3242: aload_1
    //   3243: invokevirtual 269	com/tencent/tencentmap/mapsdk/a/fb:l	()Z
    //   3246: ifne +8 -> 3254
    //   3249: aload_1
    //   3250: invokevirtual 511	com/tencent/tencentmap/mapsdk/a/fb:f	()Z
    //   3253: pop
    //   3254: lload 16
    //   3256: invokestatic 513	com/tencent/tencentmap/mapsdk/a/ez:a	(J)Z
    //   3259: istore 13
    //   3261: aload 33
    //   3263: astore 23
    //   3265: aload 33
    //   3267: getfield 281	com/tencent/tencentmap/mapsdk/a/fc:a	I
    //   3270: bipush -4
    //   3272: if_icmpeq -3139 -> 133
    //   3275: aload 33
    //   3277: astore 23
    //   3279: aload 33
    //   3281: getfield 281	com/tencent/tencentmap/mapsdk/a/fc:a	I
    //   3284: bipush -17
    //   3286: if_icmpeq -3153 -> 133
    //   3289: aload 33
    //   3291: astore 23
    //   3293: iload 13
    //   3295: ifne -3162 -> 133
    //   3298: aload 22
    //   3300: athrow
    //   3301: aload 20
    //   3303: astore 32
    //   3305: aload 22
    //   3307: astore 29
    //   3309: aload 36
    //   3311: astore 31
    //   3313: iload 6
    //   3315: istore_3
    //   3316: aload 20
    //   3318: astore 30
    //   3320: aload 22
    //   3322: astore 25
    //   3324: aload 37
    //   3326: astore 27
    //   3328: aload 20
    //   3330: astore 24
    //   3332: aload 22
    //   3334: astore 26
    //   3336: aload 38
    //   3338: astore 28
    //   3340: getstatic 520	com/tencent/tencentmap/mapsdk/a/fw:c	Z
    //   3343: ifeq +63 -> 3406
    //   3346: iload 4
    //   3348: iconst_2
    //   3349: if_icmpne +57 -> 3406
    //   3352: aload 20
    //   3354: astore 32
    //   3356: aload 22
    //   3358: astore 29
    //   3360: aload 36
    //   3362: astore 31
    //   3364: iload 6
    //   3366: istore_3
    //   3367: aload 20
    //   3369: astore 30
    //   3371: aload 22
    //   3373: astore 25
    //   3375: aload 37
    //   3377: astore 27
    //   3379: aload 20
    //   3381: astore 24
    //   3383: aload 22
    //   3385: astore 26
    //   3387: aload 38
    //   3389: astore 28
    //   3391: aload 34
    //   3393: ldc_w 522
    //   3396: aload 21
    //   3398: invokestatic 532	com/tencent/tencentmap/mapsdk/a/fz:d	(Ljava/lang/String;)Ljava/lang/String;
    //   3401: invokeinterface 378 3 0
    //   3406: aload 20
    //   3408: astore 32
    //   3410: aload 22
    //   3412: astore 29
    //   3414: aload 36
    //   3416: astore 31
    //   3418: iload 6
    //   3420: istore_3
    //   3421: aload 20
    //   3423: astore 30
    //   3425: aload 22
    //   3427: astore 25
    //   3429: aload 37
    //   3431: astore 27
    //   3433: aload 20
    //   3435: astore 24
    //   3437: aload 22
    //   3439: astore 26
    //   3441: aload 38
    //   3443: astore 28
    //   3445: aload_1
    //   3446: invokevirtual 366	com/tencent/tencentmap/mapsdk/a/fb:b	()Z
    //   3449: ifne +154 -> 3603
    //   3452: aload 20
    //   3454: astore 32
    //   3456: aload 22
    //   3458: astore 29
    //   3460: aload 36
    //   3462: astore 31
    //   3464: iload 6
    //   3466: istore_3
    //   3467: aload 20
    //   3469: astore 30
    //   3471: aload 22
    //   3473: astore 25
    //   3475: aload 37
    //   3477: astore 27
    //   3479: aload 20
    //   3481: astore 24
    //   3483: aload 22
    //   3485: astore 26
    //   3487: aload 38
    //   3489: astore 28
    //   3491: aload_1
    //   3492: invokevirtual 471	com/tencent/tencentmap/mapsdk/a/fb:h	()[B
    //   3495: astore 21
    //   3497: aload 21
    //   3499: ifnull +104 -> 3603
    //   3502: aload 20
    //   3504: astore 32
    //   3506: aload 22
    //   3508: astore 29
    //   3510: aload 36
    //   3512: astore 31
    //   3514: iload 6
    //   3516: istore_3
    //   3517: aload 20
    //   3519: astore 30
    //   3521: aload 22
    //   3523: astore 25
    //   3525: aload 37
    //   3527: astore 27
    //   3529: aload 20
    //   3531: astore 24
    //   3533: aload 22
    //   3535: astore 26
    //   3537: aload 38
    //   3539: astore 28
    //   3541: aload 21
    //   3543: arraylength
    //   3544: ifle +59 -> 3603
    //   3547: aload 20
    //   3549: astore 32
    //   3551: aload 22
    //   3553: astore 29
    //   3555: aload 36
    //   3557: astore 31
    //   3559: iload 6
    //   3561: istore_3
    //   3562: aload 20
    //   3564: astore 30
    //   3566: aload 22
    //   3568: astore 25
    //   3570: aload 37
    //   3572: astore 27
    //   3574: aload 20
    //   3576: astore 24
    //   3578: aload 22
    //   3580: astore 26
    //   3582: aload 38
    //   3584: astore 28
    //   3586: aload 34
    //   3588: checkcast 517	org/apache/http/client/methods/HttpPost
    //   3591: new 534	org/apache/http/entity/ByteArrayEntity
    //   3594: dup
    //   3595: aload 21
    //   3597: invokespecial 536	org/apache/http/entity/ByteArrayEntity:<init>	([B)V
    //   3600: invokevirtual 540	org/apache/http/client/methods/HttpPost:setEntity	(Lorg/apache/http/HttpEntity;)V
    //   3603: iconst_4
    //   3604: istore_3
    //   3605: aload 20
    //   3607: astore 30
    //   3609: aload 22
    //   3611: astore 25
    //   3613: aload 37
    //   3615: astore 27
    //   3617: aload 20
    //   3619: astore 24
    //   3621: aload 22
    //   3623: astore 26
    //   3625: aload 38
    //   3627: astore 28
    //   3629: aload 22
    //   3631: astore 31
    //   3633: aload 35
    //   3635: astore 29
    //   3637: aload_0
    //   3638: aload_1
    //   3639: invokespecial 542	com/tencent/tencentmap/mapsdk/a/ez:a	(Lcom/tencent/tencentmap/mapsdk/a/fb;)Lorg/apache/http/impl/client/DefaultHttpClient;
    //   3642: astore 23
    //   3644: iconst_5
    //   3645: istore 6
    //   3647: aload 20
    //   3649: astore 30
    //   3651: aload 22
    //   3653: astore 25
    //   3655: aload 23
    //   3657: astore 27
    //   3659: aload 20
    //   3661: astore 24
    //   3663: aload 22
    //   3665: astore 26
    //   3667: aload 23
    //   3669: astore 28
    //   3671: iload 6
    //   3673: istore_3
    //   3674: aload 22
    //   3676: astore 31
    //   3678: aload 23
    //   3680: astore 29
    //   3682: aload 39
    //   3684: invokestatic 232	java/lang/System:currentTimeMillis	()J
    //   3687: lload 16
    //   3689: lsub
    //   3690: l2i
    //   3691: putfield 544	com/tencent/tencentmap/mapsdk/a/fd:g	I
    //   3694: aload 20
    //   3696: astore 30
    //   3698: aload 22
    //   3700: astore 25
    //   3702: aload 23
    //   3704: astore 27
    //   3706: aload 20
    //   3708: astore 24
    //   3710: aload 22
    //   3712: astore 26
    //   3714: aload 23
    //   3716: astore 28
    //   3718: iload 6
    //   3720: istore_3
    //   3721: aload 22
    //   3723: astore 31
    //   3725: aload 23
    //   3727: astore 29
    //   3729: invokestatic 232	java/lang/System:currentTimeMillis	()J
    //   3732: lstore 18
    //   3734: aload 20
    //   3736: astore 30
    //   3738: aload 22
    //   3740: astore 25
    //   3742: aload 23
    //   3744: astore 27
    //   3746: aload 20
    //   3748: astore 24
    //   3750: aload 22
    //   3752: astore 26
    //   3754: aload 23
    //   3756: astore 28
    //   3758: iload 6
    //   3760: istore_3
    //   3761: aload 22
    //   3763: astore 31
    //   3765: aload 23
    //   3767: astore 29
    //   3769: aload 23
    //   3771: aload 34
    //   3773: invokevirtual 548	org/apache/http/impl/client/DefaultHttpClient:execute	(Lorg/apache/http/client/methods/HttpUriRequest;)Lorg/apache/http/HttpResponse;
    //   3776: astore 34
    //   3778: aload 20
    //   3780: astore 30
    //   3782: aload 22
    //   3784: astore 25
    //   3786: aload 23
    //   3788: astore 27
    //   3790: aload 20
    //   3792: astore 24
    //   3794: aload 22
    //   3796: astore 26
    //   3798: aload 23
    //   3800: astore 28
    //   3802: iload 6
    //   3804: istore_3
    //   3805: aload 22
    //   3807: astore 31
    //   3809: aload 23
    //   3811: astore 29
    //   3813: aload 33
    //   3815: invokestatic 232	java/lang/System:currentTimeMillis	()J
    //   3818: lload 18
    //   3820: lsub
    //   3821: l2i
    //   3822: putfield 549	com/tencent/tencentmap/mapsdk/a/fc:g	I
    //   3825: bipush 6
    //   3827: istore 6
    //   3829: aload 20
    //   3831: astore 30
    //   3833: aload 22
    //   3835: astore 25
    //   3837: aload 23
    //   3839: astore 27
    //   3841: aload 20
    //   3843: astore 24
    //   3845: aload 22
    //   3847: astore 26
    //   3849: aload 23
    //   3851: astore 28
    //   3853: iload 6
    //   3855: istore_3
    //   3856: aload 22
    //   3858: astore 31
    //   3860: aload 23
    //   3862: astore 29
    //   3864: ldc_w 271
    //   3867: new 79	java/lang/StringBuilder
    //   3870: dup
    //   3871: ldc_w 551
    //   3874: invokespecial 82	java/lang/StringBuilder:<init>	(Ljava/lang/String;)V
    //   3877: aload 33
    //   3879: getfield 549	com/tencent/tencentmap/mapsdk/a/fc:g	I
    //   3882: invokevirtual 340	java/lang/StringBuilder:append	(I)Ljava/lang/StringBuilder;
    //   3885: invokevirtual 89	java/lang/StringBuilder:toString	()Ljava/lang/String;
    //   3888: invokestatic 364	com/tencent/tencentmap/mapsdk/a/fx:a	(Ljava/lang/String;Ljava/lang/String;)V
    //   3891: aload 20
    //   3893: astore 30
    //   3895: aload 22
    //   3897: astore 25
    //   3899: aload 23
    //   3901: astore 27
    //   3903: aload 20
    //   3905: astore 24
    //   3907: aload 22
    //   3909: astore 26
    //   3911: aload 23
    //   3913: astore 28
    //   3915: iload 6
    //   3917: istore_3
    //   3918: aload 22
    //   3920: astore 31
    //   3922: aload 23
    //   3924: astore 29
    //   3926: aload 34
    //   3928: invokeinterface 557 1 0
    //   3933: invokeinterface 562 1 0
    //   3938: istore 7
    //   3940: aload 20
    //   3942: astore 30
    //   3944: aload 22
    //   3946: astore 25
    //   3948: aload 23
    //   3950: astore 27
    //   3952: aload 20
    //   3954: astore 24
    //   3956: aload 22
    //   3958: astore 26
    //   3960: aload 23
    //   3962: astore 28
    //   3964: iload 6
    //   3966: istore_3
    //   3967: aload 22
    //   3969: astore 31
    //   3971: aload 23
    //   3973: astore 29
    //   3975: aload 33
    //   3977: aload 34
    //   3979: putfield 565	com/tencent/tencentmap/mapsdk/a/fc:j	Lorg/apache/http/HttpResponse;
    //   3982: aload 22
    //   3984: astore 21
    //   3986: aload 34
    //   3988: ifnull +107 -> 4095
    //   3991: aload 20
    //   3993: astore 30
    //   3995: aload 22
    //   3997: astore 25
    //   3999: aload 23
    //   4001: astore 27
    //   4003: aload 20
    //   4005: astore 24
    //   4007: aload 22
    //   4009: astore 26
    //   4011: aload 23
    //   4013: astore 28
    //   4015: aload 22
    //   4017: astore 21
    //   4019: iload 6
    //   4021: istore_3
    //   4022: aload 22
    //   4024: astore 31
    //   4026: aload 23
    //   4028: astore 29
    //   4030: aload 34
    //   4032: ldc_w 567
    //   4035: invokeinterface 571 2 0
    //   4040: ifnull +55 -> 4095
    //   4043: aload 20
    //   4045: astore 30
    //   4047: aload 22
    //   4049: astore 25
    //   4051: aload 23
    //   4053: astore 27
    //   4055: aload 20
    //   4057: astore 24
    //   4059: aload 22
    //   4061: astore 26
    //   4063: aload 23
    //   4065: astore 28
    //   4067: iload 6
    //   4069: istore_3
    //   4070: aload 22
    //   4072: astore 31
    //   4074: aload 23
    //   4076: astore 29
    //   4078: aload 34
    //   4080: ldc_w 567
    //   4083: invokeinterface 571 2 0
    //   4088: invokeinterface 576 1 0
    //   4093: astore 21
    //   4095: aload 20
    //   4097: astore 30
    //   4099: aload 21
    //   4101: astore 25
    //   4103: aload 23
    //   4105: astore 27
    //   4107: aload 20
    //   4109: astore 24
    //   4111: aload 21
    //   4113: astore 26
    //   4115: aload 23
    //   4117: astore 28
    //   4119: iload 6
    //   4121: istore_3
    //   4122: aload 21
    //   4124: astore 31
    //   4126: aload 23
    //   4128: astore 29
    //   4130: aload 39
    //   4132: aload 33
    //   4134: getfield 549	com/tencent/tencentmap/mapsdk/a/fc:g	I
    //   4137: putfield 578	com/tencent/tencentmap/mapsdk/a/fd:h	I
    //   4140: bipush 7
    //   4142: istore_3
    //   4143: iload 7
    //   4145: lookupswitch	default:+3912->8057, 200:+467->4612, 204:+3381->7526, 301:+2257->6402, 302:+2257->6402, 303:+2257->6402, 307:+2257->6402, 408:+3381->7526, 502:+3381->7526, 503:+3381->7526, 504:+3381->7526
    //   4236: aload 20
    //   4238: astore 30
    //   4240: aload 21
    //   4242: astore 25
    //   4244: aload 23
    //   4246: astore 27
    //   4248: aload 20
    //   4250: astore 24
    //   4252: aload 21
    //   4254: astore 26
    //   4256: aload 23
    //   4258: astore 28
    //   4260: aload 21
    //   4262: astore 31
    //   4264: aload 23
    //   4266: astore 29
    //   4268: aload 33
    //   4270: iload 7
    //   4272: putfield 281	com/tencent/tencentmap/mapsdk/a/fc:a	I
    //   4275: aload 39
    //   4277: new 79	java/lang/StringBuilder
    //   4280: dup
    //   4281: invokespecial 346	java/lang/StringBuilder:<init>	()V
    //   4284: aload_1
    //   4285: invokevirtual 443	com/tencent/tencentmap/mapsdk/a/fb:a	()Ljava/lang/String;
    //   4288: invokevirtual 86	java/lang/StringBuilder:append	(Ljava/lang/String;)Ljava/lang/StringBuilder;
    //   4291: ldc_w 445
    //   4294: invokevirtual 86	java/lang/StringBuilder:append	(Ljava/lang/String;)Ljava/lang/StringBuilder;
    //   4297: iload 4
    //   4299: invokevirtual 340	java/lang/StringBuilder:append	(I)Ljava/lang/StringBuilder;
    //   4302: invokevirtual 89	java/lang/StringBuilder:toString	()Ljava/lang/String;
    //   4305: putfield 447	com/tencent/tencentmap/mapsdk/a/fd:p	Ljava/lang/String;
    //   4308: aload 39
    //   4310: iload 4
    //   4312: putfield 450	com/tencent/tencentmap/mapsdk/a/fd:s	I
    //   4315: aload 20
    //   4317: invokestatic 51	android/text/TextUtils:isEmpty	(Ljava/lang/CharSequence;)Z
    //   4320: ifeq +3248 -> 7568
    //   4323: iconst_0
    //   4324: istore_3
    //   4325: iload 4
    //   4327: iconst_1
    //   4328: iadd
    //   4329: istore 4
    //   4331: invokestatic 454	com/tencent/tencentmap/mapsdk/a/em:b	()Ljava/lang/String;
    //   4334: invokestatic 51	android/text/TextUtils:isEmpty	(Ljava/lang/CharSequence;)Z
    //   4337: ifne +198 -> 4535
    //   4340: aload 33
    //   4342: getfield 281	com/tencent/tencentmap/mapsdk/a/fc:a	I
    //   4345: bipush -21
    //   4347: if_icmpeq +188 -> 4535
    //   4350: aload 33
    //   4352: invokestatic 232	java/lang/System:currentTimeMillis	()J
    //   4355: aload_1
    //   4356: invokevirtual 263	com/tencent/tencentmap/mapsdk/a/fb:q	()J
    //   4359: lsub
    //   4360: l2i
    //   4361: putfield 457	com/tencent/tencentmap/mapsdk/a/fc:k	I
    //   4364: aload 39
    //   4366: aload 33
    //   4368: getfield 281	com/tencent/tencentmap/mapsdk/a/fc:a	I
    //   4371: putfield 458	com/tencent/tencentmap/mapsdk/a/fd:k	I
    //   4374: aload 39
    //   4376: aload 21
    //   4378: putfield 461	com/tencent/tencentmap/mapsdk/a/fd:C	Ljava/lang/String;
    //   4381: aload 39
    //   4383: aload 33
    //   4385: getfield 457	com/tencent/tencentmap/mapsdk/a/fc:k	I
    //   4388: putfield 463	com/tencent/tencentmap/mapsdk/a/fd:l	I
    //   4391: aload 39
    //   4393: invokestatic 232	java/lang/System:currentTimeMillis	()J
    //   4396: lload 16
    //   4398: lsub
    //   4399: l2i
    //   4400: putfield 466	com/tencent/tencentmap/mapsdk/a/fd:m	I
    //   4403: aload 39
    //   4405: aload 20
    //   4407: putfield 468	com/tencent/tencentmap/mapsdk/a/fd:f	Ljava/lang/String;
    //   4410: aload_1
    //   4411: invokevirtual 366	com/tencent/tencentmap/mapsdk/a/fb:b	()Z
    //   4414: ifne +3183 -> 7597
    //   4417: aload_1
    //   4418: invokevirtual 471	com/tencent/tencentmap/mapsdk/a/fb:h	()[B
    //   4421: ifnull +3176 -> 7597
    //   4424: aload 39
    //   4426: aload_1
    //   4427: invokevirtual 471	com/tencent/tencentmap/mapsdk/a/fb:h	()[B
    //   4430: arraylength
    //   4431: i2l
    //   4432: putfield 474	com/tencent/tencentmap/mapsdk/a/fd:n	J
    //   4435: aload 39
    //   4437: iload 13
    //   4439: putfield 477	com/tencent/tencentmap/mapsdk/a/fd:z	Z
    //   4442: iload 13
    //   4444: ifeq +17 -> 4461
    //   4447: aload 39
    //   4449: getfield 458	com/tencent/tencentmap/mapsdk/a/fd:k	I
    //   4452: ifeq +9 -> 4461
    //   4455: aload 39
    //   4457: iconst_1
    //   4458: putfield 480	com/tencent/tencentmap/mapsdk/a/fd:w	I
    //   4461: aload 39
    //   4463: aload_1
    //   4464: invokevirtual 482	com/tencent/tencentmap/mapsdk/a/fb:m	()Z
    //   4467: putfield 485	com/tencent/tencentmap/mapsdk/a/fd:B	Z
    //   4470: invokestatic 490	com/tencent/tencentmap/mapsdk/a/el:a	()Lcom/tencent/tencentmap/mapsdk/a/el;
    //   4473: new 492	com/tencent/tencentmap/mapsdk/a/fe
    //   4476: dup
    //   4477: aload 39
    //   4479: invokespecial 495	com/tencent/tencentmap/mapsdk/a/fe:<init>	(Lcom/tencent/tencentmap/mapsdk/a/fd;)V
    //   4482: invokevirtual 498	com/tencent/tencentmap/mapsdk/a/el:a	(Ljava/lang/Runnable;)V
    //   4485: aload_1
    //   4486: aload 39
    //   4488: invokevirtual 500	com/tencent/tencentmap/mapsdk/a/fb:a	(Lcom/tencent/tencentmap/mapsdk/a/fd;)V
    //   4491: aload 33
    //   4493: aload 39
    //   4495: getfield 313	com/tencent/tencentmap/mapsdk/a/fd:a	Lcom/tencent/tencentmap/mapsdk/a/ep;
    //   4498: invokevirtual 335	com/tencent/tencentmap/mapsdk/a/ep:a	()Ljava/lang/String;
    //   4501: putfield 502	com/tencent/tencentmap/mapsdk/a/fc:l	Ljava/lang/String;
    //   4504: aload 33
    //   4506: aload 39
    //   4508: invokevirtual 503	com/tencent/tencentmap/mapsdk/a/fd:toString	()Ljava/lang/String;
    //   4511: putfield 504	com/tencent/tencentmap/mapsdk/a/fc:d	Ljava/lang/String;
    //   4514: aload 33
    //   4516: aload 39
    //   4518: getfield 447	com/tencent/tencentmap/mapsdk/a/fd:p	Ljava/lang/String;
    //   4521: putfield 506	com/tencent/tencentmap/mapsdk/a/fc:m	Ljava/lang/String;
    //   4524: ldc_w 508
    //   4527: aload 39
    //   4529: invokevirtual 503	com/tencent/tencentmap/mapsdk/a/fd:toString	()Ljava/lang/String;
    //   4532: invokestatic 510	com/tencent/tencentmap/mapsdk/a/fx:b	(Ljava/lang/String;Ljava/lang/String;)V
    //   4535: aload 23
    //   4537: ifnull +15 -> 4552
    //   4540: aload_1
    //   4541: invokevirtual 269	com/tencent/tencentmap/mapsdk/a/fb:l	()Z
    //   4544: ifne +8 -> 4552
    //   4547: aload_1
    //   4548: invokevirtual 511	com/tencent/tencentmap/mapsdk/a/fb:f	()Z
    //   4551: pop
    //   4552: lload 16
    //   4554: invokestatic 513	com/tencent/tencentmap/mapsdk/a/ez:a	(J)Z
    //   4557: istore 13
    //   4559: aload 33
    //   4561: astore 23
    //   4563: aload 33
    //   4565: getfield 281	com/tencent/tencentmap/mapsdk/a/fc:a	I
    //   4568: bipush -4
    //   4570: if_icmpeq -4437 -> 133
    //   4573: aload 33
    //   4575: astore 23
    //   4577: aload 33
    //   4579: getfield 281	com/tencent/tencentmap/mapsdk/a/fc:a	I
    //   4582: bipush -17
    //   4584: if_icmpeq -4451 -> 133
    //   4587: aload 33
    //   4589: astore 23
    //   4591: iload 13
    //   4593: ifne -4460 -> 133
    //   4596: iload_3
    //   4597: istore 5
    //   4599: iload_2
    //   4600: istore_3
    //   4601: aload 21
    //   4603: astore 22
    //   4605: aload 33
    //   4607: astore 23
    //   4609: goto -4526 -> 83
    //   4612: aload 20
    //   4614: astore 30
    //   4616: aload 21
    //   4618: astore 25
    //   4620: aload 23
    //   4622: astore 27
    //   4624: aload 20
    //   4626: astore 24
    //   4628: aload 21
    //   4630: astore 26
    //   4632: aload 23
    //   4634: astore 28
    //   4636: aload 21
    //   4638: astore 31
    //   4640: aload 23
    //   4642: astore 29
    //   4644: aload 34
    //   4646: invokeinterface 582 1 0
    //   4651: invokeinterface 588 1 0
    //   4656: astore 22
    //   4658: iconst_1
    //   4659: istore 15
    //   4661: iconst_1
    //   4662: istore 13
    //   4664: bipush 8
    //   4666: istore 6
    //   4668: iload 6
    //   4670: istore_3
    //   4671: aload_1
    //   4672: invokevirtual 511	com/tencent/tencentmap/mapsdk/a/fb:f	()Z
    //   4675: ifeq +1333 -> 6008
    //   4678: iconst_0
    //   4679: istore 7
    //   4681: iload 6
    //   4683: istore_3
    //   4684: aload_1
    //   4685: invokevirtual 590	com/tencent/tencentmap/mapsdk/a/fb:i	()I
    //   4688: istore 11
    //   4690: iload 6
    //   4692: istore_3
    //   4693: iload 11
    //   4695: newarray <illegal type>
    //   4697: astore 24
    //   4699: iload 6
    //   4701: istore_3
    //   4702: invokestatic 232	java/lang/System:currentTimeMillis	()J
    //   4705: lstore 18
    //   4707: iload 7
    //   4709: iload 11
    //   4711: if_icmpge +427 -> 5138
    //   4714: iload 6
    //   4716: istore_3
    //   4717: aload 22
    //   4719: aload 24
    //   4721: iload 7
    //   4723: iload 11
    //   4725: iload 7
    //   4727: isub
    //   4728: invokevirtual 596	java/io/InputStream:read	([BII)I
    //   4731: istore 12
    //   4733: iload 12
    //   4735: iconst_m1
    //   4736: if_icmpeq +402 -> 5138
    //   4739: iload 7
    //   4741: iload 12
    //   4743: iadd
    //   4744: istore 7
    //   4746: goto -39 -> 4707
    //   4749: astore 24
    //   4751: aload 22
    //   4753: invokevirtual 599	java/io/InputStream:close	()V
    //   4756: iload 6
    //   4758: istore_3
    //   4759: aload 33
    //   4761: bipush -8
    //   4763: putfield 281	com/tencent/tencentmap/mapsdk/a/fc:a	I
    //   4766: iload 6
    //   4768: istore_3
    //   4769: aload 39
    //   4771: new 79	java/lang/StringBuilder
    //   4774: dup
    //   4775: ldc_w 601
    //   4778: invokespecial 82	java/lang/StringBuilder:<init>	(Ljava/lang/String;)V
    //   4781: iload 11
    //   4783: invokevirtual 340	java/lang/StringBuilder:append	(I)Ljava/lang/StringBuilder;
    //   4786: invokevirtual 89	java/lang/StringBuilder:toString	()Ljava/lang/String;
    //   4789: putfield 430	com/tencent/tencentmap/mapsdk/a/fd:r	Ljava/lang/String;
    //   4792: iload 6
    //   4794: istore_3
    //   4795: aload 39
    //   4797: iload 11
    //   4799: i2l
    //   4800: putfield 603	com/tencent/tencentmap/mapsdk/a/fd:o	J
    //   4803: aload 39
    //   4805: new 79	java/lang/StringBuilder
    //   4808: dup
    //   4809: invokespecial 346	java/lang/StringBuilder:<init>	()V
    //   4812: aload_1
    //   4813: invokevirtual 443	com/tencent/tencentmap/mapsdk/a/fb:a	()Ljava/lang/String;
    //   4816: invokevirtual 86	java/lang/StringBuilder:append	(Ljava/lang/String;)Ljava/lang/StringBuilder;
    //   4819: ldc_w 445
    //   4822: invokevirtual 86	java/lang/StringBuilder:append	(Ljava/lang/String;)Ljava/lang/StringBuilder;
    //   4825: iload 4
    //   4827: invokevirtual 340	java/lang/StringBuilder:append	(I)Ljava/lang/StringBuilder;
    //   4830: invokevirtual 89	java/lang/StringBuilder:toString	()Ljava/lang/String;
    //   4833: putfield 447	com/tencent/tencentmap/mapsdk/a/fd:p	Ljava/lang/String;
    //   4836: aload 39
    //   4838: iload 4
    //   4840: putfield 450	com/tencent/tencentmap/mapsdk/a/fd:s	I
    //   4843: aload 20
    //   4845: invokestatic 51	android/text/TextUtils:isEmpty	(Ljava/lang/CharSequence;)Z
    //   4848: ifne +19 -> 4867
    //   4851: iload 5
    //   4853: iconst_1
    //   4854: iadd
    //   4855: bipush 6
    //   4857: if_icmple +10 -> 4867
    //   4860: aload 33
    //   4862: bipush -5
    //   4864: putfield 281	com/tencent/tencentmap/mapsdk/a/fc:a	I
    //   4867: invokestatic 454	com/tencent/tencentmap/mapsdk/a/em:b	()Ljava/lang/String;
    //   4870: invokestatic 51	android/text/TextUtils:isEmpty	(Ljava/lang/CharSequence;)Z
    //   4873: ifne +192 -> 5065
    //   4876: aload 33
    //   4878: getfield 281	com/tencent/tencentmap/mapsdk/a/fc:a	I
    //   4881: bipush -21
    //   4883: if_icmpeq +182 -> 5065
    //   4886: aload 33
    //   4888: invokestatic 232	java/lang/System:currentTimeMillis	()J
    //   4891: aload_1
    //   4892: invokevirtual 263	com/tencent/tencentmap/mapsdk/a/fb:q	()J
    //   4895: lsub
    //   4896: l2i
    //   4897: putfield 457	com/tencent/tencentmap/mapsdk/a/fc:k	I
    //   4900: aload 39
    //   4902: aload 33
    //   4904: getfield 281	com/tencent/tencentmap/mapsdk/a/fc:a	I
    //   4907: putfield 458	com/tencent/tencentmap/mapsdk/a/fd:k	I
    //   4910: aload 39
    //   4912: aload 21
    //   4914: putfield 461	com/tencent/tencentmap/mapsdk/a/fd:C	Ljava/lang/String;
    //   4917: aload 39
    //   4919: aload 33
    //   4921: getfield 457	com/tencent/tencentmap/mapsdk/a/fc:k	I
    //   4924: putfield 463	com/tencent/tencentmap/mapsdk/a/fd:l	I
    //   4927: aload 39
    //   4929: invokestatic 232	java/lang/System:currentTimeMillis	()J
    //   4932: lload 16
    //   4934: lsub
    //   4935: l2i
    //   4936: putfield 466	com/tencent/tencentmap/mapsdk/a/fd:m	I
    //   4939: aload 39
    //   4941: aload 20
    //   4943: putfield 468	com/tencent/tencentmap/mapsdk/a/fd:f	Ljava/lang/String;
    //   4946: aload_1
    //   4947: invokevirtual 366	com/tencent/tencentmap/mapsdk/a/fb:b	()Z
    //   4950: ifne +179 -> 5129
    //   4953: aload_1
    //   4954: invokevirtual 471	com/tencent/tencentmap/mapsdk/a/fb:h	()[B
    //   4957: ifnull +172 -> 5129
    //   4960: aload 39
    //   4962: aload_1
    //   4963: invokevirtual 471	com/tencent/tencentmap/mapsdk/a/fb:h	()[B
    //   4966: arraylength
    //   4967: i2l
    //   4968: putfield 474	com/tencent/tencentmap/mapsdk/a/fd:n	J
    //   4971: aload 39
    //   4973: iconst_1
    //   4974: putfield 477	com/tencent/tencentmap/mapsdk/a/fd:z	Z
    //   4977: aload 39
    //   4979: getfield 458	com/tencent/tencentmap/mapsdk/a/fd:k	I
    //   4982: ifeq +9 -> 4991
    //   4985: aload 39
    //   4987: iconst_1
    //   4988: putfield 480	com/tencent/tencentmap/mapsdk/a/fd:w	I
    //   4991: aload 39
    //   4993: aload_1
    //   4994: invokevirtual 482	com/tencent/tencentmap/mapsdk/a/fb:m	()Z
    //   4997: putfield 485	com/tencent/tencentmap/mapsdk/a/fd:B	Z
    //   5000: invokestatic 490	com/tencent/tencentmap/mapsdk/a/el:a	()Lcom/tencent/tencentmap/mapsdk/a/el;
    //   5003: new 492	com/tencent/tencentmap/mapsdk/a/fe
    //   5006: dup
    //   5007: aload 39
    //   5009: invokespecial 495	com/tencent/tencentmap/mapsdk/a/fe:<init>	(Lcom/tencent/tencentmap/mapsdk/a/fd;)V
    //   5012: invokevirtual 498	com/tencent/tencentmap/mapsdk/a/el:a	(Ljava/lang/Runnable;)V
    //   5015: aload_1
    //   5016: aload 39
    //   5018: invokevirtual 500	com/tencent/tencentmap/mapsdk/a/fb:a	(Lcom/tencent/tencentmap/mapsdk/a/fd;)V
    //   5021: aload 33
    //   5023: aload 39
    //   5025: getfield 313	com/tencent/tencentmap/mapsdk/a/fd:a	Lcom/tencent/tencentmap/mapsdk/a/ep;
    //   5028: invokevirtual 335	com/tencent/tencentmap/mapsdk/a/ep:a	()Ljava/lang/String;
    //   5031: putfield 502	com/tencent/tencentmap/mapsdk/a/fc:l	Ljava/lang/String;
    //   5034: aload 33
    //   5036: aload 39
    //   5038: invokevirtual 503	com/tencent/tencentmap/mapsdk/a/fd:toString	()Ljava/lang/String;
    //   5041: putfield 504	com/tencent/tencentmap/mapsdk/a/fc:d	Ljava/lang/String;
    //   5044: aload 33
    //   5046: aload 39
    //   5048: getfield 447	com/tencent/tencentmap/mapsdk/a/fd:p	Ljava/lang/String;
    //   5051: putfield 506	com/tencent/tencentmap/mapsdk/a/fc:m	Ljava/lang/String;
    //   5054: ldc_w 508
    //   5057: aload 39
    //   5059: invokevirtual 503	com/tencent/tencentmap/mapsdk/a/fd:toString	()Ljava/lang/String;
    //   5062: invokestatic 510	com/tencent/tencentmap/mapsdk/a/fx:b	(Ljava/lang/String;Ljava/lang/String;)V
    //   5065: aload 23
    //   5067: ifnull +15 -> 5082
    //   5070: aload_1
    //   5071: invokevirtual 269	com/tencent/tencentmap/mapsdk/a/fb:l	()Z
    //   5074: ifne +8 -> 5082
    //   5077: aload_1
    //   5078: invokevirtual 511	com/tencent/tencentmap/mapsdk/a/fb:f	()Z
    //   5081: pop
    //   5082: lload 16
    //   5084: invokestatic 513	com/tencent/tencentmap/mapsdk/a/ez:a	(J)Z
    //   5087: istore 13
    //   5089: aload 33
    //   5091: astore 23
    //   5093: aload 33
    //   5095: getfield 281	com/tencent/tencentmap/mapsdk/a/fc:a	I
    //   5098: bipush -4
    //   5100: if_icmpeq -4967 -> 133
    //   5103: aload 33
    //   5105: astore 23
    //   5107: aload 33
    //   5109: getfield 281	com/tencent/tencentmap/mapsdk/a/fc:a	I
    //   5112: bipush -17
    //   5114: if_icmpeq -4981 -> 133
    //   5117: aload 33
    //   5119: astore 23
    //   5121: iload 13
    //   5123: ifeq -4990 -> 133
    //   5126: aload 33
    //   5128: areturn
    //   5129: aload 39
    //   5131: lconst_0
    //   5132: putfield 474	com/tencent/tencentmap/mapsdk/a/fd:n	J
    //   5135: goto -164 -> 4971
    //   5138: bipush 9
    //   5140: istore 6
    //   5142: iload 6
    //   5144: istore_3
    //   5145: aload 33
    //   5147: invokestatic 232	java/lang/System:currentTimeMillis	()J
    //   5150: lload 18
    //   5152: lsub
    //   5153: l2i
    //   5154: putfield 604	com/tencent/tencentmap/mapsdk/a/fc:h	I
    //   5157: iload 6
    //   5159: istore_3
    //   5160: aload 39
    //   5162: aload 33
    //   5164: getfield 604	com/tencent/tencentmap/mapsdk/a/fc:h	I
    //   5167: putfield 606	com/tencent/tencentmap/mapsdk/a/fd:j	I
    //   5170: iload 6
    //   5172: istore_3
    //   5173: aload 39
    //   5175: iload 7
    //   5177: i2l
    //   5178: putfield 603	com/tencent/tencentmap/mapsdk/a/fd:o	J
    //   5181: iload 7
    //   5183: iload 11
    //   5185: if_icmplt +393 -> 5578
    //   5188: iload 6
    //   5190: istore_3
    //   5191: aload 39
    //   5193: new 79	java/lang/StringBuilder
    //   5196: dup
    //   5197: ldc_w 608
    //   5200: invokespecial 82	java/lang/StringBuilder:<init>	(Ljava/lang/String;)V
    //   5203: iload 7
    //   5205: invokevirtual 340	java/lang/StringBuilder:append	(I)Ljava/lang/StringBuilder;
    //   5208: invokevirtual 89	java/lang/StringBuilder:toString	()Ljava/lang/String;
    //   5211: putfield 430	com/tencent/tencentmap/mapsdk/a/fd:r	Ljava/lang/String;
    //   5214: iload 6
    //   5216: istore_3
    //   5217: aload 33
    //   5219: iconst_m1
    //   5220: putfield 281	com/tencent/tencentmap/mapsdk/a/fc:a	I
    //   5223: aload 22
    //   5225: invokevirtual 599	java/io/InputStream:close	()V
    //   5228: iload 6
    //   5230: istore_3
    //   5231: aload 33
    //   5233: getfield 281	com/tencent/tencentmap/mapsdk/a/fc:a	I
    //   5236: ifne +2814 -> 8050
    //   5239: iload 6
    //   5241: istore_3
    //   5242: aload_1
    //   5243: invokevirtual 269	com/tencent/tencentmap/mapsdk/a/fb:l	()Z
    //   5246: istore 15
    //   5248: iload 15
    //   5250: ifeq +808 -> 6058
    //   5253: aload 39
    //   5255: new 79	java/lang/StringBuilder
    //   5258: dup
    //   5259: invokespecial 346	java/lang/StringBuilder:<init>	()V
    //   5262: aload_1
    //   5263: invokevirtual 443	com/tencent/tencentmap/mapsdk/a/fb:a	()Ljava/lang/String;
    //   5266: invokevirtual 86	java/lang/StringBuilder:append	(Ljava/lang/String;)Ljava/lang/StringBuilder;
    //   5269: ldc_w 445
    //   5272: invokevirtual 86	java/lang/StringBuilder:append	(Ljava/lang/String;)Ljava/lang/StringBuilder;
    //   5275: iload 4
    //   5277: invokevirtual 340	java/lang/StringBuilder:append	(I)Ljava/lang/StringBuilder;
    //   5280: invokevirtual 89	java/lang/StringBuilder:toString	()Ljava/lang/String;
    //   5283: putfield 447	com/tencent/tencentmap/mapsdk/a/fd:p	Ljava/lang/String;
    //   5286: aload 39
    //   5288: iload 4
    //   5290: putfield 450	com/tencent/tencentmap/mapsdk/a/fd:s	I
    //   5293: aload 20
    //   5295: invokestatic 51	android/text/TextUtils:isEmpty	(Ljava/lang/CharSequence;)Z
    //   5298: ifne +19 -> 5317
    //   5301: iload 5
    //   5303: iconst_1
    //   5304: iadd
    //   5305: bipush 6
    //   5307: if_icmple +10 -> 5317
    //   5310: aload 33
    //   5312: bipush -5
    //   5314: putfield 281	com/tencent/tencentmap/mapsdk/a/fc:a	I
    //   5317: invokestatic 454	com/tencent/tencentmap/mapsdk/a/em:b	()Ljava/lang/String;
    //   5320: invokestatic 51	android/text/TextUtils:isEmpty	(Ljava/lang/CharSequence;)Z
    //   5323: ifne +192 -> 5515
    //   5326: aload 33
    //   5328: getfield 281	com/tencent/tencentmap/mapsdk/a/fc:a	I
    //   5331: bipush -21
    //   5333: if_icmpeq +182 -> 5515
    //   5336: aload 33
    //   5338: invokestatic 232	java/lang/System:currentTimeMillis	()J
    //   5341: aload_1
    //   5342: invokevirtual 263	com/tencent/tencentmap/mapsdk/a/fb:q	()J
    //   5345: lsub
    //   5346: l2i
    //   5347: putfield 457	com/tencent/tencentmap/mapsdk/a/fc:k	I
    //   5350: aload 39
    //   5352: aload 33
    //   5354: getfield 281	com/tencent/tencentmap/mapsdk/a/fc:a	I
    //   5357: putfield 458	com/tencent/tencentmap/mapsdk/a/fd:k	I
    //   5360: aload 39
    //   5362: aload 21
    //   5364: putfield 461	com/tencent/tencentmap/mapsdk/a/fd:C	Ljava/lang/String;
    //   5367: aload 39
    //   5369: aload 33
    //   5371: getfield 457	com/tencent/tencentmap/mapsdk/a/fc:k	I
    //   5374: putfield 463	com/tencent/tencentmap/mapsdk/a/fd:l	I
    //   5377: aload 39
    //   5379: invokestatic 232	java/lang/System:currentTimeMillis	()J
    //   5382: lload 16
    //   5384: lsub
    //   5385: l2i
    //   5386: putfield 466	com/tencent/tencentmap/mapsdk/a/fd:m	I
    //   5389: aload 39
    //   5391: aload 20
    //   5393: putfield 468	com/tencent/tencentmap/mapsdk/a/fd:f	Ljava/lang/String;
    //   5396: aload_1
    //   5397: invokevirtual 366	com/tencent/tencentmap/mapsdk/a/fb:b	()Z
    //   5400: ifne +649 -> 6049
    //   5403: aload_1
    //   5404: invokevirtual 471	com/tencent/tencentmap/mapsdk/a/fb:h	()[B
    //   5407: ifnull +642 -> 6049
    //   5410: aload 39
    //   5412: aload_1
    //   5413: invokevirtual 471	com/tencent/tencentmap/mapsdk/a/fb:h	()[B
    //   5416: arraylength
    //   5417: i2l
    //   5418: putfield 474	com/tencent/tencentmap/mapsdk/a/fd:n	J
    //   5421: aload 39
    //   5423: iconst_1
    //   5424: putfield 477	com/tencent/tencentmap/mapsdk/a/fd:z	Z
    //   5427: aload 39
    //   5429: getfield 458	com/tencent/tencentmap/mapsdk/a/fd:k	I
    //   5432: ifeq +9 -> 5441
    //   5435: aload 39
    //   5437: iconst_1
    //   5438: putfield 480	com/tencent/tencentmap/mapsdk/a/fd:w	I
    //   5441: aload 39
    //   5443: aload_1
    //   5444: invokevirtual 482	com/tencent/tencentmap/mapsdk/a/fb:m	()Z
    //   5447: putfield 485	com/tencent/tencentmap/mapsdk/a/fd:B	Z
    //   5450: invokestatic 490	com/tencent/tencentmap/mapsdk/a/el:a	()Lcom/tencent/tencentmap/mapsdk/a/el;
    //   5453: new 492	com/tencent/tencentmap/mapsdk/a/fe
    //   5456: dup
    //   5457: aload 39
    //   5459: invokespecial 495	com/tencent/tencentmap/mapsdk/a/fe:<init>	(Lcom/tencent/tencentmap/mapsdk/a/fd;)V
    //   5462: invokevirtual 498	com/tencent/tencentmap/mapsdk/a/el:a	(Ljava/lang/Runnable;)V
    //   5465: aload_1
    //   5466: aload 39
    //   5468: invokevirtual 500	com/tencent/tencentmap/mapsdk/a/fb:a	(Lcom/tencent/tencentmap/mapsdk/a/fd;)V
    //   5471: aload 33
    //   5473: aload 39
    //   5475: getfield 313	com/tencent/tencentmap/mapsdk/a/fd:a	Lcom/tencent/tencentmap/mapsdk/a/ep;
    //   5478: invokevirtual 335	com/tencent/tencentmap/mapsdk/a/ep:a	()Ljava/lang/String;
    //   5481: putfield 502	com/tencent/tencentmap/mapsdk/a/fc:l	Ljava/lang/String;
    //   5484: aload 33
    //   5486: aload 39
    //   5488: invokevirtual 503	com/tencent/tencentmap/mapsdk/a/fd:toString	()Ljava/lang/String;
    //   5491: putfield 504	com/tencent/tencentmap/mapsdk/a/fc:d	Ljava/lang/String;
    //   5494: aload 33
    //   5496: aload 39
    //   5498: getfield 447	com/tencent/tencentmap/mapsdk/a/fd:p	Ljava/lang/String;
    //   5501: putfield 506	com/tencent/tencentmap/mapsdk/a/fc:m	Ljava/lang/String;
    //   5504: ldc_w 508
    //   5507: aload 39
    //   5509: invokevirtual 503	com/tencent/tencentmap/mapsdk/a/fd:toString	()Ljava/lang/String;
    //   5512: invokestatic 510	com/tencent/tencentmap/mapsdk/a/fx:b	(Ljava/lang/String;Ljava/lang/String;)V
    //   5515: aload 23
    //   5517: ifnull +15 -> 5532
    //   5520: aload_1
    //   5521: invokevirtual 269	com/tencent/tencentmap/mapsdk/a/fb:l	()Z
    //   5524: ifne +8 -> 5532
    //   5527: aload_1
    //   5528: invokevirtual 511	com/tencent/tencentmap/mapsdk/a/fb:f	()Z
    //   5531: pop
    //   5532: lload 16
    //   5534: invokestatic 513	com/tencent/tencentmap/mapsdk/a/ez:a	(J)Z
    //   5537: istore 13
    //   5539: aload 33
    //   5541: astore 23
    //   5543: aload 33
    //   5545: getfield 281	com/tencent/tencentmap/mapsdk/a/fc:a	I
    //   5548: bipush -4
    //   5550: if_icmpeq -5417 -> 133
    //   5553: aload 33
    //   5555: astore 23
    //   5557: aload 33
    //   5559: getfield 281	com/tencent/tencentmap/mapsdk/a/fc:a	I
    //   5562: bipush -17
    //   5564: if_icmpeq -5431 -> 133
    //   5567: aload 33
    //   5569: astore 23
    //   5571: iload 13
    //   5573: ifne -5440 -> 133
    //   5576: aconst_null
    //   5577: areturn
    //   5578: iload 6
    //   5580: istore_3
    //   5581: aload 33
    //   5583: iload 7
    //   5585: newarray <illegal type>
    //   5587: putfield 611	com/tencent/tencentmap/mapsdk/a/fc:e	[B
    //   5590: iload 6
    //   5592: istore_3
    //   5593: aload 24
    //   5595: iconst_0
    //   5596: aload 33
    //   5598: getfield 611	com/tencent/tencentmap/mapsdk/a/fc:e	[B
    //   5601: iconst_0
    //   5602: iload 7
    //   5604: invokestatic 615	java/lang/System:arraycopy	(Ljava/lang/Object;ILjava/lang/Object;II)V
    //   5607: iload 6
    //   5609: istore_3
    //   5610: aload 33
    //   5612: iconst_0
    //   5613: putfield 281	com/tencent/tencentmap/mapsdk/a/fc:a	I
    //   5616: goto -393 -> 5223
    //   5619: astore 22
    //   5621: iconst_1
    //   5622: istore 13
    //   5624: iload_2
    //   5625: istore 7
    //   5627: goto -4196 -> 1431
    //   5630: astore 24
    //   5632: aload 22
    //   5634: invokevirtual 599	java/io/InputStream:close	()V
    //   5637: iload 6
    //   5639: istore_3
    //   5640: aload 33
    //   5642: bipush -8
    //   5644: putfield 281	com/tencent/tencentmap/mapsdk/a/fc:a	I
    //   5647: iload 6
    //   5649: istore_3
    //   5650: aload 39
    //   5652: new 79	java/lang/StringBuilder
    //   5655: dup
    //   5656: ldc_w 601
    //   5659: invokespecial 82	java/lang/StringBuilder:<init>	(Ljava/lang/String;)V
    //   5662: iload 11
    //   5664: invokevirtual 340	java/lang/StringBuilder:append	(I)Ljava/lang/StringBuilder;
    //   5667: invokevirtual 89	java/lang/StringBuilder:toString	()Ljava/lang/String;
    //   5670: putfield 430	com/tencent/tencentmap/mapsdk/a/fd:r	Ljava/lang/String;
    //   5673: aload 39
    //   5675: new 79	java/lang/StringBuilder
    //   5678: dup
    //   5679: invokespecial 346	java/lang/StringBuilder:<init>	()V
    //   5682: aload_1
    //   5683: invokevirtual 443	com/tencent/tencentmap/mapsdk/a/fb:a	()Ljava/lang/String;
    //   5686: invokevirtual 86	java/lang/StringBuilder:append	(Ljava/lang/String;)Ljava/lang/StringBuilder;
    //   5689: ldc_w 445
    //   5692: invokevirtual 86	java/lang/StringBuilder:append	(Ljava/lang/String;)Ljava/lang/StringBuilder;
    //   5695: iload 4
    //   5697: invokevirtual 340	java/lang/StringBuilder:append	(I)Ljava/lang/StringBuilder;
    //   5700: invokevirtual 89	java/lang/StringBuilder:toString	()Ljava/lang/String;
    //   5703: putfield 447	com/tencent/tencentmap/mapsdk/a/fd:p	Ljava/lang/String;
    //   5706: aload 39
    //   5708: iload 4
    //   5710: putfield 450	com/tencent/tencentmap/mapsdk/a/fd:s	I
    //   5713: aload 20
    //   5715: invokestatic 51	android/text/TextUtils:isEmpty	(Ljava/lang/CharSequence;)Z
    //   5718: ifne +19 -> 5737
    //   5721: iload 5
    //   5723: iconst_1
    //   5724: iadd
    //   5725: bipush 6
    //   5727: if_icmple +10 -> 5737
    //   5730: aload 33
    //   5732: bipush -5
    //   5734: putfield 281	com/tencent/tencentmap/mapsdk/a/fc:a	I
    //   5737: invokestatic 454	com/tencent/tencentmap/mapsdk/a/em:b	()Ljava/lang/String;
    //   5740: invokestatic 51	android/text/TextUtils:isEmpty	(Ljava/lang/CharSequence;)Z
    //   5743: ifne +192 -> 5935
    //   5746: aload 33
    //   5748: getfield 281	com/tencent/tencentmap/mapsdk/a/fc:a	I
    //   5751: bipush -21
    //   5753: if_icmpeq +182 -> 5935
    //   5756: aload 33
    //   5758: invokestatic 232	java/lang/System:currentTimeMillis	()J
    //   5761: aload_1
    //   5762: invokevirtual 263	com/tencent/tencentmap/mapsdk/a/fb:q	()J
    //   5765: lsub
    //   5766: l2i
    //   5767: putfield 457	com/tencent/tencentmap/mapsdk/a/fc:k	I
    //   5770: aload 39
    //   5772: aload 33
    //   5774: getfield 281	com/tencent/tencentmap/mapsdk/a/fc:a	I
    //   5777: putfield 458	com/tencent/tencentmap/mapsdk/a/fd:k	I
    //   5780: aload 39
    //   5782: aload 21
    //   5784: putfield 461	com/tencent/tencentmap/mapsdk/a/fd:C	Ljava/lang/String;
    //   5787: aload 39
    //   5789: aload 33
    //   5791: getfield 457	com/tencent/tencentmap/mapsdk/a/fc:k	I
    //   5794: putfield 463	com/tencent/tencentmap/mapsdk/a/fd:l	I
    //   5797: aload 39
    //   5799: invokestatic 232	java/lang/System:currentTimeMillis	()J
    //   5802: lload 16
    //   5804: lsub
    //   5805: l2i
    //   5806: putfield 466	com/tencent/tencentmap/mapsdk/a/fd:m	I
    //   5809: aload 39
    //   5811: aload 20
    //   5813: putfield 468	com/tencent/tencentmap/mapsdk/a/fd:f	Ljava/lang/String;
    //   5816: aload_1
    //   5817: invokevirtual 366	com/tencent/tencentmap/mapsdk/a/fb:b	()Z
    //   5820: ifne +179 -> 5999
    //   5823: aload_1
    //   5824: invokevirtual 471	com/tencent/tencentmap/mapsdk/a/fb:h	()[B
    //   5827: ifnull +172 -> 5999
    //   5830: aload 39
    //   5832: aload_1
    //   5833: invokevirtual 471	com/tencent/tencentmap/mapsdk/a/fb:h	()[B
    //   5836: arraylength
    //   5837: i2l
    //   5838: putfield 474	com/tencent/tencentmap/mapsdk/a/fd:n	J
    //   5841: aload 39
    //   5843: iconst_1
    //   5844: putfield 477	com/tencent/tencentmap/mapsdk/a/fd:z	Z
    //   5847: aload 39
    //   5849: getfield 458	com/tencent/tencentmap/mapsdk/a/fd:k	I
    //   5852: ifeq +9 -> 5861
    //   5855: aload 39
    //   5857: iconst_1
    //   5858: putfield 480	com/tencent/tencentmap/mapsdk/a/fd:w	I
    //   5861: aload 39
    //   5863: aload_1
    //   5864: invokevirtual 482	com/tencent/tencentmap/mapsdk/a/fb:m	()Z
    //   5867: putfield 485	com/tencent/tencentmap/mapsdk/a/fd:B	Z
    //   5870: invokestatic 490	com/tencent/tencentmap/mapsdk/a/el:a	()Lcom/tencent/tencentmap/mapsdk/a/el;
    //   5873: new 492	com/tencent/tencentmap/mapsdk/a/fe
    //   5876: dup
    //   5877: aload 39
    //   5879: invokespecial 495	com/tencent/tencentmap/mapsdk/a/fe:<init>	(Lcom/tencent/tencentmap/mapsdk/a/fd;)V
    //   5882: invokevirtual 498	com/tencent/tencentmap/mapsdk/a/el:a	(Ljava/lang/Runnable;)V
    //   5885: aload_1
    //   5886: aload 39
    //   5888: invokevirtual 500	com/tencent/tencentmap/mapsdk/a/fb:a	(Lcom/tencent/tencentmap/mapsdk/a/fd;)V
    //   5891: aload 33
    //   5893: aload 39
    //   5895: getfield 313	com/tencent/tencentmap/mapsdk/a/fd:a	Lcom/tencent/tencentmap/mapsdk/a/ep;
    //   5898: invokevirtual 335	com/tencent/tencentmap/mapsdk/a/ep:a	()Ljava/lang/String;
    //   5901: putfield 502	com/tencent/tencentmap/mapsdk/a/fc:l	Ljava/lang/String;
    //   5904: aload 33
    //   5906: aload 39
    //   5908: invokevirtual 503	com/tencent/tencentmap/mapsdk/a/fd:toString	()Ljava/lang/String;
    //   5911: putfield 504	com/tencent/tencentmap/mapsdk/a/fc:d	Ljava/lang/String;
    //   5914: aload 33
    //   5916: aload 39
    //   5918: getfield 447	com/tencent/tencentmap/mapsdk/a/fd:p	Ljava/lang/String;
    //   5921: putfield 506	com/tencent/tencentmap/mapsdk/a/fc:m	Ljava/lang/String;
    //   5924: ldc_w 508
    //   5927: aload 39
    //   5929: invokevirtual 503	com/tencent/tencentmap/mapsdk/a/fd:toString	()Ljava/lang/String;
    //   5932: invokestatic 510	com/tencent/tencentmap/mapsdk/a/fx:b	(Ljava/lang/String;Ljava/lang/String;)V
    //   5935: aload 23
    //   5937: ifnull +15 -> 5952
    //   5940: aload_1
    //   5941: invokevirtual 269	com/tencent/tencentmap/mapsdk/a/fb:l	()Z
    //   5944: ifne +8 -> 5952
    //   5947: aload_1
    //   5948: invokevirtual 511	com/tencent/tencentmap/mapsdk/a/fb:f	()Z
    //   5951: pop
    //   5952: lload 16
    //   5954: invokestatic 513	com/tencent/tencentmap/mapsdk/a/ez:a	(J)Z
    //   5957: istore 13
    //   5959: aload 33
    //   5961: astore 23
    //   5963: aload 33
    //   5965: getfield 281	com/tencent/tencentmap/mapsdk/a/fc:a	I
    //   5968: bipush -4
    //   5970: if_icmpeq -5837 -> 133
    //   5973: aload 33
    //   5975: astore 23
    //   5977: aload 33
    //   5979: getfield 281	com/tencent/tencentmap/mapsdk/a/fc:a	I
    //   5982: bipush -17
    //   5984: if_icmpeq -5851 -> 133
    //   5987: aload 33
    //   5989: astore 23
    //   5991: iload 13
    //   5993: ifeq -5860 -> 133
    //   5996: aload 33
    //   5998: areturn
    //   5999: aload 39
    //   6001: lconst_0
    //   6002: putfield 474	com/tencent/tencentmap/mapsdk/a/fd:n	J
    //   6005: goto -164 -> 5841
    //   6008: iload 6
    //   6010: istore_3
    //   6011: ldc_w 271
    //   6014: ldc_w 617
    //   6017: invokestatic 510	com/tencent/tencentmap/mapsdk/a/fx:b	(Ljava/lang/String;Ljava/lang/String;)V
    //   6020: iload 6
    //   6022: istore_3
    //   6023: aload 33
    //   6025: aload 22
    //   6027: putfield 620	com/tencent/tencentmap/mapsdk/a/fc:f	Ljava/io/InputStream;
    //   6030: iload 6
    //   6032: istore_3
    //   6033: aload 33
    //   6035: iconst_0
    //   6036: putfield 281	com/tencent/tencentmap/mapsdk/a/fc:a	I
    //   6039: goto -811 -> 5228
    //   6042: astore 22
    //   6044: iload_2
    //   6045: istore_3
    //   6046: goto -3847 -> 2199
    //   6049: aload 39
    //   6051: lconst_0
    //   6052: putfield 474	com/tencent/tencentmap/mapsdk/a/fd:n	J
    //   6055: goto -634 -> 5421
    //   6058: iload 6
    //   6060: istore_3
    //   6061: aload 39
    //   6063: iconst_0
    //   6064: putfield 480	com/tencent/tencentmap/mapsdk/a/fd:w	I
    //   6067: aload 39
    //   6069: new 79	java/lang/StringBuilder
    //   6072: dup
    //   6073: invokespecial 346	java/lang/StringBuilder:<init>	()V
    //   6076: aload_1
    //   6077: invokevirtual 443	com/tencent/tencentmap/mapsdk/a/fb:a	()Ljava/lang/String;
    //   6080: invokevirtual 86	java/lang/StringBuilder:append	(Ljava/lang/String;)Ljava/lang/StringBuilder;
    //   6083: ldc_w 445
    //   6086: invokevirtual 86	java/lang/StringBuilder:append	(Ljava/lang/String;)Ljava/lang/StringBuilder;
    //   6089: iload 4
    //   6091: invokevirtual 340	java/lang/StringBuilder:append	(I)Ljava/lang/StringBuilder;
    //   6094: invokevirtual 89	java/lang/StringBuilder:toString	()Ljava/lang/String;
    //   6097: putfield 447	com/tencent/tencentmap/mapsdk/a/fd:p	Ljava/lang/String;
    //   6100: aload 39
    //   6102: iload 4
    //   6104: putfield 450	com/tencent/tencentmap/mapsdk/a/fd:s	I
    //   6107: aload 20
    //   6109: invokestatic 51	android/text/TextUtils:isEmpty	(Ljava/lang/CharSequence;)Z
    //   6112: ifne +19 -> 6131
    //   6115: iload 5
    //   6117: iconst_1
    //   6118: iadd
    //   6119: bipush 6
    //   6121: if_icmple +10 -> 6131
    //   6124: aload 33
    //   6126: bipush -5
    //   6128: putfield 281	com/tencent/tencentmap/mapsdk/a/fc:a	I
    //   6131: invokestatic 454	com/tencent/tencentmap/mapsdk/a/em:b	()Ljava/lang/String;
    //   6134: invokestatic 51	android/text/TextUtils:isEmpty	(Ljava/lang/CharSequence;)Z
    //   6137: ifne +192 -> 6329
    //   6140: aload 33
    //   6142: getfield 281	com/tencent/tencentmap/mapsdk/a/fc:a	I
    //   6145: bipush -21
    //   6147: if_icmpeq +182 -> 6329
    //   6150: aload 33
    //   6152: invokestatic 232	java/lang/System:currentTimeMillis	()J
    //   6155: aload_1
    //   6156: invokevirtual 263	com/tencent/tencentmap/mapsdk/a/fb:q	()J
    //   6159: lsub
    //   6160: l2i
    //   6161: putfield 457	com/tencent/tencentmap/mapsdk/a/fc:k	I
    //   6164: aload 39
    //   6166: aload 33
    //   6168: getfield 281	com/tencent/tencentmap/mapsdk/a/fc:a	I
    //   6171: putfield 458	com/tencent/tencentmap/mapsdk/a/fd:k	I
    //   6174: aload 39
    //   6176: aload 21
    //   6178: putfield 461	com/tencent/tencentmap/mapsdk/a/fd:C	Ljava/lang/String;
    //   6181: aload 39
    //   6183: aload 33
    //   6185: getfield 457	com/tencent/tencentmap/mapsdk/a/fc:k	I
    //   6188: putfield 463	com/tencent/tencentmap/mapsdk/a/fd:l	I
    //   6191: aload 39
    //   6193: invokestatic 232	java/lang/System:currentTimeMillis	()J
    //   6196: lload 16
    //   6198: lsub
    //   6199: l2i
    //   6200: putfield 466	com/tencent/tencentmap/mapsdk/a/fd:m	I
    //   6203: aload 39
    //   6205: aload 20
    //   6207: putfield 468	com/tencent/tencentmap/mapsdk/a/fd:f	Ljava/lang/String;
    //   6210: aload_1
    //   6211: invokevirtual 366	com/tencent/tencentmap/mapsdk/a/fb:b	()Z
    //   6214: ifne +179 -> 6393
    //   6217: aload_1
    //   6218: invokevirtual 471	com/tencent/tencentmap/mapsdk/a/fb:h	()[B
    //   6221: ifnull +172 -> 6393
    //   6224: aload 39
    //   6226: aload_1
    //   6227: invokevirtual 471	com/tencent/tencentmap/mapsdk/a/fb:h	()[B
    //   6230: arraylength
    //   6231: i2l
    //   6232: putfield 474	com/tencent/tencentmap/mapsdk/a/fd:n	J
    //   6235: aload 39
    //   6237: iconst_1
    //   6238: putfield 477	com/tencent/tencentmap/mapsdk/a/fd:z	Z
    //   6241: aload 39
    //   6243: getfield 458	com/tencent/tencentmap/mapsdk/a/fd:k	I
    //   6246: ifeq +9 -> 6255
    //   6249: aload 39
    //   6251: iconst_1
    //   6252: putfield 480	com/tencent/tencentmap/mapsdk/a/fd:w	I
    //   6255: aload 39
    //   6257: aload_1
    //   6258: invokevirtual 482	com/tencent/tencentmap/mapsdk/a/fb:m	()Z
    //   6261: putfield 485	com/tencent/tencentmap/mapsdk/a/fd:B	Z
    //   6264: invokestatic 490	com/tencent/tencentmap/mapsdk/a/el:a	()Lcom/tencent/tencentmap/mapsdk/a/el;
    //   6267: new 492	com/tencent/tencentmap/mapsdk/a/fe
    //   6270: dup
    //   6271: aload 39
    //   6273: invokespecial 495	com/tencent/tencentmap/mapsdk/a/fe:<init>	(Lcom/tencent/tencentmap/mapsdk/a/fd;)V
    //   6276: invokevirtual 498	com/tencent/tencentmap/mapsdk/a/el:a	(Ljava/lang/Runnable;)V
    //   6279: aload_1
    //   6280: aload 39
    //   6282: invokevirtual 500	com/tencent/tencentmap/mapsdk/a/fb:a	(Lcom/tencent/tencentmap/mapsdk/a/fd;)V
    //   6285: aload 33
    //   6287: aload 39
    //   6289: getfield 313	com/tencent/tencentmap/mapsdk/a/fd:a	Lcom/tencent/tencentmap/mapsdk/a/ep;
    //   6292: invokevirtual 335	com/tencent/tencentmap/mapsdk/a/ep:a	()Ljava/lang/String;
    //   6295: putfield 502	com/tencent/tencentmap/mapsdk/a/fc:l	Ljava/lang/String;
    //   6298: aload 33
    //   6300: aload 39
    //   6302: invokevirtual 503	com/tencent/tencentmap/mapsdk/a/fd:toString	()Ljava/lang/String;
    //   6305: putfield 504	com/tencent/tencentmap/mapsdk/a/fc:d	Ljava/lang/String;
    //   6308: aload 33
    //   6310: aload 39
    //   6312: getfield 447	com/tencent/tencentmap/mapsdk/a/fd:p	Ljava/lang/String;
    //   6315: putfield 506	com/tencent/tencentmap/mapsdk/a/fc:m	Ljava/lang/String;
    //   6318: ldc_w 508
    //   6321: aload 39
    //   6323: invokevirtual 503	com/tencent/tencentmap/mapsdk/a/fd:toString	()Ljava/lang/String;
    //   6326: invokestatic 510	com/tencent/tencentmap/mapsdk/a/fx:b	(Ljava/lang/String;Ljava/lang/String;)V
    //   6329: aload 23
    //   6331: ifnull +15 -> 6346
    //   6334: aload_1
    //   6335: invokevirtual 269	com/tencent/tencentmap/mapsdk/a/fb:l	()Z
    //   6338: ifne +8 -> 6346
    //   6341: aload_1
    //   6342: invokevirtual 511	com/tencent/tencentmap/mapsdk/a/fb:f	()Z
    //   6345: pop
    //   6346: lload 16
    //   6348: invokestatic 513	com/tencent/tencentmap/mapsdk/a/ez:a	(J)Z
    //   6351: istore 13
    //   6353: aload 33
    //   6355: astore 23
    //   6357: aload 33
    //   6359: getfield 281	com/tencent/tencentmap/mapsdk/a/fc:a	I
    //   6362: bipush -4
    //   6364: if_icmpeq -6231 -> 133
    //   6367: aload 33
    //   6369: astore 23
    //   6371: aload 33
    //   6373: getfield 281	com/tencent/tencentmap/mapsdk/a/fc:a	I
    //   6376: bipush -17
    //   6378: if_icmpeq -6245 -> 133
    //   6381: aload 33
    //   6383: astore 23
    //   6385: iload 13
    //   6387: ifeq -6254 -> 133
    //   6390: aload 33
    //   6392: areturn
    //   6393: aload 39
    //   6395: lconst_0
    //   6396: putfield 474	com/tencent/tencentmap/mapsdk/a/fd:n	J
    //   6399: goto -164 -> 6235
    //   6402: aload 20
    //   6404: astore 30
    //   6406: aload 21
    //   6408: astore 25
    //   6410: aload 23
    //   6412: astore 27
    //   6414: aload 20
    //   6416: astore 24
    //   6418: aload 21
    //   6420: astore 26
    //   6422: aload 23
    //   6424: astore 28
    //   6426: aload 21
    //   6428: astore 31
    //   6430: aload 23
    //   6432: astore 29
    //   6434: aload 33
    //   6436: bipush -21
    //   6438: putfield 281	com/tencent/tencentmap/mapsdk/a/fc:a	I
    //   6441: bipush 10
    //   6443: istore 6
    //   6445: aload 20
    //   6447: astore 32
    //   6449: aload 21
    //   6451: astore 29
    //   6453: aload 23
    //   6455: astore 31
    //   6457: iload 6
    //   6459: istore_3
    //   6460: aload 20
    //   6462: astore 30
    //   6464: aload 21
    //   6466: astore 25
    //   6468: aload 23
    //   6470: astore 27
    //   6472: aload 20
    //   6474: astore 24
    //   6476: aload 21
    //   6478: astore 26
    //   6480: aload 23
    //   6482: astore 28
    //   6484: aload 34
    //   6486: ldc_w 622
    //   6489: invokeinterface 571 2 0
    //   6494: astore 34
    //   6496: aload 20
    //   6498: astore 22
    //   6500: aload 34
    //   6502: ifnull +118 -> 6620
    //   6505: aload 20
    //   6507: astore 32
    //   6509: aload 21
    //   6511: astore 29
    //   6513: aload 23
    //   6515: astore 31
    //   6517: iload 6
    //   6519: istore_3
    //   6520: aload 20
    //   6522: astore 30
    //   6524: aload 21
    //   6526: astore 25
    //   6528: aload 23
    //   6530: astore 27
    //   6532: aload 20
    //   6534: astore 24
    //   6536: aload 21
    //   6538: astore 26
    //   6540: aload 23
    //   6542: astore 28
    //   6544: aload 34
    //   6546: invokeinterface 576 1 0
    //   6551: astore 20
    //   6553: aload 20
    //   6555: astore 32
    //   6557: aload 21
    //   6559: astore 29
    //   6561: aload 23
    //   6563: astore 31
    //   6565: iload 6
    //   6567: istore_3
    //   6568: aload 20
    //   6570: astore 30
    //   6572: aload 21
    //   6574: astore 25
    //   6576: aload 23
    //   6578: astore 27
    //   6580: aload 20
    //   6582: astore 24
    //   6584: aload 21
    //   6586: astore 26
    //   6588: aload 23
    //   6590: astore 28
    //   6592: ldc_w 271
    //   6595: new 79	java/lang/StringBuilder
    //   6598: dup
    //   6599: ldc_w 624
    //   6602: invokespecial 82	java/lang/StringBuilder:<init>	(Ljava/lang/String;)V
    //   6605: aload 20
    //   6607: invokevirtual 86	java/lang/StringBuilder:append	(Ljava/lang/String;)Ljava/lang/StringBuilder;
    //   6610: invokevirtual 89	java/lang/StringBuilder:toString	()Ljava/lang/String;
    //   6613: invokestatic 510	com/tencent/tencentmap/mapsdk/a/fx:b	(Ljava/lang/String;Ljava/lang/String;)V
    //   6616: aload 20
    //   6618: astore 22
    //   6620: aload 22
    //   6622: astore 20
    //   6624: iconst_1
    //   6625: istore 14
    //   6627: aload 20
    //   6629: astore 26
    //   6631: aload 21
    //   6633: astore 25
    //   6635: aload 23
    //   6637: astore 24
    //   6639: aload 20
    //   6641: astore 22
    //   6643: aload 20
    //   6645: astore 27
    //   6647: aload 39
    //   6649: iconst_1
    //   6650: putfield 626	com/tencent/tencentmap/mapsdk/a/fd:e	Z
    //   6653: aload 20
    //   6655: astore 26
    //   6657: aload 21
    //   6659: astore 25
    //   6661: aload 23
    //   6663: astore 24
    //   6665: aload 20
    //   6667: astore 22
    //   6669: aload 20
    //   6671: astore 27
    //   6673: aload 20
    //   6675: invokestatic 51	android/text/TextUtils:isEmpty	(Ljava/lang/CharSequence;)Z
    //   6678: istore 15
    //   6680: iload 15
    //   6682: ifeq +22 -> 6704
    //   6685: aconst_null
    //   6686: astore 22
    //   6688: aconst_null
    //   6689: astore 27
    //   6691: aconst_null
    //   6692: astore 20
    //   6694: aload 33
    //   6696: bipush -6
    //   6698: putfield 281	com/tencent/tencentmap/mapsdk/a/fc:a	I
    //   6701: goto -2426 -> 4275
    //   6704: aload 20
    //   6706: astore 26
    //   6708: aload 21
    //   6710: astore 25
    //   6712: aload 23
    //   6714: astore 24
    //   6716: aload 20
    //   6718: astore 22
    //   6720: aload 20
    //   6722: astore 27
    //   6724: aload_1
    //   6725: invokevirtual 628	com/tencent/tencentmap/mapsdk/a/fb:k	()Z
    //   6728: ifne +1319 -> 8047
    //   6731: aload 20
    //   6733: astore 26
    //   6735: aload 21
    //   6737: astore 25
    //   6739: aload 23
    //   6741: astore 24
    //   6743: aload 20
    //   6745: astore 22
    //   6747: aload 20
    //   6749: astore 27
    //   6751: ldc_w 271
    //   6754: ldc_w 630
    //   6757: invokestatic 510	com/tencent/tencentmap/mapsdk/a/fx:b	(Ljava/lang/String;Ljava/lang/String;)V
    //   6760: aload 20
    //   6762: astore 26
    //   6764: aload 21
    //   6766: astore 25
    //   6768: aload 23
    //   6770: astore 24
    //   6772: aload 20
    //   6774: astore 22
    //   6776: aload 20
    //   6778: astore 27
    //   6780: aload 33
    //   6782: aload 20
    //   6784: putfield 631	com/tencent/tencentmap/mapsdk/a/fc:c	Ljava/lang/String;
    //   6787: aload 20
    //   6789: astore 26
    //   6791: aload 21
    //   6793: astore 25
    //   6795: aload 23
    //   6797: astore 24
    //   6799: aload 20
    //   6801: astore 22
    //   6803: aload 20
    //   6805: astore 27
    //   6807: aload 33
    //   6809: bipush -7
    //   6811: putfield 281	com/tencent/tencentmap/mapsdk/a/fc:a	I
    //   6814: aload 20
    //   6816: astore 26
    //   6818: aload 21
    //   6820: astore 25
    //   6822: aload 23
    //   6824: astore 24
    //   6826: aload 20
    //   6828: astore 22
    //   6830: aload 20
    //   6832: astore 27
    //   6834: aload_1
    //   6835: invokevirtual 269	com/tencent/tencentmap/mapsdk/a/fb:l	()Z
    //   6838: istore 14
    //   6840: iload 14
    //   6842: ifeq +343 -> 7185
    //   6845: aload 39
    //   6847: new 79	java/lang/StringBuilder
    //   6850: dup
    //   6851: invokespecial 346	java/lang/StringBuilder:<init>	()V
    //   6854: aload_1
    //   6855: invokevirtual 443	com/tencent/tencentmap/mapsdk/a/fb:a	()Ljava/lang/String;
    //   6858: invokevirtual 86	java/lang/StringBuilder:append	(Ljava/lang/String;)Ljava/lang/StringBuilder;
    //   6861: ldc_w 445
    //   6864: invokevirtual 86	java/lang/StringBuilder:append	(Ljava/lang/String;)Ljava/lang/StringBuilder;
    //   6867: iload 4
    //   6869: invokevirtual 340	java/lang/StringBuilder:append	(I)Ljava/lang/StringBuilder;
    //   6872: invokevirtual 89	java/lang/StringBuilder:toString	()Ljava/lang/String;
    //   6875: putfield 447	com/tencent/tencentmap/mapsdk/a/fd:p	Ljava/lang/String;
    //   6878: aload 39
    //   6880: iload 4
    //   6882: putfield 450	com/tencent/tencentmap/mapsdk/a/fd:s	I
    //   6885: aload 20
    //   6887: invokestatic 51	android/text/TextUtils:isEmpty	(Ljava/lang/CharSequence;)Z
    //   6890: ifne +19 -> 6909
    //   6893: iload 5
    //   6895: iconst_1
    //   6896: iadd
    //   6897: bipush 6
    //   6899: if_icmple +10 -> 6909
    //   6902: aload 33
    //   6904: bipush -5
    //   6906: putfield 281	com/tencent/tencentmap/mapsdk/a/fc:a	I
    //   6909: invokestatic 454	com/tencent/tencentmap/mapsdk/a/em:b	()Ljava/lang/String;
    //   6912: invokestatic 51	android/text/TextUtils:isEmpty	(Ljava/lang/CharSequence;)Z
    //   6915: ifne +198 -> 7113
    //   6918: aload 33
    //   6920: getfield 281	com/tencent/tencentmap/mapsdk/a/fc:a	I
    //   6923: bipush -21
    //   6925: if_icmpeq +188 -> 7113
    //   6928: aload 33
    //   6930: invokestatic 232	java/lang/System:currentTimeMillis	()J
    //   6933: aload_1
    //   6934: invokevirtual 263	com/tencent/tencentmap/mapsdk/a/fb:q	()J
    //   6937: lsub
    //   6938: l2i
    //   6939: putfield 457	com/tencent/tencentmap/mapsdk/a/fc:k	I
    //   6942: aload 39
    //   6944: aload 33
    //   6946: getfield 281	com/tencent/tencentmap/mapsdk/a/fc:a	I
    //   6949: putfield 458	com/tencent/tencentmap/mapsdk/a/fd:k	I
    //   6952: aload 39
    //   6954: aload 21
    //   6956: putfield 461	com/tencent/tencentmap/mapsdk/a/fd:C	Ljava/lang/String;
    //   6959: aload 39
    //   6961: aload 33
    //   6963: getfield 457	com/tencent/tencentmap/mapsdk/a/fc:k	I
    //   6966: putfield 463	com/tencent/tencentmap/mapsdk/a/fd:l	I
    //   6969: aload 39
    //   6971: invokestatic 232	java/lang/System:currentTimeMillis	()J
    //   6974: lload 16
    //   6976: lsub
    //   6977: l2i
    //   6978: putfield 466	com/tencent/tencentmap/mapsdk/a/fd:m	I
    //   6981: aload 39
    //   6983: aload 20
    //   6985: putfield 468	com/tencent/tencentmap/mapsdk/a/fd:f	Ljava/lang/String;
    //   6988: aload_1
    //   6989: invokevirtual 366	com/tencent/tencentmap/mapsdk/a/fb:b	()Z
    //   6992: ifne +184 -> 7176
    //   6995: aload_1
    //   6996: invokevirtual 471	com/tencent/tencentmap/mapsdk/a/fb:h	()[B
    //   6999: ifnull +177 -> 7176
    //   7002: aload 39
    //   7004: aload_1
    //   7005: invokevirtual 471	com/tencent/tencentmap/mapsdk/a/fb:h	()[B
    //   7008: arraylength
    //   7009: i2l
    //   7010: putfield 474	com/tencent/tencentmap/mapsdk/a/fd:n	J
    //   7013: aload 39
    //   7015: iload 13
    //   7017: putfield 477	com/tencent/tencentmap/mapsdk/a/fd:z	Z
    //   7020: iload 13
    //   7022: ifeq +17 -> 7039
    //   7025: aload 39
    //   7027: getfield 458	com/tencent/tencentmap/mapsdk/a/fd:k	I
    //   7030: ifeq +9 -> 7039
    //   7033: aload 39
    //   7035: iconst_1
    //   7036: putfield 480	com/tencent/tencentmap/mapsdk/a/fd:w	I
    //   7039: aload 39
    //   7041: aload_1
    //   7042: invokevirtual 482	com/tencent/tencentmap/mapsdk/a/fb:m	()Z
    //   7045: putfield 485	com/tencent/tencentmap/mapsdk/a/fd:B	Z
    //   7048: invokestatic 490	com/tencent/tencentmap/mapsdk/a/el:a	()Lcom/tencent/tencentmap/mapsdk/a/el;
    //   7051: new 492	com/tencent/tencentmap/mapsdk/a/fe
    //   7054: dup
    //   7055: aload 39
    //   7057: invokespecial 495	com/tencent/tencentmap/mapsdk/a/fe:<init>	(Lcom/tencent/tencentmap/mapsdk/a/fd;)V
    //   7060: invokevirtual 498	com/tencent/tencentmap/mapsdk/a/el:a	(Ljava/lang/Runnable;)V
    //   7063: aload_1
    //   7064: aload 39
    //   7066: invokevirtual 500	com/tencent/tencentmap/mapsdk/a/fb:a	(Lcom/tencent/tencentmap/mapsdk/a/fd;)V
    //   7069: aload 33
    //   7071: aload 39
    //   7073: getfield 313	com/tencent/tencentmap/mapsdk/a/fd:a	Lcom/tencent/tencentmap/mapsdk/a/ep;
    //   7076: invokevirtual 335	com/tencent/tencentmap/mapsdk/a/ep:a	()Ljava/lang/String;
    //   7079: putfield 502	com/tencent/tencentmap/mapsdk/a/fc:l	Ljava/lang/String;
    //   7082: aload 33
    //   7084: aload 39
    //   7086: invokevirtual 503	com/tencent/tencentmap/mapsdk/a/fd:toString	()Ljava/lang/String;
    //   7089: putfield 504	com/tencent/tencentmap/mapsdk/a/fc:d	Ljava/lang/String;
    //   7092: aload 33
    //   7094: aload 39
    //   7096: getfield 447	com/tencent/tencentmap/mapsdk/a/fd:p	Ljava/lang/String;
    //   7099: putfield 506	com/tencent/tencentmap/mapsdk/a/fc:m	Ljava/lang/String;
    //   7102: ldc_w 508
    //   7105: aload 39
    //   7107: invokevirtual 503	com/tencent/tencentmap/mapsdk/a/fd:toString	()Ljava/lang/String;
    //   7110: invokestatic 510	com/tencent/tencentmap/mapsdk/a/fx:b	(Ljava/lang/String;Ljava/lang/String;)V
    //   7113: aload 23
    //   7115: ifnull +15 -> 7130
    //   7118: aload_1
    //   7119: invokevirtual 269	com/tencent/tencentmap/mapsdk/a/fb:l	()Z
    //   7122: ifne +8 -> 7130
    //   7125: aload_1
    //   7126: invokevirtual 511	com/tencent/tencentmap/mapsdk/a/fb:f	()Z
    //   7129: pop
    //   7130: lload 16
    //   7132: invokestatic 513	com/tencent/tencentmap/mapsdk/a/ez:a	(J)Z
    //   7135: istore 13
    //   7137: aload 33
    //   7139: astore 23
    //   7141: aload 33
    //   7143: getfield 281	com/tencent/tencentmap/mapsdk/a/fc:a	I
    //   7146: bipush -4
    //   7148: if_icmpeq -7015 -> 133
    //   7151: aload 33
    //   7153: astore 23
    //   7155: aload 33
    //   7157: getfield 281	com/tencent/tencentmap/mapsdk/a/fc:a	I
    //   7160: bipush -17
    //   7162: if_icmpeq -7029 -> 133
    //   7165: aload 33
    //   7167: astore 23
    //   7169: iload 13
    //   7171: ifne -7038 -> 133
    //   7174: aconst_null
    //   7175: areturn
    //   7176: aload 39
    //   7178: lconst_0
    //   7179: putfield 474	com/tencent/tencentmap/mapsdk/a/fd:n	J
    //   7182: goto -169 -> 7013
    //   7185: aload 39
    //   7187: new 79	java/lang/StringBuilder
    //   7190: dup
    //   7191: invokespecial 346	java/lang/StringBuilder:<init>	()V
    //   7194: aload_1
    //   7195: invokevirtual 443	com/tencent/tencentmap/mapsdk/a/fb:a	()Ljava/lang/String;
    //   7198: invokevirtual 86	java/lang/StringBuilder:append	(Ljava/lang/String;)Ljava/lang/StringBuilder;
    //   7201: ldc_w 445
    //   7204: invokevirtual 86	java/lang/StringBuilder:append	(Ljava/lang/String;)Ljava/lang/StringBuilder;
    //   7207: iload 4
    //   7209: invokevirtual 340	java/lang/StringBuilder:append	(I)Ljava/lang/StringBuilder;
    //   7212: invokevirtual 89	java/lang/StringBuilder:toString	()Ljava/lang/String;
    //   7215: putfield 447	com/tencent/tencentmap/mapsdk/a/fd:p	Ljava/lang/String;
    //   7218: aload 39
    //   7220: iload 4
    //   7222: putfield 450	com/tencent/tencentmap/mapsdk/a/fd:s	I
    //   7225: aload 20
    //   7227: invokestatic 51	android/text/TextUtils:isEmpty	(Ljava/lang/CharSequence;)Z
    //   7230: ifne +19 -> 7249
    //   7233: iload 5
    //   7235: iconst_1
    //   7236: iadd
    //   7237: bipush 6
    //   7239: if_icmple +10 -> 7249
    //   7242: aload 33
    //   7244: bipush -5
    //   7246: putfield 281	com/tencent/tencentmap/mapsdk/a/fc:a	I
    //   7249: invokestatic 454	com/tencent/tencentmap/mapsdk/a/em:b	()Ljava/lang/String;
    //   7252: invokestatic 51	android/text/TextUtils:isEmpty	(Ljava/lang/CharSequence;)Z
    //   7255: ifne +198 -> 7453
    //   7258: aload 33
    //   7260: getfield 281	com/tencent/tencentmap/mapsdk/a/fc:a	I
    //   7263: bipush -21
    //   7265: if_icmpeq +188 -> 7453
    //   7268: aload 33
    //   7270: invokestatic 232	java/lang/System:currentTimeMillis	()J
    //   7273: aload_1
    //   7274: invokevirtual 263	com/tencent/tencentmap/mapsdk/a/fb:q	()J
    //   7277: lsub
    //   7278: l2i
    //   7279: putfield 457	com/tencent/tencentmap/mapsdk/a/fc:k	I
    //   7282: aload 39
    //   7284: aload 33
    //   7286: getfield 281	com/tencent/tencentmap/mapsdk/a/fc:a	I
    //   7289: putfield 458	com/tencent/tencentmap/mapsdk/a/fd:k	I
    //   7292: aload 39
    //   7294: aload 21
    //   7296: putfield 461	com/tencent/tencentmap/mapsdk/a/fd:C	Ljava/lang/String;
    //   7299: aload 39
    //   7301: aload 33
    //   7303: getfield 457	com/tencent/tencentmap/mapsdk/a/fc:k	I
    //   7306: putfield 463	com/tencent/tencentmap/mapsdk/a/fd:l	I
    //   7309: aload 39
    //   7311: invokestatic 232	java/lang/System:currentTimeMillis	()J
    //   7314: lload 16
    //   7316: lsub
    //   7317: l2i
    //   7318: putfield 466	com/tencent/tencentmap/mapsdk/a/fd:m	I
    //   7321: aload 39
    //   7323: aload 20
    //   7325: putfield 468	com/tencent/tencentmap/mapsdk/a/fd:f	Ljava/lang/String;
    //   7328: aload_1
    //   7329: invokevirtual 366	com/tencent/tencentmap/mapsdk/a/fb:b	()Z
    //   7332: ifne +185 -> 7517
    //   7335: aload_1
    //   7336: invokevirtual 471	com/tencent/tencentmap/mapsdk/a/fb:h	()[B
    //   7339: ifnull +178 -> 7517
    //   7342: aload 39
    //   7344: aload_1
    //   7345: invokevirtual 471	com/tencent/tencentmap/mapsdk/a/fb:h	()[B
    //   7348: arraylength
    //   7349: i2l
    //   7350: putfield 474	com/tencent/tencentmap/mapsdk/a/fd:n	J
    //   7353: aload 39
    //   7355: iload 13
    //   7357: putfield 477	com/tencent/tencentmap/mapsdk/a/fd:z	Z
    //   7360: iload 13
    //   7362: ifeq +17 -> 7379
    //   7365: aload 39
    //   7367: getfield 458	com/tencent/tencentmap/mapsdk/a/fd:k	I
    //   7370: ifeq +9 -> 7379
    //   7373: aload 39
    //   7375: iconst_1
    //   7376: putfield 480	com/tencent/tencentmap/mapsdk/a/fd:w	I
    //   7379: aload 39
    //   7381: aload_1
    //   7382: invokevirtual 482	com/tencent/tencentmap/mapsdk/a/fb:m	()Z
    //   7385: putfield 485	com/tencent/tencentmap/mapsdk/a/fd:B	Z
    //   7388: invokestatic 490	com/tencent/tencentmap/mapsdk/a/el:a	()Lcom/tencent/tencentmap/mapsdk/a/el;
    //   7391: new 492	com/tencent/tencentmap/mapsdk/a/fe
    //   7394: dup
    //   7395: aload 39
    //   7397: invokespecial 495	com/tencent/tencentmap/mapsdk/a/fe:<init>	(Lcom/tencent/tencentmap/mapsdk/a/fd;)V
    //   7400: invokevirtual 498	com/tencent/tencentmap/mapsdk/a/el:a	(Ljava/lang/Runnable;)V
    //   7403: aload_1
    //   7404: aload 39
    //   7406: invokevirtual 500	com/tencent/tencentmap/mapsdk/a/fb:a	(Lcom/tencent/tencentmap/mapsdk/a/fd;)V
    //   7409: aload 33
    //   7411: aload 39
    //   7413: getfield 313	com/tencent/tencentmap/mapsdk/a/fd:a	Lcom/tencent/tencentmap/mapsdk/a/ep;
    //   7416: invokevirtual 335	com/tencent/tencentmap/mapsdk/a/ep:a	()Ljava/lang/String;
    //   7419: putfield 502	com/tencent/tencentmap/mapsdk/a/fc:l	Ljava/lang/String;
    //   7422: aload 33
    //   7424: aload 39
    //   7426: invokevirtual 503	com/tencent/tencentmap/mapsdk/a/fd:toString	()Ljava/lang/String;
    //   7429: putfield 504	com/tencent/tencentmap/mapsdk/a/fc:d	Ljava/lang/String;
    //   7432: aload 33
    //   7434: aload 39
    //   7436: getfield 447	com/tencent/tencentmap/mapsdk/a/fd:p	Ljava/lang/String;
    //   7439: putfield 506	com/tencent/tencentmap/mapsdk/a/fc:m	Ljava/lang/String;
    //   7442: ldc_w 508
    //   7445: aload 39
    //   7447: invokevirtual 503	com/tencent/tencentmap/mapsdk/a/fd:toString	()Ljava/lang/String;
    //   7450: invokestatic 510	com/tencent/tencentmap/mapsdk/a/fx:b	(Ljava/lang/String;Ljava/lang/String;)V
    //   7453: aload 23
    //   7455: ifnull +15 -> 7470
    //   7458: aload_1
    //   7459: invokevirtual 269	com/tencent/tencentmap/mapsdk/a/fb:l	()Z
    //   7462: ifne +8 -> 7470
    //   7465: aload_1
    //   7466: invokevirtual 511	com/tencent/tencentmap/mapsdk/a/fb:f	()Z
    //   7469: pop
    //   7470: lload 16
    //   7472: invokestatic 513	com/tencent/tencentmap/mapsdk/a/ez:a	(J)Z
    //   7475: istore 13
    //   7477: aload 33
    //   7479: astore 23
    //   7481: aload 33
    //   7483: getfield 281	com/tencent/tencentmap/mapsdk/a/fc:a	I
    //   7486: bipush -4
    //   7488: if_icmpeq -7355 -> 133
    //   7491: aload 33
    //   7493: astore 23
    //   7495: aload 33
    //   7497: getfield 281	com/tencent/tencentmap/mapsdk/a/fc:a	I
    //   7500: bipush -17
    //   7502: if_icmpeq -7369 -> 133
    //   7505: aload 33
    //   7507: astore 23
    //   7509: iload 13
    //   7511: ifeq -7378 -> 133
    //   7514: aload 33
    //   7516: areturn
    //   7517: aload 39
    //   7519: lconst_0
    //   7520: putfield 474	com/tencent/tencentmap/mapsdk/a/fd:n	J
    //   7523: goto -170 -> 7353
    //   7526: aload 20
    //   7528: astore 30
    //   7530: aload 21
    //   7532: astore 25
    //   7534: aload 23
    //   7536: astore 27
    //   7538: aload 20
    //   7540: astore 24
    //   7542: aload 21
    //   7544: astore 26
    //   7546: aload 23
    //   7548: astore 28
    //   7550: aload 21
    //   7552: astore 31
    //   7554: aload 23
    //   7556: astore 29
    //   7558: aload 33
    //   7560: iload 7
    //   7562: putfield 281	com/tencent/tencentmap/mapsdk/a/fc:a	I
    //   7565: goto -3290 -> 4275
    //   7568: iload 5
    //   7570: iconst_1
    //   7571: iadd
    //   7572: istore_3
    //   7573: iload_3
    //   7574: bipush 6
    //   7576: if_icmple +468 -> 8044
    //   7579: iconst_0
    //   7580: istore_3
    //   7581: aload 33
    //   7583: bipush -5
    //   7585: putfield 281	com/tencent/tencentmap/mapsdk/a/fc:a	I
    //   7588: iload 4
    //   7590: iconst_1
    //   7591: iadd
    //   7592: istore 4
    //   7594: goto -3263 -> 4331
    //   7597: aload 39
    //   7599: lconst_0
    //   7600: putfield 474	com/tencent/tencentmap/mapsdk/a/fd:n	J
    //   7603: goto -3168 -> 4435
    //   7606: aload 22
    //   7608: instanceof 633
    //   7611: ifeq +9 -> 7620
    //   7614: bipush -11
    //   7616: istore_2
    //   7617: goto -6105 -> 1512
    //   7620: aload 22
    //   7622: instanceof 635
    //   7625: ifeq +9 -> 7634
    //   7628: bipush -13
    //   7630: istore_2
    //   7631: goto -6119 -> 1512
    //   7634: aload 22
    //   7636: instanceof 637
    //   7639: ifeq +9 -> 7648
    //   7642: bipush -14
    //   7644: istore_2
    //   7645: goto -6133 -> 1512
    //   7648: aload 22
    //   7650: instanceof 639
    //   7653: ifeq +9 -> 7662
    //   7656: bipush -15
    //   7658: istore_2
    //   7659: goto -6147 -> 1512
    //   7662: aload 22
    //   7664: instanceof 641
    //   7667: ifeq +9 -> 7676
    //   7670: bipush -16
    //   7672: istore_2
    //   7673: goto -6161 -> 1512
    //   7676: aload 22
    //   7678: instanceof 643
    //   7681: ifeq +9 -> 7690
    //   7684: bipush -22
    //   7686: istore_2
    //   7687: goto -6175 -> 1512
    //   7690: aload 22
    //   7692: instanceof 645
    //   7695: ifeq +9 -> 7704
    //   7698: bipush -12
    //   7700: istore_2
    //   7701: goto -6189 -> 1512
    //   7704: aload 22
    //   7706: instanceof 647
    //   7709: istore 15
    //   7711: iload 15
    //   7713: ifeq +9 -> 7722
    //   7716: bipush -24
    //   7718: istore_2
    //   7719: goto -6207 -> 1512
    //   7722: bipush -3
    //   7724: istore_2
    //   7725: goto -6213 -> 1512
    //   7728: bipush -4
    //   7730: istore_2
    //   7731: goto -6219 -> 1512
    //   7734: iload 5
    //   7736: iconst_1
    //   7737: iadd
    //   7738: istore 5
    //   7740: iload 5
    //   7742: istore_2
    //   7743: iload 4
    //   7745: istore_3
    //   7746: iload 5
    //   7748: bipush 6
    //   7750: if_icmple -6156 -> 1594
    //   7753: iload 4
    //   7755: iconst_1
    //   7756: iadd
    //   7757: istore_3
    //   7758: iconst_0
    //   7759: istore_2
    //   7760: aload 33
    //   7762: bipush -5
    //   7764: putfield 281	com/tencent/tencentmap/mapsdk/a/fc:a	I
    //   7767: goto -6173 -> 1594
    //   7770: aload 39
    //   7772: lconst_0
    //   7773: putfield 474	com/tencent/tencentmap/mapsdk/a/fd:n	J
    //   7776: goto -6078 -> 1698
    //   7779: iload 5
    //   7781: iconst_1
    //   7782: iadd
    //   7783: istore 6
    //   7785: iload 6
    //   7787: istore_2
    //   7788: iload 4
    //   7790: istore 5
    //   7792: iload 6
    //   7794: bipush 6
    //   7796: if_icmple -5541 -> 2255
    //   7799: iload 4
    //   7801: iconst_1
    //   7802: iadd
    //   7803: istore 5
    //   7805: iconst_0
    //   7806: istore_2
    //   7807: aload 33
    //   7809: bipush -5
    //   7811: putfield 281	com/tencent/tencentmap/mapsdk/a/fc:a	I
    //   7814: goto -5559 -> 2255
    //   7817: aload 39
    //   7819: lconst_0
    //   7820: putfield 474	com/tencent/tencentmap/mapsdk/a/fd:n	J
    //   7823: goto -5464 -> 2359
    //   7826: aload 39
    //   7828: lconst_0
    //   7829: putfield 474	com/tencent/tencentmap/mapsdk/a/fd:n	J
    //   7832: goto -4695 -> 3137
    //   7835: aload_1
    //   7836: invokevirtual 269	com/tencent/tencentmap/mapsdk/a/fb:l	()Z
    //   7839: ifeq -7706 -> 133
    //   7842: new 241	com/tencent/tencentmap/mapsdk/a/fc
    //   7845: dup
    //   7846: invokespecial 242	com/tencent/tencentmap/mapsdk/a/fc:<init>	()V
    //   7849: astore_1
    //   7850: aload_1
    //   7851: bipush -20
    //   7853: putfield 281	com/tencent/tencentmap/mapsdk/a/fc:a	I
    //   7856: aload_1
    //   7857: areturn
    //   7858: astore 22
    //   7860: goto -3104 -> 4756
    //   7863: astore 22
    //   7865: goto -2228 -> 5637
    //   7868: astore 22
    //   7870: goto -2642 -> 5228
    //   7873: astore 20
    //   7875: goto -4638 -> 3237
    //   7878: astore 22
    //   7880: iconst_1
    //   7881: istore 13
    //   7883: goto -4914 -> 2969
    //   7886: astore 22
    //   7888: aload 26
    //   7890: astore 20
    //   7892: aload 25
    //   7894: astore 21
    //   7896: aload 24
    //   7898: astore 23
    //   7900: goto -4931 -> 2969
    //   7903: astore 22
    //   7905: aconst_null
    //   7906: astore 20
    //   7908: goto -4939 -> 2969
    //   7911: astore 22
    //   7913: goto -4944 -> 2969
    //   7916: astore 22
    //   7918: goto -5459 -> 2459
    //   7921: astore 20
    //   7923: iconst_1
    //   7924: istore 14
    //   7926: aload 22
    //   7928: astore 20
    //   7930: iload_2
    //   7931: istore_3
    //   7932: goto -5733 -> 2199
    //   7935: astore 21
    //   7937: iload 6
    //   7939: istore_3
    //   7940: aload 22
    //   7942: astore 21
    //   7944: aload 28
    //   7946: astore 23
    //   7948: goto -5749 -> 2199
    //   7951: astore 22
    //   7953: goto -6155 -> 1798
    //   7956: astore 22
    //   7958: iload_2
    //   7959: istore 7
    //   7961: aload 31
    //   7963: astore 21
    //   7965: aload 29
    //   7967: astore 23
    //   7969: goto -6538 -> 1431
    //   7972: astore 22
    //   7974: iconst_1
    //   7975: istore 14
    //   7977: aload 27
    //   7979: astore 20
    //   7981: iload_2
    //   7982: istore 7
    //   7984: iload 6
    //   7986: istore_3
    //   7987: goto -6556 -> 1431
    //   7990: astore 23
    //   7992: iconst_2
    //   7993: istore_3
    //   7994: aload 22
    //   7996: astore 21
    //   7998: aload 23
    //   8000: astore 22
    //   8002: aload 27
    //   8004: astore 23
    //   8006: goto -6575 -> 1431
    //   8009: astore 22
    //   8011: goto -3476 -> 4535
    //   8014: astore 20
    //   8016: goto -563 -> 7453
    //   8019: astore 20
    //   8021: goto -908 -> 7113
    //   8024: astore 20
    //   8026: goto -1697 -> 6329
    //   8029: astore 20
    //   8031: goto -2516 -> 5515
    //   8034: astore 20
    //   8036: goto -2101 -> 5935
    //   8039: astore 20
    //   8041: goto -2976 -> 5065
    //   8044: goto -3713 -> 4331
    //   8047: goto -3772 -> 4275
    //   8050: iload 15
    //   8052: istore 13
    //   8054: goto -3779 -> 4275
    //   8057: goto -3821 -> 4236
    // Local variable table:
    //   start	length	slot	name	signature
    //   0	8060	0	this	ez
    //   0	8060	1	paramfb	fb
    //   226	7756	2	i	int
    //   74	7920	3	j	int
    //   52	7751	4	k	int
    //   81	7723	5	m	int
    //   248	7737	6	n	int
    //   251	7732	7	i1	int
    //   40	192	8	i2	int
    //   49	177	9	i3	int
    //   71	100	10	i4	int
    //   4688	975	11	i5	int
    //   4731	13	12	i6	int
    //   207	7846	13	bool1	boolean
    //   60	7916	14	bool2	boolean
    //   4659	3392	15	bool3	boolean
    //   99	7372	16	l1	long
    //   3732	1419	18	l2	long
    //   57	2101	20	localObject1	Object
    //   2183	1	20	localThrowable1	Throwable
    //   2187	5352	20	localObject2	Object
    //   7873	1	20	localThrowable2	Throwable
    //   7890	17	20	localObject3	Object
    //   7921	1	20	localThrowable3	Throwable
    //   7928	52	20	localObject4	Object
    //   8014	1	20	localThrowable4	Throwable
    //   8019	1	20	localThrowable5	Throwable
    //   8024	1	20	localThrowable6	Throwable
    //   8029	1	20	localThrowable7	Throwable
    //   8034	1	20	localThrowable8	Throwable
    //   8039	1	20	localThrowable9	Throwable
    //   693	7202	21	localObject5	Object
    //   7935	1	21	localThrowable10	Throwable
    //   7942	55	21	localObject6	Object
    //   78	1305	22	str1	String
    //   1414	88	22	localException1	Exception
    //   1867	1057	22	localObject7	Object
    //   2955	1116	22	localObject8	Object
    //   4603	621	22	localObject9	Object
    //   5619	407	22	localException2	Exception
    //   6042	1	22	localThrowable11	Throwable
    //   6498	1207	22	localObject10	Object
    //   7858	1	22	localException3	Exception
    //   7863	1	22	localException4	Exception
    //   7868	1	22	localException5	Exception
    //   7878	1	22	localObject11	Object
    //   7886	1	22	localObject12	Object
    //   7903	1	22	localObject13	Object
    //   7911	1	22	localObject14	Object
    //   7916	25	22	localThrowable12	Throwable
    //   7951	1	22	localThrowable13	Throwable
    //   7956	1	22	localException6	Exception
    //   7972	23	22	localException7	Exception
    //   8000	1	22	localException8	Exception
    //   8009	1	22	localThrowable14	Throwable
    //   7	7961	23	localObject15	Object
    //   7990	9	23	localException9	Exception
    //   8004	1	23	localObject16	Object
    //   245	4475	24	localObject17	Object
    //   4749	845	24	localOutOfMemoryError1	OutOfMemoryError
    //   5630	1	24	localOutOfMemoryError2	OutOfMemoryError
    //   6416	1481	24	localObject18	Object
    //   241	7652	25	localObject19	Object
    //   237	7652	26	localObject20	Object
    //   186	7817	27	localObject21	Object
    //   192	7753	28	localObject22	Object
    //   198	7768	29	localObject23	Object
    //   717	6812	30	localObject24	Object
    //   860	7102	31	localObject25	Object
    //   852	5704	32	localObject26	Object
    //   143	7665	33	localfc	fc
    //   346	6199	34	localObject27	Object
    //   201	3433	35	localObject28	Object
    //   204	3352	36	localObject29	Object
    //   189	3425	37	localObject30	Object
    //   195	3431	38	localObject31	Object
    //   159	7668	39	localfd	fd
    //   17	161	40	localey	ey
    //   24	494	41	localList	java.util.List
    //   31	133	42	str2	String
    //   1249	1632	43	localIterator	java.util.Iterator
    //   1349	1589	44	str3	String
    // Exception table:
    //   from	to	target	type
    //   889	946	1414	java/lang/Exception
    //   985	992	1414	java/lang/Exception
    //   1031	1042	1414	java/lang/Exception
    //   1081	1094	1414	java/lang/Exception
    //   1133	1139	1414	java/lang/Exception
    //   1183	1193	1414	java/lang/Exception
    //   1237	1251	1414	java/lang/Exception
    //   1290	1300	1414	java/lang/Exception
    //   1339	1351	1414	java/lang/Exception
    //   1390	1411	1414	java/lang/Exception
    //   2169	2180	1414	java/lang/Exception
    //   2577	2583	1414	java/lang/Exception
    //   2628	2642	1414	java/lang/Exception
    //   2681	2734	1414	java/lang/Exception
    //   2778	2792	1414	java/lang/Exception
    //   2831	2841	1414	java/lang/Exception
    //   2880	2892	1414	java/lang/Exception
    //   2931	2952	1414	java/lang/Exception
    //   3340	3346	1414	java/lang/Exception
    //   3391	3406	1414	java/lang/Exception
    //   3445	3452	1414	java/lang/Exception
    //   3491	3497	1414	java/lang/Exception
    //   3541	3547	1414	java/lang/Exception
    //   3586	3603	1414	java/lang/Exception
    //   6484	6496	1414	java/lang/Exception
    //   6544	6553	1414	java/lang/Exception
    //   6592	6616	1414	java/lang/Exception
    //   889	946	2183	java/lang/Throwable
    //   985	992	2183	java/lang/Throwable
    //   1031	1042	2183	java/lang/Throwable
    //   1081	1094	2183	java/lang/Throwable
    //   1133	1139	2183	java/lang/Throwable
    //   1183	1193	2183	java/lang/Throwable
    //   1237	1251	2183	java/lang/Throwable
    //   1290	1300	2183	java/lang/Throwable
    //   1339	1351	2183	java/lang/Throwable
    //   1390	1411	2183	java/lang/Throwable
    //   2169	2180	2183	java/lang/Throwable
    //   2577	2583	2183	java/lang/Throwable
    //   2628	2642	2183	java/lang/Throwable
    //   2681	2734	2183	java/lang/Throwable
    //   2778	2792	2183	java/lang/Throwable
    //   2831	2841	2183	java/lang/Throwable
    //   2880	2892	2183	java/lang/Throwable
    //   2931	2952	2183	java/lang/Throwable
    //   3340	3346	2183	java/lang/Throwable
    //   3391	3406	2183	java/lang/Throwable
    //   3445	3452	2183	java/lang/Throwable
    //   3491	3497	2183	java/lang/Throwable
    //   3541	3547	2183	java/lang/Throwable
    //   3586	3603	2183	java/lang/Throwable
    //   3637	3644	2183	java/lang/Throwable
    //   3682	3694	2183	java/lang/Throwable
    //   3729	3734	2183	java/lang/Throwable
    //   3769	3778	2183	java/lang/Throwable
    //   3813	3825	2183	java/lang/Throwable
    //   3864	3891	2183	java/lang/Throwable
    //   3926	3940	2183	java/lang/Throwable
    //   3975	3982	2183	java/lang/Throwable
    //   4030	4043	2183	java/lang/Throwable
    //   4078	4095	2183	java/lang/Throwable
    //   4130	4140	2183	java/lang/Throwable
    //   4268	4275	2183	java/lang/Throwable
    //   4644	4658	2183	java/lang/Throwable
    //   6434	6441	2183	java/lang/Throwable
    //   6484	6496	2183	java/lang/Throwable
    //   6544	6553	2183	java/lang/Throwable
    //   6592	6616	2183	java/lang/Throwable
    //   7558	7565	2183	java/lang/Throwable
    //   889	946	2955	finally
    //   985	992	2955	finally
    //   1031	1042	2955	finally
    //   1081	1094	2955	finally
    //   1133	1139	2955	finally
    //   1183	1193	2955	finally
    //   1237	1251	2955	finally
    //   1290	1300	2955	finally
    //   1339	1351	2955	finally
    //   1390	1411	2955	finally
    //   2169	2180	2955	finally
    //   2577	2583	2955	finally
    //   2628	2642	2955	finally
    //   2681	2734	2955	finally
    //   2778	2792	2955	finally
    //   2831	2841	2955	finally
    //   2880	2892	2955	finally
    //   2931	2952	2955	finally
    //   3340	3346	2955	finally
    //   3391	3406	2955	finally
    //   3445	3452	2955	finally
    //   3491	3497	2955	finally
    //   3541	3547	2955	finally
    //   3586	3603	2955	finally
    //   3637	3644	2955	finally
    //   3682	3694	2955	finally
    //   3729	3734	2955	finally
    //   3769	3778	2955	finally
    //   3813	3825	2955	finally
    //   3864	3891	2955	finally
    //   3926	3940	2955	finally
    //   3975	3982	2955	finally
    //   4030	4043	2955	finally
    //   4078	4095	2955	finally
    //   4130	4140	2955	finally
    //   4268	4275	2955	finally
    //   4644	4658	2955	finally
    //   6434	6441	2955	finally
    //   6484	6496	2955	finally
    //   6544	6553	2955	finally
    //   6592	6616	2955	finally
    //   7558	7565	2955	finally
    //   4693	4699	4749	java/lang/OutOfMemoryError
    //   4671	4678	5619	java/lang/Exception
    //   4684	4690	5619	java/lang/Exception
    //   4693	4699	5619	java/lang/Exception
    //   4702	4707	5619	java/lang/Exception
    //   4717	4733	5619	java/lang/Exception
    //   4759	4766	5619	java/lang/Exception
    //   4769	4792	5619	java/lang/Exception
    //   4795	4803	5619	java/lang/Exception
    //   5145	5157	5619	java/lang/Exception
    //   5160	5170	5619	java/lang/Exception
    //   5173	5181	5619	java/lang/Exception
    //   5191	5214	5619	java/lang/Exception
    //   5217	5223	5619	java/lang/Exception
    //   5231	5239	5619	java/lang/Exception
    //   5242	5248	5619	java/lang/Exception
    //   5581	5590	5619	java/lang/Exception
    //   5593	5607	5619	java/lang/Exception
    //   5610	5616	5619	java/lang/Exception
    //   5640	5647	5619	java/lang/Exception
    //   5650	5673	5619	java/lang/Exception
    //   6011	6020	5619	java/lang/Exception
    //   6023	6030	5619	java/lang/Exception
    //   6033	6039	5619	java/lang/Exception
    //   6061	6067	5619	java/lang/Exception
    //   5581	5590	5630	java/lang/OutOfMemoryError
    //   4671	4678	6042	java/lang/Throwable
    //   4684	4690	6042	java/lang/Throwable
    //   4693	4699	6042	java/lang/Throwable
    //   4702	4707	6042	java/lang/Throwable
    //   4717	4733	6042	java/lang/Throwable
    //   4751	4756	6042	java/lang/Throwable
    //   4759	4766	6042	java/lang/Throwable
    //   4769	4792	6042	java/lang/Throwable
    //   4795	4803	6042	java/lang/Throwable
    //   5145	5157	6042	java/lang/Throwable
    //   5160	5170	6042	java/lang/Throwable
    //   5173	5181	6042	java/lang/Throwable
    //   5191	5214	6042	java/lang/Throwable
    //   5217	5223	6042	java/lang/Throwable
    //   5223	5228	6042	java/lang/Throwable
    //   5231	5239	6042	java/lang/Throwable
    //   5242	5248	6042	java/lang/Throwable
    //   5581	5590	6042	java/lang/Throwable
    //   5593	5607	6042	java/lang/Throwable
    //   5610	5616	6042	java/lang/Throwable
    //   5632	5637	6042	java/lang/Throwable
    //   5640	5647	6042	java/lang/Throwable
    //   5650	5673	6042	java/lang/Throwable
    //   6011	6020	6042	java/lang/Throwable
    //   6023	6030	6042	java/lang/Throwable
    //   6033	6039	6042	java/lang/Throwable
    //   6061	6067	6042	java/lang/Throwable
    //   4751	4756	7858	java/lang/Exception
    //   5632	5637	7863	java/lang/Exception
    //   5223	5228	7868	java/lang/Exception
    //   3172	3237	7873	java/lang/Throwable
    //   4671	4678	7878	finally
    //   4684	4690	7878	finally
    //   4693	4699	7878	finally
    //   4702	4707	7878	finally
    //   4717	4733	7878	finally
    //   4751	4756	7878	finally
    //   4759	4766	7878	finally
    //   4769	4792	7878	finally
    //   4795	4803	7878	finally
    //   5145	5157	7878	finally
    //   5160	5170	7878	finally
    //   5173	5181	7878	finally
    //   5191	5214	7878	finally
    //   5217	5223	7878	finally
    //   5223	5228	7878	finally
    //   5231	5239	7878	finally
    //   5242	5248	7878	finally
    //   5581	5590	7878	finally
    //   5593	5607	7878	finally
    //   5610	5616	7878	finally
    //   5632	5637	7878	finally
    //   5640	5647	7878	finally
    //   5650	5673	7878	finally
    //   6011	6020	7878	finally
    //   6023	6030	7878	finally
    //   6033	6039	7878	finally
    //   6061	6067	7878	finally
    //   253	259	7886	finally
    //   277	288	7886	finally
    //   306	317	7886	finally
    //   335	348	7886	finally
    //   366	373	7886	finally
    //   391	400	7886	finally
    //   418	427	7886	finally
    //   445	454	7886	finally
    //   472	489	7886	finally
    //   515	536	7886	finally
    //   556	562	7886	finally
    //   580	588	7886	finally
    //   606	613	7886	finally
    //   631	640	7886	finally
    //   658	695	7886	finally
    //   713	719	7886	finally
    //   741	749	7886	finally
    //   767	778	7886	finally
    //   796	818	7886	finally
    //   836	843	7886	finally
    //   1897	1920	7886	finally
    //   1941	1950	7886	finally
    //   1968	1996	7886	finally
    //   2017	2039	7886	finally
    //   2060	2088	7886	finally
    //   2109	2116	7886	finally
    //   6647	6653	7886	finally
    //   6673	6680	7886	finally
    //   6724	6731	7886	finally
    //   6751	6760	7886	finally
    //   6780	6787	7886	finally
    //   6807	6814	7886	finally
    //   6834	6840	7886	finally
    //   6694	6701	7903	finally
    //   1431	1509	7911	finally
    //   1512	1539	7911	finally
    //   7606	7614	7911	finally
    //   7620	7628	7911	finally
    //   7634	7642	7911	finally
    //   7648	7656	7911	finally
    //   7662	7670	7911	finally
    //   7676	7684	7911	finally
    //   7690	7698	7911	finally
    //   7704	7711	7911	finally
    //   2394	2459	7916	java/lang/Throwable
    //   6647	6653	7921	java/lang/Throwable
    //   6673	6680	7921	java/lang/Throwable
    //   6694	6701	7921	java/lang/Throwable
    //   6724	6731	7921	java/lang/Throwable
    //   6751	6760	7921	java/lang/Throwable
    //   6780	6787	7921	java/lang/Throwable
    //   6807	6814	7921	java/lang/Throwable
    //   6834	6840	7921	java/lang/Throwable
    //   253	259	7935	java/lang/Throwable
    //   277	288	7935	java/lang/Throwable
    //   306	317	7935	java/lang/Throwable
    //   335	348	7935	java/lang/Throwable
    //   366	373	7935	java/lang/Throwable
    //   391	400	7935	java/lang/Throwable
    //   418	427	7935	java/lang/Throwable
    //   445	454	7935	java/lang/Throwable
    //   472	489	7935	java/lang/Throwable
    //   515	536	7935	java/lang/Throwable
    //   556	562	7935	java/lang/Throwable
    //   580	588	7935	java/lang/Throwable
    //   606	613	7935	java/lang/Throwable
    //   631	640	7935	java/lang/Throwable
    //   658	695	7935	java/lang/Throwable
    //   713	719	7935	java/lang/Throwable
    //   741	749	7935	java/lang/Throwable
    //   767	778	7935	java/lang/Throwable
    //   796	818	7935	java/lang/Throwable
    //   836	843	7935	java/lang/Throwable
    //   1897	1920	7935	java/lang/Throwable
    //   1941	1950	7935	java/lang/Throwable
    //   1968	1996	7935	java/lang/Throwable
    //   2017	2039	7935	java/lang/Throwable
    //   2060	2088	7935	java/lang/Throwable
    //   2109	2116	7935	java/lang/Throwable
    //   1733	1798	7951	java/lang/Throwable
    //   3637	3644	7956	java/lang/Exception
    //   3682	3694	7956	java/lang/Exception
    //   3729	3734	7956	java/lang/Exception
    //   3769	3778	7956	java/lang/Exception
    //   3813	3825	7956	java/lang/Exception
    //   3864	3891	7956	java/lang/Exception
    //   3926	3940	7956	java/lang/Exception
    //   3975	3982	7956	java/lang/Exception
    //   4030	4043	7956	java/lang/Exception
    //   4078	4095	7956	java/lang/Exception
    //   4130	4140	7956	java/lang/Exception
    //   4268	4275	7956	java/lang/Exception
    //   4644	4658	7956	java/lang/Exception
    //   6434	6441	7956	java/lang/Exception
    //   7558	7565	7956	java/lang/Exception
    //   6647	6653	7972	java/lang/Exception
    //   6673	6680	7972	java/lang/Exception
    //   6694	6701	7972	java/lang/Exception
    //   6724	6731	7972	java/lang/Exception
    //   6751	6760	7972	java/lang/Exception
    //   6780	6787	7972	java/lang/Exception
    //   6807	6814	7972	java/lang/Exception
    //   6834	6840	7972	java/lang/Exception
    //   253	259	7990	java/lang/Exception
    //   277	288	7990	java/lang/Exception
    //   306	317	7990	java/lang/Exception
    //   335	348	7990	java/lang/Exception
    //   366	373	7990	java/lang/Exception
    //   391	400	7990	java/lang/Exception
    //   418	427	7990	java/lang/Exception
    //   445	454	7990	java/lang/Exception
    //   472	489	7990	java/lang/Exception
    //   515	536	7990	java/lang/Exception
    //   556	562	7990	java/lang/Exception
    //   580	588	7990	java/lang/Exception
    //   606	613	7990	java/lang/Exception
    //   631	640	7990	java/lang/Exception
    //   658	695	7990	java/lang/Exception
    //   713	719	7990	java/lang/Exception
    //   741	749	7990	java/lang/Exception
    //   767	778	7990	java/lang/Exception
    //   796	818	7990	java/lang/Exception
    //   836	843	7990	java/lang/Exception
    //   1897	1920	7990	java/lang/Exception
    //   1941	1950	7990	java/lang/Exception
    //   1968	1996	7990	java/lang/Exception
    //   2017	2039	7990	java/lang/Exception
    //   2060	2088	7990	java/lang/Exception
    //   2109	2116	7990	java/lang/Exception
    //   4470	4535	8009	java/lang/Throwable
    //   7388	7453	8014	java/lang/Throwable
    //   7048	7113	8019	java/lang/Throwable
    //   6264	6329	8024	java/lang/Throwable
    //   5450	5515	8029	java/lang/Throwable
    //   5870	5935	8034	java/lang/Throwable
    //   5000	5065	8039	java/lang/Throwable
  }
  
  public final ew a(String paramString)
  {
    return a(true, paramString, null);
  }
  
  public final ew a(String paramString, byte[] paramArrayOfByte)
  {
    return a(false, paramString, paramArrayOfByte);
  }
  
  public final ex a(ew paramew)
  {
    try
    {
      fb localfb = (fb)paramew;
      localfb.a(System.currentTimeMillis());
      fx.b("REQUEST_TAG", "doRequest... key:" + paramew.a());
      fc localfc = b(localfb);
      long l1 = System.currentTimeMillis();
      long l2 = localfb.q();
      fx.b("REQUEST_TAG", "endRequest... key:" + paramew.a() + "costTime: " + (l1 - l2));
      return localfc;
    }
    catch (Throwable paramew)
    {
      paramew = new fc();
      paramew.a = -19;
    }
    return paramew;
  }
}


/* Location:              /Users/Han/Desktop/wxall// 6.6.7/dex2jar-2.0/classes3-dex2jar.jar!/com/tencent/tencentmap/mapsdk/a/ez.class
 * Java compiler version: 6 (50.0)
 * JD-Core Version:       0.7.1
 */