package com.tencent.tencentmap.mapsdk.a;

public final class fo
{
  public static dw a;
  
  /* Error */
  public static boolean a(String paramString, boolean paramBoolean1, long paramLong1, long paramLong2, java.util.Map paramMap, boolean paramBoolean2)
  {
    // Byte code:
    //   0: aload_0
    //   1: iconst_1
    //   2: lconst_0
    //   3: lconst_0
    //   4: aload 6
    //   6: iconst_1
    //   7: invokestatic 14	com/tencent/beacon/event/UserAction:onUserAction	(Ljava/lang/String;ZJJLjava/util/Map;Z)Z
    //   10: istore_1
    //   11: ldc 16
    //   13: new 18	java/lang/StringBuilder
    //   16: dup
    //   17: ldc 20
    //   19: invokespecial 24	java/lang/StringBuilder:<init>	(Ljava/lang/String;)V
    //   22: aload_0
    //   23: invokevirtual 28	java/lang/StringBuilder:append	(Ljava/lang/String;)Ljava/lang/StringBuilder;
    //   26: ldc 30
    //   28: invokevirtual 28	java/lang/StringBuilder:append	(Ljava/lang/String;)Ljava/lang/StringBuilder;
    //   31: iload_1
    //   32: invokevirtual 33	java/lang/StringBuilder:append	(Z)Ljava/lang/StringBuilder;
    //   35: invokevirtual 37	java/lang/StringBuilder:toString	()Ljava/lang/String;
    //   38: invokestatic 43	com/tencent/tencentmap/mapsdk/a/fx:c	(Ljava/lang/String;Ljava/lang/String;)V
    //   41: iload_1
    //   42: istore 8
    //   44: iload_1
    //   45: ifne +70 -> 115
    //   48: iload_1
    //   49: istore 8
    //   51: iload_1
    //   52: istore 7
    //   54: getstatic 45	com/tencent/tencentmap/mapsdk/a/fo:a	Lcom/tencent/tencentmap/mapsdk/a/dw;
    //   57: ifnull +58 -> 115
    //   60: iload_1
    //   61: istore 7
    //   63: getstatic 45	com/tencent/tencentmap/mapsdk/a/fo:a	Lcom/tencent/tencentmap/mapsdk/a/dw;
    //   66: aload_0
    //   67: iconst_1
    //   68: lconst_0
    //   69: lconst_0
    //   70: aload 6
    //   72: iconst_1
    //   73: invokeinterface 49 9 0
    //   78: istore 8
    //   80: iload 8
    //   82: istore 7
    //   84: ldc 16
    //   86: new 18	java/lang/StringBuilder
    //   89: dup
    //   90: ldc 51
    //   92: invokespecial 24	java/lang/StringBuilder:<init>	(Ljava/lang/String;)V
    //   95: aload_0
    //   96: invokevirtual 28	java/lang/StringBuilder:append	(Ljava/lang/String;)Ljava/lang/StringBuilder;
    //   99: ldc 30
    //   101: invokevirtual 28	java/lang/StringBuilder:append	(Ljava/lang/String;)Ljava/lang/StringBuilder;
    //   104: iload 8
    //   106: invokevirtual 33	java/lang/StringBuilder:append	(Z)Ljava/lang/StringBuilder;
    //   109: invokevirtual 37	java/lang/StringBuilder:toString	()Ljava/lang/String;
    //   112: invokestatic 43	com/tencent/tencentmap/mapsdk/a/fx:c	(Ljava/lang/String;Ljava/lang/String;)V
    //   115: iload 8
    //   117: ireturn
    //   118: astore_0
    //   119: iload 7
    //   121: ireturn
    //   122: astore 9
    //   124: iconst_0
    //   125: istore_1
    //   126: goto -85 -> 41
    //   129: astore 9
    //   131: goto -90 -> 41
    // Local variable table:
    //   start	length	slot	name	signature
    //   0	134	0	paramString	String
    //   0	134	1	paramBoolean1	boolean
    //   0	134	2	paramLong1	long
    //   0	134	4	paramLong2	long
    //   0	134	6	paramMap	java.util.Map
    //   0	134	7	paramBoolean2	boolean
    //   42	74	8	bool	boolean
    //   122	1	9	localThrowable1	Throwable
    //   129	1	9	localThrowable2	Throwable
    // Exception table:
    //   from	to	target	type
    //   54	60	118	java/lang/Throwable
    //   63	80	118	java/lang/Throwable
    //   84	115	118	java/lang/Throwable
    //   0	11	122	java/lang/Throwable
    //   11	41	129	java/lang/Throwable
  }
}


/* Location:              /Users/Han/Desktop/wxall/微信反编译/反编译 6.6.7/dex2jar-2.0/classes3-dex2jar.jar!/com/tencent/tencentmap/mapsdk/a/fo.class
 * Java compiler version: 6 (50.0)
 * JD-Core Version:       0.7.1
 */