package com.tencent.mm.plugin.music.b.a;

public final class f
{
  public int lAe = 4;
  
  /* Error */
  public final boolean biA()
  {
    // Byte code:
    //   0: aload_0
    //   1: monitorenter
    //   2: aload_0
    //   3: getfield 12	com/tencent/mm/plugin/music/b/a/f:lAe	I
    //   6: istore_1
    //   7: iload_1
    //   8: iconst_2
    //   9: if_icmpne +9 -> 18
    //   12: iconst_1
    //   13: istore_2
    //   14: aload_0
    //   15: monitorexit
    //   16: iload_2
    //   17: ireturn
    //   18: iconst_0
    //   19: istore_2
    //   20: goto -6 -> 14
    //   23: astore_3
    //   24: aload_0
    //   25: monitorexit
    //   26: aload_3
    //   27: athrow
    // Local variable table:
    //   start	length	slot	name	signature
    //   0	28	0	this	f
    //   6	4	1	i	int
    //   13	7	2	bool	boolean
    //   23	4	3	localObject	Object
    // Exception table:
    //   from	to	target	type
    //   2	7	23	finally
  }
  
  /* Error */
  public final boolean isPlaying()
  {
    // Byte code:
    //   0: aload_0
    //   1: monitorenter
    //   2: aload_0
    //   3: getfield 12	com/tencent/mm/plugin/music/b/a/f:lAe	I
    //   6: istore_1
    //   7: iload_1
    //   8: iconst_3
    //   9: if_icmpne +9 -> 18
    //   12: iconst_1
    //   13: istore_2
    //   14: aload_0
    //   15: monitorexit
    //   16: iload_2
    //   17: ireturn
    //   18: iconst_0
    //   19: istore_2
    //   20: goto -6 -> 14
    //   23: astore_3
    //   24: aload_0
    //   25: monitorexit
    //   26: aload_3
    //   27: athrow
    // Local variable table:
    //   start	length	slot	name	signature
    //   0	28	0	this	f
    //   6	4	1	i	int
    //   13	7	2	bool	boolean
    //   23	4	3	localObject	Object
    // Exception table:
    //   from	to	target	type
    //   2	7	23	finally
  }
}


/* Location:              /Users/Han/Desktop/wxall/微信反编译/反编译 6.6.7/dex2jar-2.0/classes5-dex2jar.jar!/com/tencent/mm/plugin/music/b/a/f.class
 * Java compiler version: 6 (50.0)
 * JD-Core Version:       0.7.1
 */